package com.google.android.apps.youtube.api.service.jar;

import android.os.IBinder;
import android.os.Parcel;
import java.util.List;

class IApiPlayerService$Stub$Proxy
  implements IApiPlayerService
{
  private IBinder a;
  
  IApiPlayerService$Stub$Proxy(IBinder paramIBinder)
  {
    a = paramIBinder;
  }
  
  public final void a(int paramInt)
  {
    Parcel localParcel1 = Parcel.obtain();
    Parcel localParcel2 = Parcel.obtain();
    try
    {
      localParcel1.writeInterfaceToken("com.google.android.apps.youtube.api.service.jar.IApiPlayerService");
      localParcel1.writeInt(paramInt);
      a.transact(14, localParcel1, localParcel2, 0);
      localParcel2.readException();
      return;
    }
    finally
    {
      localParcel2.recycle();
      localParcel1.recycle();
    }
  }
  
  /* Error */
  public final void a(int paramInt, android.view.KeyEvent paramKeyEvent)
  {
    // Byte code:
    //   0: invokestatic 23	android/os/Parcel:obtain	()Landroid/os/Parcel;
    //   3: astore_3
    //   4: invokestatic 23	android/os/Parcel:obtain	()Landroid/os/Parcel;
    //   7: astore 4
    //   9: aload_3
    //   10: ldc 25
    //   12: invokevirtual 29	android/os/Parcel:writeInterfaceToken	(Ljava/lang/String;)V
    //   15: aload_3
    //   16: iload_1
    //   17: invokevirtual 32	android/os/Parcel:writeInt	(I)V
    //   20: aload_2
    //   21: ifnull +45 -> 66
    //   24: aload_3
    //   25: iconst_1
    //   26: invokevirtual 32	android/os/Parcel:writeInt	(I)V
    //   29: aload_2
    //   30: aload_3
    //   31: iconst_0
    //   32: invokevirtual 51	android/view/KeyEvent:writeToParcel	(Landroid/os/Parcel;I)V
    //   35: aload_0
    //   36: getfield 15	com/google/android/apps/youtube/api/service/jar/IApiPlayerService$Stub$Proxy:a	Landroid/os/IBinder;
    //   39: bipush 22
    //   41: aload_3
    //   42: aload 4
    //   44: iconst_0
    //   45: invokeinterface 38 5 0
    //   50: pop
    //   51: aload 4
    //   53: invokevirtual 41	android/os/Parcel:readException	()V
    //   56: aload 4
    //   58: invokevirtual 44	android/os/Parcel:recycle	()V
    //   61: aload_3
    //   62: invokevirtual 44	android/os/Parcel:recycle	()V
    //   65: return
    //   66: aload_3
    //   67: iconst_0
    //   68: invokevirtual 32	android/os/Parcel:writeInt	(I)V
    //   71: goto -36 -> 35
    //   74: astore_2
    //   75: aload 4
    //   77: invokevirtual 44	android/os/Parcel:recycle	()V
    //   80: aload_3
    //   81: invokevirtual 44	android/os/Parcel:recycle	()V
    //   84: aload_2
    //   85: athrow
    // Local variable table:
    //   start	length	slot	name	signature
    //   0	86	0	this	Proxy
    //   0	86	1	paramInt	int
    //   0	86	2	paramKeyEvent	android.view.KeyEvent
    //   3	78	3	localParcel1	Parcel
    //   7	69	4	localParcel2	Parcel
    // Exception table:
    //   from	to	target	type
    //   9	20	74	finally
    //   24	35	74	finally
    //   35	56	74	finally
    //   66	71	74	finally
  }
  
  public final void a(String paramString, int paramInt)
  {
    Parcel localParcel1 = Parcel.obtain();
    Parcel localParcel2 = Parcel.obtain();
    try
    {
      localParcel1.writeInterfaceToken("com.google.android.apps.youtube.api.service.jar.IApiPlayerService");
      localParcel1.writeString(paramString);
      localParcel1.writeInt(paramInt);
      a.transact(1, localParcel1, localParcel2, 0);
      localParcel2.readException();
      return;
    }
    finally
    {
      localParcel2.recycle();
      localParcel1.recycle();
    }
  }
  
  public final void a(String paramString, int paramInt1, int paramInt2)
  {
    Parcel localParcel1 = Parcel.obtain();
    Parcel localParcel2 = Parcel.obtain();
    try
    {
      localParcel1.writeInterfaceToken("com.google.android.apps.youtube.api.service.jar.IApiPlayerService");
      localParcel1.writeString(paramString);
      localParcel1.writeInt(paramInt1);
      localParcel1.writeInt(paramInt2);
      a.transact(3, localParcel1, localParcel2, 0);
      localParcel2.readException();
      return;
    }
    finally
    {
      localParcel2.recycle();
      localParcel1.recycle();
    }
  }
  
  public final void a(List paramList, int paramInt1, int paramInt2)
  {
    Parcel localParcel1 = Parcel.obtain();
    Parcel localParcel2 = Parcel.obtain();
    try
    {
      localParcel1.writeInterfaceToken("com.google.android.apps.youtube.api.service.jar.IApiPlayerService");
      localParcel1.writeStringList(paramList);
      localParcel1.writeInt(paramInt1);
      localParcel1.writeInt(paramInt2);
      a.transact(5, localParcel1, localParcel2, 0);
      localParcel2.readException();
      return;
    }
    finally
    {
      localParcel2.recycle();
      localParcel1.recycle();
    }
  }
  
  public final boolean a(byte[] paramArrayOfByte)
  {
    boolean bool = false;
    Parcel localParcel1 = Parcel.obtain();
    Parcel localParcel2 = Parcel.obtain();
    try
    {
      localParcel1.writeInterfaceToken("com.google.android.apps.youtube.api.service.jar.IApiPlayerService");
      localParcel1.writeByteArray(paramArrayOfByte);
      a.transact(25, localParcel1, localParcel2, 0);
      localParcel2.readException();
      int i = localParcel2.readInt();
      if (i != 0) {
        bool = true;
      }
      return bool;
    }
    finally
    {
      localParcel2.recycle();
      localParcel1.recycle();
    }
  }
  
  public IBinder asBinder()
  {
    return a;
  }
  
  public final void b()
  {
    Parcel localParcel1 = Parcel.obtain();
    Parcel localParcel2 = Parcel.obtain();
    try
    {
      localParcel1.writeInterfaceToken("com.google.android.apps.youtube.api.service.jar.IApiPlayerService");
      a.transact(7, localParcel1, localParcel2, 0);
      localParcel2.readException();
      return;
    }
    finally
    {
      localParcel2.recycle();
      localParcel1.recycle();
    }
  }
  
  public final void b(int paramInt)
  {
    Parcel localParcel1 = Parcel.obtain();
    Parcel localParcel2 = Parcel.obtain();
    try
    {
      localParcel1.writeInterfaceToken("com.google.android.apps.youtube.api.service.jar.IApiPlayerService");
      localParcel1.writeInt(paramInt);
      a.transact(15, localParcel1, localParcel2, 0);
      localParcel2.readException();
      return;
    }
    finally
    {
      localParcel2.recycle();
      localParcel1.recycle();
    }
  }
  
  /* Error */
  public final void b(int paramInt, android.view.KeyEvent paramKeyEvent)
  {
    // Byte code:
    //   0: invokestatic 23	android/os/Parcel:obtain	()Landroid/os/Parcel;
    //   3: astore_3
    //   4: invokestatic 23	android/os/Parcel:obtain	()Landroid/os/Parcel;
    //   7: astore 4
    //   9: aload_3
    //   10: ldc 25
    //   12: invokevirtual 29	android/os/Parcel:writeInterfaceToken	(Ljava/lang/String;)V
    //   15: aload_3
    //   16: iload_1
    //   17: invokevirtual 32	android/os/Parcel:writeInt	(I)V
    //   20: aload_2
    //   21: ifnull +45 -> 66
    //   24: aload_3
    //   25: iconst_1
    //   26: invokevirtual 32	android/os/Parcel:writeInt	(I)V
    //   29: aload_2
    //   30: aload_3
    //   31: iconst_0
    //   32: invokevirtual 51	android/view/KeyEvent:writeToParcel	(Landroid/os/Parcel;I)V
    //   35: aload_0
    //   36: getfield 15	com/google/android/apps/youtube/api/service/jar/IApiPlayerService$Stub$Proxy:a	Landroid/os/IBinder;
    //   39: bipush 23
    //   41: aload_3
    //   42: aload 4
    //   44: iconst_0
    //   45: invokeinterface 38 5 0
    //   50: pop
    //   51: aload 4
    //   53: invokevirtual 41	android/os/Parcel:readException	()V
    //   56: aload 4
    //   58: invokevirtual 44	android/os/Parcel:recycle	()V
    //   61: aload_3
    //   62: invokevirtual 44	android/os/Parcel:recycle	()V
    //   65: return
    //   66: aload_3
    //   67: iconst_0
    //   68: invokevirtual 32	android/os/Parcel:writeInt	(I)V
    //   71: goto -36 -> 35
    //   74: astore_2
    //   75: aload 4
    //   77: invokevirtual 44	android/os/Parcel:recycle	()V
    //   80: aload_3
    //   81: invokevirtual 44	android/os/Parcel:recycle	()V
    //   84: aload_2
    //   85: athrow
    // Local variable table:
    //   start	length	slot	name	signature
    //   0	86	0	this	Proxy
    //   0	86	1	paramInt	int
    //   0	86	2	paramKeyEvent	android.view.KeyEvent
    //   3	78	3	localParcel1	Parcel
    //   7	69	4	localParcel2	Parcel
    // Exception table:
    //   from	to	target	type
    //   9	20	74	finally
    //   24	35	74	finally
    //   35	56	74	finally
    //   66	71	74	finally
  }
  
  public final void b(String paramString, int paramInt)
  {
    Parcel localParcel1 = Parcel.obtain();
    Parcel localParcel2 = Parcel.obtain();
    try
    {
      localParcel1.writeInterfaceToken("com.google.android.apps.youtube.api.service.jar.IApiPlayerService");
      localParcel1.writeString(paramString);
      localParcel1.writeInt(paramInt);
      a.transact(2, localParcel1, localParcel2, 0);
      localParcel2.readException();
      return;
    }
    finally
    {
      localParcel2.recycle();
      localParcel1.recycle();
    }
  }
  
  public final void b(String paramString, int paramInt1, int paramInt2)
  {
    Parcel localParcel1 = Parcel.obtain();
    Parcel localParcel2 = Parcel.obtain();
    try
    {
      localParcel1.writeInterfaceToken("com.google.android.apps.youtube.api.service.jar.IApiPlayerService");
      localParcel1.writeString(paramString);
      localParcel1.writeInt(paramInt1);
      localParcel1.writeInt(paramInt2);
      a.transact(4, localParcel1, localParcel2, 0);
      localParcel2.readException();
      return;
    }
    finally
    {
      localParcel2.recycle();
      localParcel1.recycle();
    }
  }
  
  public final void b(List paramList, int paramInt1, int paramInt2)
  {
    Parcel localParcel1 = Parcel.obtain();
    Parcel localParcel2 = Parcel.obtain();
    try
    {
      localParcel1.writeInterfaceToken("com.google.android.apps.youtube.api.service.jar.IApiPlayerService");
      localParcel1.writeStringList(paramList);
      localParcel1.writeInt(paramInt1);
      localParcel1.writeInt(paramInt2);
      a.transact(6, localParcel1, localParcel2, 0);
      localParcel2.readException();
      return;
    }
    finally
    {
      localParcel2.recycle();
      localParcel1.recycle();
    }
  }
  
  public final void b(boolean paramBoolean)
  {
    int i = 0;
    Parcel localParcel1 = Parcel.obtain();
    Parcel localParcel2 = Parcel.obtain();
    try
    {
      localParcel1.writeInterfaceToken("com.google.android.apps.youtube.api.service.jar.IApiPlayerService");
      if (paramBoolean) {
        i = 1;
      }
      localParcel1.writeInt(i);
      a.transact(11, localParcel1, localParcel2, 0);
      localParcel2.readException();
      return;
    }
    finally
    {
      localParcel2.recycle();
      localParcel1.recycle();
    }
  }
  
  public final void c()
  {
    Parcel localParcel1 = Parcel.obtain();
    Parcel localParcel2 = Parcel.obtain();
    try
    {
      localParcel1.writeInterfaceToken("com.google.android.apps.youtube.api.service.jar.IApiPlayerService");
      a.transact(8, localParcel1, localParcel2, 0);
      localParcel2.readException();
      return;
    }
    finally
    {
      localParcel2.recycle();
      localParcel1.recycle();
    }
  }
  
  public final void c(boolean paramBoolean)
  {
    int i = 0;
    Parcel localParcel1 = Parcel.obtain();
    Parcel localParcel2 = Parcel.obtain();
    try
    {
      localParcel1.writeInterfaceToken("com.google.android.apps.youtube.api.service.jar.IApiPlayerService");
      if (paramBoolean) {
        i = 1;
      }
      localParcel1.writeInt(i);
      a.transact(16, localParcel1, localParcel2, 0);
      localParcel2.readException();
      return;
    }
    finally
    {
      localParcel2.recycle();
      localParcel1.recycle();
    }
  }
  
  public final void d()
  {
    Parcel localParcel1 = Parcel.obtain();
    Parcel localParcel2 = Parcel.obtain();
    try
    {
      localParcel1.writeInterfaceToken("com.google.android.apps.youtube.api.service.jar.IApiPlayerService");
      a.transact(9, localParcel1, localParcel2, 0);
      localParcel2.readException();
      return;
    }
    finally
    {
      localParcel2.recycle();
      localParcel1.recycle();
    }
  }
  
  public final void d(boolean paramBoolean)
  {
    int i = 0;
    Parcel localParcel1 = Parcel.obtain();
    Parcel localParcel2 = Parcel.obtain();
    try
    {
      localParcel1.writeInterfaceToken("com.google.android.apps.youtube.api.service.jar.IApiPlayerService");
      if (paramBoolean) {
        i = 1;
      }
      localParcel1.writeInt(i);
      a.transact(17, localParcel1, localParcel2, 0);
      localParcel2.readException();
      return;
    }
    finally
    {
      localParcel2.recycle();
      localParcel1.recycle();
    }
  }
  
  public final void e(boolean paramBoolean)
  {
    int i = 0;
    Parcel localParcel1 = Parcel.obtain();
    Parcel localParcel2 = Parcel.obtain();
    try
    {
      localParcel1.writeInterfaceToken("com.google.android.apps.youtube.api.service.jar.IApiPlayerService");
      if (paramBoolean) {
        i = 1;
      }
      localParcel1.writeInt(i);
      a.transact(19, localParcel1, localParcel2, 0);
      localParcel2.readException();
      return;
    }
    finally
    {
      localParcel2.recycle();
      localParcel1.recycle();
    }
  }
  
  public final boolean e()
  {
    boolean bool = false;
    Parcel localParcel1 = Parcel.obtain();
    Parcel localParcel2 = Parcel.obtain();
    try
    {
      localParcel1.writeInterfaceToken("com.google.android.apps.youtube.api.service.jar.IApiPlayerService");
      a.transact(10, localParcel1, localParcel2, 0);
      localParcel2.readException();
      int i = localParcel2.readInt();
      if (i != 0) {
        bool = true;
      }
      return bool;
    }
    finally
    {
      localParcel2.recycle();
      localParcel1.recycle();
    }
  }
  
  public final void f()
  {
    Parcel localParcel1 = Parcel.obtain();
    Parcel localParcel2 = Parcel.obtain();
    try
    {
      localParcel1.writeInterfaceToken("com.google.android.apps.youtube.api.service.jar.IApiPlayerService");
      a.transact(12, localParcel1, localParcel2, 0);
      localParcel2.readException();
      return;
    }
    finally
    {
      localParcel2.recycle();
      localParcel1.recycle();
    }
  }
  
  public final void f(boolean paramBoolean)
  {
    int i = 0;
    Parcel localParcel1 = Parcel.obtain();
    Parcel localParcel2 = Parcel.obtain();
    try
    {
      localParcel1.writeInterfaceToken("com.google.android.apps.youtube.api.service.jar.IApiPlayerService");
      if (paramBoolean) {
        i = 1;
      }
      localParcel1.writeInt(i);
      a.transact(21, localParcel1, localParcel2, 0);
      localParcel2.readException();
      return;
    }
    finally
    {
      localParcel2.recycle();
      localParcel1.recycle();
    }
  }
  
  public final void g()
  {
    Parcel localParcel1 = Parcel.obtain();
    Parcel localParcel2 = Parcel.obtain();
    try
    {
      localParcel1.writeInterfaceToken("com.google.android.apps.youtube.api.service.jar.IApiPlayerService");
      a.transact(13, localParcel1, localParcel2, 0);
      localParcel2.readException();
      return;
    }
    finally
    {
      localParcel2.recycle();
      localParcel1.recycle();
    }
  }
  
  public final void h()
  {
    Parcel localParcel1 = Parcel.obtain();
    Parcel localParcel2 = Parcel.obtain();
    try
    {
      localParcel1.writeInterfaceToken("com.google.android.apps.youtube.api.service.jar.IApiPlayerService");
      a.transact(18, localParcel1, localParcel2, 0);
      localParcel2.readException();
      return;
    }
    finally
    {
      localParcel2.recycle();
      localParcel1.recycle();
    }
  }
  
  public final void i()
  {
    Parcel localParcel1 = Parcel.obtain();
    Parcel localParcel2 = Parcel.obtain();
    try
    {
      localParcel1.writeInterfaceToken("com.google.android.apps.youtube.api.service.jar.IApiPlayerService");
      a.transact(20, localParcel1, localParcel2, 0);
      localParcel2.readException();
      return;
    }
    finally
    {
      localParcel2.recycle();
      localParcel1.recycle();
    }
  }
  
  public final byte[] j()
  {
    Parcel localParcel1 = Parcel.obtain();
    Parcel localParcel2 = Parcel.obtain();
    try
    {
      localParcel1.writeInterfaceToken("com.google.android.apps.youtube.api.service.jar.IApiPlayerService");
      a.transact(24, localParcel1, localParcel2, 0);
      localParcel2.readException();
      byte[] arrayOfByte = localParcel2.createByteArray();
      return arrayOfByte;
    }
    finally
    {
      localParcel2.recycle();
      localParcel1.recycle();
    }
  }
  
  public final void k()
  {
    Parcel localParcel1 = Parcel.obtain();
    Parcel localParcel2 = Parcel.obtain();
    try
    {
      localParcel1.writeInterfaceToken("com.google.android.apps.youtube.api.service.jar.IApiPlayerService");
      a.transact(26, localParcel1, localParcel2, 0);
      localParcel2.readException();
      return;
    }
    finally
    {
      localParcel2.recycle();
      localParcel1.recycle();
    }
  }
  
  public final void l()
  {
    Parcel localParcel1 = Parcel.obtain();
    Parcel localParcel2 = Parcel.obtain();
    try
    {
      localParcel1.writeInterfaceToken("com.google.android.apps.youtube.api.service.jar.IApiPlayerService");
      a.transact(27, localParcel1, localParcel2, 0);
      localParcel2.readException();
      return;
    }
    finally
    {
      localParcel2.recycle();
      localParcel1.recycle();
    }
  }
}

/* Location:
 * Qualified Name:     com.google.android.apps.youtube.api.service.jar.IApiPlayerService.Stub.Proxy
 * Java Class Version: 6 (50.0)
 * JD-Core Version:    0.7.1
 */