public final class blr
  implements blp
{
  private String a;
  private String b;
  
  public blr() {}
  
  public blr(String paramString1, String paramString2)
  {
    if (blv.a(paramString1))
    {
      paramString1 = null;
      a = paramString1;
      if (!blv.a(paramString2)) {
        break label43;
      }
    }
    label43:
    for (paramString1 = (String)localObject;; paramString1 = paramString2.trim())
    {
      b = paramString1;
      return;
      paramString1 = paramString1.trim();
      break;
    }
  }
  
  /* Error */
  public final void a(String paramString, java.util.Map paramMap)
  {
    // Byte code:
    //   0: aload_1
    //   1: aload_2
    //   2: invokestatic 38	blv:a	(Ljava/lang/String;Ljava/util/Map;)Ljava/lang/String;
    //   5: astore 4
    //   7: ldc 40
    //   9: invokestatic 46	java/lang/System:getProperty	(Ljava/lang/String;)Ljava/lang/String;
    //   12: astore_2
    //   13: aload_0
    //   14: getfield 22	blr:a	Ljava/lang/String;
    //   17: invokestatic 20	blv:a	(Ljava/lang/String;)Z
    //   20: ifne +266 -> 286
    //   23: aload_0
    //   24: getfield 24	blr:b	Ljava/lang/String;
    //   27: invokestatic 20	blv:a	(Ljava/lang/String;)Z
    //   30: ifne +256 -> 286
    //   33: ldc 48
    //   35: iconst_3
    //   36: anewarray 4	java/lang/Object
    //   39: dup
    //   40: iconst_0
    //   41: aload_2
    //   42: aastore
    //   43: dup
    //   44: iconst_1
    //   45: aload_0
    //   46: getfield 22	blr:a	Ljava/lang/String;
    //   49: aastore
    //   50: dup
    //   51: iconst_2
    //   52: aload_0
    //   53: getfield 24	blr:b	Ljava/lang/String;
    //   56: aastore
    //   57: invokestatic 52	java/lang/String:format	(Ljava/lang/String;[Ljava/lang/Object;)Ljava/lang/String;
    //   60: astore_2
    //   61: aload_2
    //   62: invokestatic 56	java/lang/String:valueOf	(Ljava/lang/Object;)Ljava/lang/String;
    //   65: astore_1
    //   66: aload_1
    //   67: invokevirtual 60	java/lang/String:length	()I
    //   70: ifeq +69 -> 139
    //   73: ldc 62
    //   75: aload_1
    //   76: invokevirtual 65	java/lang/String:concat	(Ljava/lang/String;)Ljava/lang/String;
    //   79: pop
    //   80: aconst_null
    //   81: astore_3
    //   82: new 67	java/net/URL
    //   85: dup
    //   86: aload 4
    //   88: invokespecial 70	java/net/URL:<init>	(Ljava/lang/String;)V
    //   91: invokevirtual 74	java/net/URL:openConnection	()Ljava/net/URLConnection;
    //   94: checkcast 76	java/net/HttpURLConnection
    //   97: astore_1
    //   98: aload_1
    //   99: ldc 78
    //   101: aload_2
    //   102: invokevirtual 81	java/net/HttpURLConnection:setRequestProperty	(Ljava/lang/String;Ljava/lang/String;)V
    //   105: aload 4
    //   107: invokestatic 56	java/lang/String:valueOf	(Ljava/lang/Object;)Ljava/lang/String;
    //   110: astore_2
    //   111: aload_2
    //   112: invokevirtual 60	java/lang/String:length	()I
    //   115: ifeq +37 -> 152
    //   118: ldc 83
    //   120: aload_2
    //   121: invokevirtual 65	java/lang/String:concat	(Ljava/lang/String;)Ljava/lang/String;
    //   124: pop
    //   125: aload_1
    //   126: invokevirtual 86	java/net/HttpURLConnection:getResponseCode	()I
    //   129: pop
    //   130: aload_1
    //   131: ifnull +7 -> 138
    //   134: aload_1
    //   135: invokevirtual 89	java/net/HttpURLConnection:disconnect	()V
    //   138: return
    //   139: new 26	java/lang/String
    //   142: dup
    //   143: ldc 62
    //   145: invokespecial 90	java/lang/String:<init>	(Ljava/lang/String;)V
    //   148: pop
    //   149: goto -69 -> 80
    //   152: new 26	java/lang/String
    //   155: dup
    //   156: ldc 83
    //   158: invokespecial 90	java/lang/String:<init>	(Ljava/lang/String;)V
    //   161: pop
    //   162: goto -37 -> 125
    //   165: astore_3
    //   166: aload_1
    //   167: astore_2
    //   168: aload_3
    //   169: astore_1
    //   170: aload 4
    //   172: invokestatic 56	java/lang/String:valueOf	(Ljava/lang/Object;)Ljava/lang/String;
    //   175: astore_3
    //   176: aload_3
    //   177: invokevirtual 60	java/lang/String:length	()I
    //   180: ifeq +39 -> 219
    //   183: ldc 92
    //   185: aload_3
    //   186: invokevirtual 65	java/lang/String:concat	(Ljava/lang/String;)Ljava/lang/String;
    //   189: astore_3
    //   190: ldc 94
    //   192: aload_3
    //   193: invokestatic 96	blv:a	(Ljava/lang/String;Ljava/lang/String;)V
    //   196: new 98	blq
    //   199: dup
    //   200: aload_1
    //   201: invokevirtual 101	java/net/MalformedURLException:getMessage	()Ljava/lang/String;
    //   204: invokespecial 102	blq:<init>	(Ljava/lang/String;)V
    //   207: athrow
    //   208: astore_1
    //   209: aload_2
    //   210: ifnull +7 -> 217
    //   213: aload_2
    //   214: invokevirtual 89	java/net/HttpURLConnection:disconnect	()V
    //   217: aload_1
    //   218: athrow
    //   219: new 26	java/lang/String
    //   222: dup
    //   223: ldc 92
    //   225: invokespecial 90	java/lang/String:<init>	(Ljava/lang/String;)V
    //   228: astore_3
    //   229: goto -39 -> 190
    //   232: astore_2
    //   233: aload_3
    //   234: astore_1
    //   235: ldc 94
    //   237: ldc 104
    //   239: invokestatic 96	blv:a	(Ljava/lang/String;Ljava/lang/String;)V
    //   242: new 98	blq
    //   245: dup
    //   246: aload_2
    //   247: invokevirtual 105	java/io/IOException:getMessage	()Ljava/lang/String;
    //   250: invokespecial 102	blq:<init>	(Ljava/lang/String;)V
    //   253: athrow
    //   254: astore_3
    //   255: aload_1
    //   256: astore_2
    //   257: aload_3
    //   258: astore_1
    //   259: goto -50 -> 209
    //   262: astore_1
    //   263: aconst_null
    //   264: astore_2
    //   265: goto -56 -> 209
    //   268: astore_3
    //   269: aload_1
    //   270: astore_2
    //   271: aload_3
    //   272: astore_1
    //   273: goto -64 -> 209
    //   276: astore_2
    //   277: goto -42 -> 235
    //   280: astore_1
    //   281: aconst_null
    //   282: astore_2
    //   283: goto -113 -> 170
    //   286: goto -225 -> 61
    // Local variable table:
    //   start	length	slot	name	signature
    //   0	289	0	this	blr
    //   0	289	1	paramString	String
    //   0	289	2	paramMap	java.util.Map
    //   81	1	3	localObject1	Object
    //   165	4	3	localMalformedURLException	java.net.MalformedURLException
    //   175	59	3	str1	String
    //   254	4	3	localObject2	Object
    //   268	4	3	localObject3	Object
    //   5	166	4	str2	String
    // Exception table:
    //   from	to	target	type
    //   98	125	165	java/net/MalformedURLException
    //   125	130	165	java/net/MalformedURLException
    //   152	162	165	java/net/MalformedURLException
    //   170	190	208	finally
    //   190	208	208	finally
    //   219	229	208	finally
    //   82	98	232	java/io/IOException
    //   235	254	254	finally
    //   82	98	262	finally
    //   98	125	268	finally
    //   125	130	268	finally
    //   152	162	268	finally
    //   98	125	276	java/io/IOException
    //   125	130	276	java/io/IOException
    //   152	162	276	java/io/IOException
    //   82	98	280	java/net/MalformedURLException
  }
}

/* Location:
 * Qualified Name:     blr
 * Java Class Version: 6 (50.0)
 * JD-Core Version:    0.7.1
 */