import android.os.IBinder;
import android.os.Parcel;

public final class brw
  implements bru
{
  private IBinder a;
  
  public brw(IBinder paramIBinder)
  {
    a = paramIBinder;
  }
  
  public final void a()
  {
    Parcel localParcel1 = Parcel.obtain();
    Parcel localParcel2 = Parcel.obtain();
    try
    {
      localParcel1.writeInterfaceToken("com.google.android.apps.youtube.api.jar.client.IAdOverlayClient");
      a.transact(2, localParcel1, localParcel2, 0);
      localParcel2.readException();
      return;
    }
    finally
    {
      localParcel2.recycle();
      localParcel1.recycle();
    }
  }
  
  public final void a(int paramInt)
  {
    Parcel localParcel1 = Parcel.obtain();
    Parcel localParcel2 = Parcel.obtain();
    try
    {
      localParcel1.writeInterfaceToken("com.google.android.apps.youtube.api.jar.client.IAdOverlayClient");
      localParcel1.writeInt(paramInt);
      a.transact(6, localParcel1, localParcel2, 0);
      localParcel2.readException();
      return;
    }
    finally
    {
      localParcel2.recycle();
      localParcel1.recycle();
    }
  }
  
  /* Error */
  public final void a(android.graphics.Bitmap paramBitmap)
  {
    // Byte code:
    //   0: invokestatic 22	android/os/Parcel:obtain	()Landroid/os/Parcel;
    //   3: astore_2
    //   4: invokestatic 22	android/os/Parcel:obtain	()Landroid/os/Parcel;
    //   7: astore_3
    //   8: aload_2
    //   9: ldc 24
    //   11: invokevirtual 28	android/os/Parcel:writeInterfaceToken	(Ljava/lang/String;)V
    //   14: aload_1
    //   15: ifnull +42 -> 57
    //   18: aload_2
    //   19: iconst_1
    //   20: invokevirtual 44	android/os/Parcel:writeInt	(I)V
    //   23: aload_1
    //   24: aload_2
    //   25: iconst_0
    //   26: invokevirtual 51	android/graphics/Bitmap:writeToParcel	(Landroid/os/Parcel;I)V
    //   29: aload_0
    //   30: getfield 15	brw:a	Landroid/os/IBinder;
    //   33: bipush 7
    //   35: aload_2
    //   36: aload_3
    //   37: iconst_0
    //   38: invokeinterface 34 5 0
    //   43: pop
    //   44: aload_3
    //   45: invokevirtual 37	android/os/Parcel:readException	()V
    //   48: aload_3
    //   49: invokevirtual 40	android/os/Parcel:recycle	()V
    //   52: aload_2
    //   53: invokevirtual 40	android/os/Parcel:recycle	()V
    //   56: return
    //   57: aload_2
    //   58: iconst_0
    //   59: invokevirtual 44	android/os/Parcel:writeInt	(I)V
    //   62: goto -33 -> 29
    //   65: astore_1
    //   66: aload_3
    //   67: invokevirtual 40	android/os/Parcel:recycle	()V
    //   70: aload_2
    //   71: invokevirtual 40	android/os/Parcel:recycle	()V
    //   74: aload_1
    //   75: athrow
    // Local variable table:
    //   start	length	slot	name	signature
    //   0	76	0	this	brw
    //   0	76	1	paramBitmap	android.graphics.Bitmap
    //   3	68	2	localParcel1	Parcel
    //   7	60	3	localParcel2	Parcel
    // Exception table:
    //   from	to	target	type
    //   8	14	65	finally
    //   18	29	65	finally
    //   29	48	65	finally
    //   57	62	65	finally
  }
  
  /* Error */
  public final void a(com.google.android.apps.youtube.api.service.jar.IAdOverlayService paramIAdOverlayService)
  {
    // Byte code:
    //   0: invokestatic 22	android/os/Parcel:obtain	()Landroid/os/Parcel;
    //   3: astore_2
    //   4: invokestatic 22	android/os/Parcel:obtain	()Landroid/os/Parcel;
    //   7: astore_3
    //   8: aload_2
    //   9: ldc 24
    //   11: invokevirtual 28	android/os/Parcel:writeInterfaceToken	(Ljava/lang/String;)V
    //   14: aload_1
    //   15: ifnull +42 -> 57
    //   18: aload_1
    //   19: invokeinterface 58 1 0
    //   24: astore_1
    //   25: aload_2
    //   26: aload_1
    //   27: invokevirtual 61	android/os/Parcel:writeStrongBinder	(Landroid/os/IBinder;)V
    //   30: aload_0
    //   31: getfield 15	brw:a	Landroid/os/IBinder;
    //   34: iconst_1
    //   35: aload_2
    //   36: aload_3
    //   37: iconst_0
    //   38: invokeinterface 34 5 0
    //   43: pop
    //   44: aload_3
    //   45: invokevirtual 37	android/os/Parcel:readException	()V
    //   48: aload_3
    //   49: invokevirtual 40	android/os/Parcel:recycle	()V
    //   52: aload_2
    //   53: invokevirtual 40	android/os/Parcel:recycle	()V
    //   56: return
    //   57: aconst_null
    //   58: astore_1
    //   59: goto -34 -> 25
    //   62: astore_1
    //   63: aload_3
    //   64: invokevirtual 40	android/os/Parcel:recycle	()V
    //   67: aload_2
    //   68: invokevirtual 40	android/os/Parcel:recycle	()V
    //   71: aload_1
    //   72: athrow
    // Local variable table:
    //   start	length	slot	name	signature
    //   0	73	0	this	brw
    //   0	73	1	paramIAdOverlayService	com.google.android.apps.youtube.api.service.jar.IAdOverlayService
    //   3	65	2	localParcel1	Parcel
    //   7	57	3	localParcel2	Parcel
    // Exception table:
    //   from	to	target	type
    //   8	14	62	finally
    //   18	25	62	finally
    //   25	48	62	finally
  }
  
  public final void a(String paramString)
  {
    Parcel localParcel1 = Parcel.obtain();
    Parcel localParcel2 = Parcel.obtain();
    try
    {
      localParcel1.writeInterfaceToken("com.google.android.apps.youtube.api.jar.client.IAdOverlayClient");
      localParcel1.writeString(paramString);
      a.transact(5, localParcel1, localParcel2, 0);
      localParcel2.readException();
      return;
    }
    finally
    {
      localParcel2.recycle();
      localParcel1.recycle();
    }
  }
  
  public final void a(boolean paramBoolean)
  {
    int i = 0;
    Parcel localParcel1 = Parcel.obtain();
    Parcel localParcel2 = Parcel.obtain();
    try
    {
      localParcel1.writeInterfaceToken("com.google.android.apps.youtube.api.jar.client.IAdOverlayClient");
      if (paramBoolean) {
        i = 1;
      }
      localParcel1.writeInt(i);
      a.transact(3, localParcel1, localParcel2, 0);
      localParcel2.readException();
      return;
    }
    finally
    {
      localParcel2.recycle();
      localParcel1.recycle();
    }
  }
  
  public final IBinder asBinder()
  {
    return a;
  }
  
  public final void b()
  {
    Parcel localParcel1 = Parcel.obtain();
    Parcel localParcel2 = Parcel.obtain();
    try
    {
      localParcel1.writeInterfaceToken("com.google.android.apps.youtube.api.jar.client.IAdOverlayClient");
      a.transact(4, localParcel1, localParcel2, 0);
      localParcel2.readException();
      return;
    }
    finally
    {
      localParcel2.recycle();
      localParcel1.recycle();
    }
  }
  
  public final void b(int paramInt)
  {
    Parcel localParcel1 = Parcel.obtain();
    Parcel localParcel2 = Parcel.obtain();
    try
    {
      localParcel1.writeInterfaceToken("com.google.android.apps.youtube.api.jar.client.IAdOverlayClient");
      localParcel1.writeInt(paramInt);
      a.transact(12, localParcel1, localParcel2, 0);
      localParcel2.readException();
      return;
    }
    finally
    {
      localParcel2.recycle();
      localParcel1.recycle();
    }
  }
  
  public final void b(String paramString)
  {
    Parcel localParcel1 = Parcel.obtain();
    Parcel localParcel2 = Parcel.obtain();
    try
    {
      localParcel1.writeInterfaceToken("com.google.android.apps.youtube.api.jar.client.IAdOverlayClient");
      localParcel1.writeString(paramString);
      a.transact(9, localParcel1, localParcel2, 0);
      localParcel2.readException();
      return;
    }
    finally
    {
      localParcel2.recycle();
      localParcel1.recycle();
    }
  }
  
  public final void b(boolean paramBoolean)
  {
    int i = 0;
    Parcel localParcel1 = Parcel.obtain();
    Parcel localParcel2 = Parcel.obtain();
    try
    {
      localParcel1.writeInterfaceToken("com.google.android.apps.youtube.api.jar.client.IAdOverlayClient");
      if (paramBoolean) {
        i = 1;
      }
      localParcel1.writeInt(i);
      a.transact(8, localParcel1, localParcel2, 0);
      localParcel2.readException();
      return;
    }
    finally
    {
      localParcel2.recycle();
      localParcel1.recycle();
    }
  }
  
  public final void c()
  {
    Parcel localParcel1 = Parcel.obtain();
    Parcel localParcel2 = Parcel.obtain();
    try
    {
      localParcel1.writeInterfaceToken("com.google.android.apps.youtube.api.jar.client.IAdOverlayClient");
      a.transact(11, localParcel1, localParcel2, 0);
      localParcel2.readException();
      return;
    }
    finally
    {
      localParcel2.recycle();
      localParcel1.recycle();
    }
  }
  
  public final void c(int paramInt)
  {
    Parcel localParcel1 = Parcel.obtain();
    Parcel localParcel2 = Parcel.obtain();
    try
    {
      localParcel1.writeInterfaceToken("com.google.android.apps.youtube.api.jar.client.IAdOverlayClient");
      localParcel1.writeInt(paramInt);
      a.transact(10, localParcel1, localParcel2, 0);
      localParcel2.readException();
      return;
    }
    finally
    {
      localParcel2.recycle();
      localParcel1.recycle();
    }
  }
}

/* Location:
 * Qualified Name:     brw
 * Java Class Version: 6 (50.0)
 * JD-Core Version:    0.7.1
 */