import android.os.IBinder;
import android.os.Parcel;
import android.view.KeyEvent;
import java.util.List;
import java.util.Map;

public final class bsf
  implements bsd
{
  private IBinder a;
  
  public bsf(IBinder paramIBinder)
  {
    a = paramIBinder;
  }
  
  public final void a()
  {
    Parcel localParcel1 = Parcel.obtain();
    Parcel localParcel2 = Parcel.obtain();
    try
    {
      localParcel1.writeInterfaceToken("com.google.android.apps.youtube.api.jar.client.IControlsOverlayClient");
      a.transact(9, localParcel1, localParcel2, 0);
      localParcel2.readException();
      return;
    }
    finally
    {
      localParcel2.recycle();
      localParcel1.recycle();
    }
  }
  
  public final void a(long paramLong1, long paramLong2, long paramLong3, long paramLong4)
  {
    Parcel localParcel1 = Parcel.obtain();
    Parcel localParcel2 = Parcel.obtain();
    try
    {
      localParcel1.writeInterfaceToken("com.google.android.apps.youtube.api.jar.client.IControlsOverlayClient");
      localParcel1.writeLong(paramLong1);
      localParcel1.writeLong(paramLong2);
      localParcel1.writeLong(paramLong3);
      localParcel1.writeLong(paramLong4);
      a.transact(14, localParcel1, localParcel2, 0);
      localParcel2.readException();
      return;
    }
    finally
    {
      localParcel2.recycle();
      localParcel1.recycle();
    }
  }
  
  /* Error */
  public final void a(com.google.android.apps.youtube.api.service.jar.IControlsOverlayService paramIControlsOverlayService)
  {
    // Byte code:
    //   0: invokestatic 22	android/os/Parcel:obtain	()Landroid/os/Parcel;
    //   3: astore_2
    //   4: invokestatic 22	android/os/Parcel:obtain	()Landroid/os/Parcel;
    //   7: astore_3
    //   8: aload_2
    //   9: ldc 24
    //   11: invokevirtual 28	android/os/Parcel:writeInterfaceToken	(Ljava/lang/String;)V
    //   14: aload_1
    //   15: ifnull +42 -> 57
    //   18: aload_1
    //   19: invokeinterface 52 1 0
    //   24: astore_1
    //   25: aload_2
    //   26: aload_1
    //   27: invokevirtual 55	android/os/Parcel:writeStrongBinder	(Landroid/os/IBinder;)V
    //   30: aload_0
    //   31: getfield 15	bsf:a	Landroid/os/IBinder;
    //   34: iconst_1
    //   35: aload_2
    //   36: aload_3
    //   37: iconst_0
    //   38: invokeinterface 34 5 0
    //   43: pop
    //   44: aload_3
    //   45: invokevirtual 37	android/os/Parcel:readException	()V
    //   48: aload_3
    //   49: invokevirtual 40	android/os/Parcel:recycle	()V
    //   52: aload_2
    //   53: invokevirtual 40	android/os/Parcel:recycle	()V
    //   56: return
    //   57: aconst_null
    //   58: astore_1
    //   59: goto -34 -> 25
    //   62: astore_1
    //   63: aload_3
    //   64: invokevirtual 40	android/os/Parcel:recycle	()V
    //   67: aload_2
    //   68: invokevirtual 40	android/os/Parcel:recycle	()V
    //   71: aload_1
    //   72: athrow
    // Local variable table:
    //   start	length	slot	name	signature
    //   0	73	0	this	bsf
    //   0	73	1	paramIControlsOverlayService	com.google.android.apps.youtube.api.service.jar.IControlsOverlayService
    //   3	65	2	localParcel1	Parcel
    //   7	57	3	localParcel2	Parcel
    // Exception table:
    //   from	to	target	type
    //   8	14	62	finally
    //   18	25	62	finally
    //   25	48	62	finally
  }
  
  public final void a(String paramString)
  {
    Parcel localParcel1 = Parcel.obtain();
    Parcel localParcel2 = Parcel.obtain();
    try
    {
      localParcel1.writeInterfaceToken("com.google.android.apps.youtube.api.jar.client.IControlsOverlayClient");
      localParcel1.writeString(paramString);
      a.transact(2, localParcel1, localParcel2, 0);
      localParcel2.readException();
      return;
    }
    finally
    {
      localParcel2.recycle();
      localParcel1.recycle();
    }
  }
  
  public final void a(String paramString, boolean paramBoolean)
  {
    int i = 0;
    Parcel localParcel1 = Parcel.obtain();
    Parcel localParcel2 = Parcel.obtain();
    try
    {
      localParcel1.writeInterfaceToken("com.google.android.apps.youtube.api.jar.client.IControlsOverlayClient");
      localParcel1.writeString(paramString);
      if (paramBoolean) {
        i = 1;
      }
      localParcel1.writeInt(i);
      a.transact(12, localParcel1, localParcel2, 0);
      localParcel2.readException();
      return;
    }
    finally
    {
      localParcel2.recycle();
      localParcel1.recycle();
    }
  }
  
  public final void a(List paramList)
  {
    Parcel localParcel1 = Parcel.obtain();
    Parcel localParcel2 = Parcel.obtain();
    try
    {
      localParcel1.writeInterfaceToken("com.google.android.apps.youtube.api.jar.client.IControlsOverlayClient");
      localParcel1.writeTypedList(paramList);
      a.transact(24, localParcel1, localParcel2, 0);
      localParcel2.readException();
      return;
    }
    finally
    {
      localParcel2.recycle();
      localParcel1.recycle();
    }
  }
  
  public final void a(Map paramMap)
  {
    Parcel localParcel1 = Parcel.obtain();
    Parcel localParcel2 = Parcel.obtain();
    try
    {
      localParcel1.writeInterfaceToken("com.google.android.apps.youtube.api.jar.client.IControlsOverlayClient");
      localParcel1.writeMap(paramMap);
      a.transact(22, localParcel1, localParcel2, 0);
      localParcel2.readException();
      return;
    }
    finally
    {
      localParcel2.recycle();
      localParcel1.recycle();
    }
  }
  
  /* Error */
  public final void a(pem parampem)
  {
    // Byte code:
    //   0: invokestatic 22	android/os/Parcel:obtain	()Landroid/os/Parcel;
    //   3: astore_2
    //   4: invokestatic 22	android/os/Parcel:obtain	()Landroid/os/Parcel;
    //   7: astore_3
    //   8: aload_2
    //   9: ldc 24
    //   11: invokevirtual 28	android/os/Parcel:writeInterfaceToken	(Ljava/lang/String;)V
    //   14: aload_1
    //   15: ifnull +42 -> 57
    //   18: aload_2
    //   19: iconst_1
    //   20: invokevirtual 63	android/os/Parcel:writeInt	(I)V
    //   23: aload_1
    //   24: aload_2
    //   25: iconst_0
    //   26: invokevirtual 78	pem:writeToParcel	(Landroid/os/Parcel;I)V
    //   29: aload_0
    //   30: getfield 15	bsf:a	Landroid/os/IBinder;
    //   33: bipush 11
    //   35: aload_2
    //   36: aload_3
    //   37: iconst_0
    //   38: invokeinterface 34 5 0
    //   43: pop
    //   44: aload_3
    //   45: invokevirtual 37	android/os/Parcel:readException	()V
    //   48: aload_3
    //   49: invokevirtual 40	android/os/Parcel:recycle	()V
    //   52: aload_2
    //   53: invokevirtual 40	android/os/Parcel:recycle	()V
    //   56: return
    //   57: aload_2
    //   58: iconst_0
    //   59: invokevirtual 63	android/os/Parcel:writeInt	(I)V
    //   62: goto -33 -> 29
    //   65: astore_1
    //   66: aload_3
    //   67: invokevirtual 40	android/os/Parcel:recycle	()V
    //   70: aload_2
    //   71: invokevirtual 40	android/os/Parcel:recycle	()V
    //   74: aload_1
    //   75: athrow
    // Local variable table:
    //   start	length	slot	name	signature
    //   0	76	0	this	bsf
    //   0	76	1	parampem	pem
    //   3	68	2	localParcel1	Parcel
    //   7	60	3	localParcel2	Parcel
    // Exception table:
    //   from	to	target	type
    //   8	14	65	finally
    //   18	29	65	finally
    //   29	48	65	finally
    //   57	62	65	finally
  }
  
  /* Error */
  public final void a(ppw paramppw)
  {
    // Byte code:
    //   0: invokestatic 22	android/os/Parcel:obtain	()Landroid/os/Parcel;
    //   3: astore_2
    //   4: invokestatic 22	android/os/Parcel:obtain	()Landroid/os/Parcel;
    //   7: astore_3
    //   8: aload_2
    //   9: ldc 24
    //   11: invokevirtual 28	android/os/Parcel:writeInterfaceToken	(Ljava/lang/String;)V
    //   14: aload_1
    //   15: ifnull +42 -> 57
    //   18: aload_2
    //   19: iconst_1
    //   20: invokevirtual 63	android/os/Parcel:writeInt	(I)V
    //   23: aload_1
    //   24: aload_2
    //   25: iconst_0
    //   26: invokevirtual 82	ppw:writeToParcel	(Landroid/os/Parcel;I)V
    //   29: aload_0
    //   30: getfield 15	bsf:a	Landroid/os/IBinder;
    //   33: bipush 21
    //   35: aload_2
    //   36: aload_3
    //   37: iconst_0
    //   38: invokeinterface 34 5 0
    //   43: pop
    //   44: aload_3
    //   45: invokevirtual 37	android/os/Parcel:readException	()V
    //   48: aload_3
    //   49: invokevirtual 40	android/os/Parcel:recycle	()V
    //   52: aload_2
    //   53: invokevirtual 40	android/os/Parcel:recycle	()V
    //   56: return
    //   57: aload_2
    //   58: iconst_0
    //   59: invokevirtual 63	android/os/Parcel:writeInt	(I)V
    //   62: goto -33 -> 29
    //   65: astore_1
    //   66: aload_3
    //   67: invokevirtual 40	android/os/Parcel:recycle	()V
    //   70: aload_2
    //   71: invokevirtual 40	android/os/Parcel:recycle	()V
    //   74: aload_1
    //   75: athrow
    // Local variable table:
    //   start	length	slot	name	signature
    //   0	76	0	this	bsf
    //   0	76	1	paramppw	ppw
    //   3	68	2	localParcel1	Parcel
    //   7	60	3	localParcel2	Parcel
    // Exception table:
    //   from	to	target	type
    //   8	14	65	finally
    //   18	29	65	finally
    //   29	48	65	finally
    //   57	62	65	finally
  }
  
  public final void a(boolean paramBoolean)
  {
    int i = 0;
    Parcel localParcel1 = Parcel.obtain();
    Parcel localParcel2 = Parcel.obtain();
    try
    {
      localParcel1.writeInterfaceToken("com.google.android.apps.youtube.api.jar.client.IControlsOverlayClient");
      if (paramBoolean) {
        i = 1;
      }
      localParcel1.writeInt(i);
      a.transact(3, localParcel1, localParcel2, 0);
      localParcel2.readException();
      return;
    }
    finally
    {
      localParcel2.recycle();
      localParcel1.recycle();
    }
  }
  
  public final void a(lyq[] paramArrayOflyq, int paramInt)
  {
    Parcel localParcel1 = Parcel.obtain();
    Parcel localParcel2 = Parcel.obtain();
    try
    {
      localParcel1.writeInterfaceToken("com.google.android.apps.youtube.api.jar.client.IControlsOverlayClient");
      localParcel1.writeTypedArray(paramArrayOflyq, 0);
      localParcel1.writeInt(paramInt);
      a.transact(4, localParcel1, localParcel2, 0);
      localParcel2.readException();
      return;
    }
    finally
    {
      localParcel2.recycle();
      localParcel1.recycle();
    }
  }
  
  public final boolean a(int paramInt, KeyEvent paramKeyEvent)
  {
    boolean bool = true;
    Parcel localParcel1 = Parcel.obtain();
    Parcel localParcel2 = Parcel.obtain();
    for (;;)
    {
      try
      {
        localParcel1.writeInterfaceToken("com.google.android.apps.youtube.api.jar.client.IControlsOverlayClient");
        localParcel1.writeInt(paramInt);
        if (paramKeyEvent != null)
        {
          localParcel1.writeInt(1);
          paramKeyEvent.writeToParcel(localParcel1, 0);
          a.transact(17, localParcel1, localParcel2, 0);
          localParcel2.readException();
          paramInt = localParcel2.readInt();
          if (paramInt != 0) {
            return bool;
          }
        }
        else
        {
          localParcel1.writeInt(0);
          continue;
        }
        bool = false;
      }
      finally
      {
        localParcel2.recycle();
        localParcel1.recycle();
      }
    }
  }
  
  public final IBinder asBinder()
  {
    return a;
  }
  
  public final void b()
  {
    Parcel localParcel1 = Parcel.obtain();
    Parcel localParcel2 = Parcel.obtain();
    try
    {
      localParcel1.writeInterfaceToken("com.google.android.apps.youtube.api.jar.client.IControlsOverlayClient");
      a.transact(10, localParcel1, localParcel2, 0);
      localParcel2.readException();
      return;
    }
    finally
    {
      localParcel2.recycle();
      localParcel1.recycle();
    }
  }
  
  public final void b(boolean paramBoolean)
  {
    int i = 0;
    Parcel localParcel1 = Parcel.obtain();
    Parcel localParcel2 = Parcel.obtain();
    try
    {
      localParcel1.writeInterfaceToken("com.google.android.apps.youtube.api.jar.client.IControlsOverlayClient");
      if (paramBoolean) {
        i = 1;
      }
      localParcel1.writeInt(i);
      a.transact(5, localParcel1, localParcel2, 0);
      localParcel2.readException();
      return;
    }
    finally
    {
      localParcel2.recycle();
      localParcel1.recycle();
    }
  }
  
  public final boolean b(int paramInt, KeyEvent paramKeyEvent)
  {
    boolean bool = true;
    Parcel localParcel1 = Parcel.obtain();
    Parcel localParcel2 = Parcel.obtain();
    for (;;)
    {
      try
      {
        localParcel1.writeInterfaceToken("com.google.android.apps.youtube.api.jar.client.IControlsOverlayClient");
        localParcel1.writeInt(paramInt);
        if (paramKeyEvent != null)
        {
          localParcel1.writeInt(1);
          paramKeyEvent.writeToParcel(localParcel1, 0);
          a.transact(18, localParcel1, localParcel2, 0);
          localParcel2.readException();
          paramInt = localParcel2.readInt();
          if (paramInt != 0) {
            return bool;
          }
        }
        else
        {
          localParcel1.writeInt(0);
          continue;
        }
        bool = false;
      }
      finally
      {
        localParcel2.recycle();
        localParcel1.recycle();
      }
    }
  }
  
  public final void c()
  {
    Parcel localParcel1 = Parcel.obtain();
    Parcel localParcel2 = Parcel.obtain();
    try
    {
      localParcel1.writeInterfaceToken("com.google.android.apps.youtube.api.jar.client.IControlsOverlayClient");
      a.transact(15, localParcel1, localParcel2, 0);
      localParcel2.readException();
      return;
    }
    finally
    {
      localParcel2.recycle();
      localParcel1.recycle();
    }
  }
  
  public final void c(boolean paramBoolean)
  {
    int i = 0;
    Parcel localParcel1 = Parcel.obtain();
    Parcel localParcel2 = Parcel.obtain();
    try
    {
      localParcel1.writeInterfaceToken("com.google.android.apps.youtube.api.jar.client.IControlsOverlayClient");
      if (paramBoolean) {
        i = 1;
      }
      localParcel1.writeInt(i);
      a.transact(6, localParcel1, localParcel2, 0);
      localParcel2.readException();
      return;
    }
    finally
    {
      localParcel2.recycle();
      localParcel1.recycle();
    }
  }
  
  public final void d()
  {
    Parcel localParcel1 = Parcel.obtain();
    Parcel localParcel2 = Parcel.obtain();
    try
    {
      localParcel1.writeInterfaceToken("com.google.android.apps.youtube.api.jar.client.IControlsOverlayClient");
      a.transact(16, localParcel1, localParcel2, 0);
      localParcel2.readException();
      return;
    }
    finally
    {
      localParcel2.recycle();
      localParcel1.recycle();
    }
  }
  
  public final void d(boolean paramBoolean)
  {
    int i = 0;
    Parcel localParcel1 = Parcel.obtain();
    Parcel localParcel2 = Parcel.obtain();
    try
    {
      localParcel1.writeInterfaceToken("com.google.android.apps.youtube.api.jar.client.IControlsOverlayClient");
      if (paramBoolean) {
        i = 1;
      }
      localParcel1.writeInt(i);
      a.transact(7, localParcel1, localParcel2, 0);
      localParcel2.readException();
      return;
    }
    finally
    {
      localParcel2.recycle();
      localParcel1.recycle();
    }
  }
  
  public final void e()
  {
    Parcel localParcel1 = Parcel.obtain();
    Parcel localParcel2 = Parcel.obtain();
    try
    {
      localParcel1.writeInterfaceToken("com.google.android.apps.youtube.api.jar.client.IControlsOverlayClient");
      a.transact(23, localParcel1, localParcel2, 0);
      localParcel2.readException();
      return;
    }
    finally
    {
      localParcel2.recycle();
      localParcel1.recycle();
    }
  }
  
  public final void e(boolean paramBoolean)
  {
    int i = 0;
    Parcel localParcel1 = Parcel.obtain();
    Parcel localParcel2 = Parcel.obtain();
    try
    {
      localParcel1.writeInterfaceToken("com.google.android.apps.youtube.api.jar.client.IControlsOverlayClient");
      if (paramBoolean) {
        i = 1;
      }
      localParcel1.writeInt(i);
      a.transact(8, localParcel1, localParcel2, 0);
      localParcel2.readException();
      return;
    }
    finally
    {
      localParcel2.recycle();
      localParcel1.recycle();
    }
  }
  
  public final void f(boolean paramBoolean)
  {
    int i = 0;
    Parcel localParcel1 = Parcel.obtain();
    Parcel localParcel2 = Parcel.obtain();
    try
    {
      localParcel1.writeInterfaceToken("com.google.android.apps.youtube.api.jar.client.IControlsOverlayClient");
      if (paramBoolean) {
        i = 1;
      }
      localParcel1.writeInt(i);
      a.transact(13, localParcel1, localParcel2, 0);
      localParcel2.readException();
      return;
    }
    finally
    {
      localParcel2.recycle();
      localParcel1.recycle();
    }
  }
  
  public final void g(boolean paramBoolean)
  {
    int i = 0;
    Parcel localParcel1 = Parcel.obtain();
    Parcel localParcel2 = Parcel.obtain();
    try
    {
      localParcel1.writeInterfaceToken("com.google.android.apps.youtube.api.jar.client.IControlsOverlayClient");
      if (paramBoolean) {
        i = 1;
      }
      localParcel1.writeInt(i);
      a.transact(19, localParcel1, localParcel2, 0);
      localParcel2.readException();
      return;
    }
    finally
    {
      localParcel2.recycle();
      localParcel1.recycle();
    }
  }
  
  public final void h(boolean paramBoolean)
  {
    int i = 0;
    Parcel localParcel1 = Parcel.obtain();
    Parcel localParcel2 = Parcel.obtain();
    try
    {
      localParcel1.writeInterfaceToken("com.google.android.apps.youtube.api.jar.client.IControlsOverlayClient");
      if (paramBoolean) {
        i = 1;
      }
      localParcel1.writeInt(i);
      a.transact(20, localParcel1, localParcel2, 0);
      localParcel2.readException();
      return;
    }
    finally
    {
      localParcel2.recycle();
      localParcel1.recycle();
    }
  }
}

/* Location:
 * Qualified Name:     bsf
 * Java Class Version: 6 (50.0)
 * JD-Core Version:    0.7.1
 */