import android.os.IBinder;
import android.os.Parcel;

public final class bsl
  implements bsj
{
  private IBinder a;
  
  public bsl(IBinder paramIBinder)
  {
    a = paramIBinder;
  }
  
  /* Error */
  public final void a(com.google.android.apps.youtube.api.service.jar.IPlayerUiService paramIPlayerUiService)
  {
    // Byte code:
    //   0: invokestatic 23	android/os/Parcel:obtain	()Landroid/os/Parcel;
    //   3: astore_2
    //   4: invokestatic 23	android/os/Parcel:obtain	()Landroid/os/Parcel;
    //   7: astore_3
    //   8: aload_2
    //   9: ldc 25
    //   11: invokevirtual 29	android/os/Parcel:writeInterfaceToken	(Ljava/lang/String;)V
    //   14: aload_1
    //   15: ifnull +42 -> 57
    //   18: aload_1
    //   19: invokeinterface 35 1 0
    //   24: astore_1
    //   25: aload_2
    //   26: aload_1
    //   27: invokevirtual 38	android/os/Parcel:writeStrongBinder	(Landroid/os/IBinder;)V
    //   30: aload_0
    //   31: getfield 15	bsl:a	Landroid/os/IBinder;
    //   34: iconst_1
    //   35: aload_2
    //   36: aload_3
    //   37: iconst_0
    //   38: invokeinterface 44 5 0
    //   43: pop
    //   44: aload_3
    //   45: invokevirtual 47	android/os/Parcel:readException	()V
    //   48: aload_3
    //   49: invokevirtual 50	android/os/Parcel:recycle	()V
    //   52: aload_2
    //   53: invokevirtual 50	android/os/Parcel:recycle	()V
    //   56: return
    //   57: aconst_null
    //   58: astore_1
    //   59: goto -34 -> 25
    //   62: astore_1
    //   63: aload_3
    //   64: invokevirtual 50	android/os/Parcel:recycle	()V
    //   67: aload_2
    //   68: invokevirtual 50	android/os/Parcel:recycle	()V
    //   71: aload_1
    //   72: athrow
    // Local variable table:
    //   start	length	slot	name	signature
    //   0	73	0	this	bsl
    //   0	73	1	paramIPlayerUiService	com.google.android.apps.youtube.api.service.jar.IPlayerUiService
    //   3	65	2	localParcel1	Parcel
    //   7	57	3	localParcel2	Parcel
    // Exception table:
    //   from	to	target	type
    //   8	14	62	finally
    //   18	25	62	finally
    //   25	48	62	finally
  }
  
  public final void a(boolean paramBoolean)
  {
    int i = 0;
    Parcel localParcel1 = Parcel.obtain();
    Parcel localParcel2 = Parcel.obtain();
    try
    {
      localParcel1.writeInterfaceToken("com.google.android.apps.youtube.api.jar.client.IPlayerUiClient");
      if (paramBoolean) {
        i = 1;
      }
      localParcel1.writeInt(i);
      a.transact(2, localParcel1, localParcel2, 0);
      localParcel2.readException();
      return;
    }
    finally
    {
      localParcel2.recycle();
      localParcel1.recycle();
    }
  }
  
  public final IBinder asBinder()
  {
    return a;
  }
}

/* Location:
 * Qualified Name:     bsl
 * Java Class Version: 6 (50.0)
 * JD-Core Version:    0.7.1
 */