import java.util.HashMap;
import java.util.Map;

@gqf
public final class gns
  implements gnq
{
  private static Map c;
  private final fhh a;
  private final gpa b;
  
  static
  {
    HashMap localHashMap = new HashMap();
    c = localHashMap;
    localHashMap.put("resize", Integer.valueOf(1));
    c.put("playVideo", Integer.valueOf(2));
    c.put("storePicture", Integer.valueOf(3));
    c.put("createCalendarEvent", Integer.valueOf(4));
    c.put("setOrientationProperties", Integer.valueOf(5));
    c.put("closeResizedAd", Integer.valueOf(6));
  }
  
  public gns(fhh paramfhh, gpa paramgpa)
  {
    a = paramfhh;
    b = paramgpa;
  }
  
  /* Error */
  public final void a(grq paramgrq, Map paramMap)
  {
    // Byte code:
    //   0: iconst_m1
    //   1: istore 5
    //   3: aload_2
    //   4: ldc 59
    //   6: invokeinterface 63 2 0
    //   11: checkcast 65	java/lang/String
    //   14: astore 9
    //   16: getstatic 22	gns:c	Ljava/util/Map;
    //   19: aload 9
    //   21: invokeinterface 63 2 0
    //   26: checkcast 26	java/lang/Integer
    //   29: invokevirtual 69	java/lang/Integer:intValue	()I
    //   32: istore_3
    //   33: iload_3
    //   34: iconst_5
    //   35: if_icmpeq +26 -> 61
    //   38: aload_0
    //   39: getfield 51	gns:a	Lfhh;
    //   42: ifnull +19 -> 61
    //   45: aload_0
    //   46: getfield 51	gns:a	Lfhh;
    //   49: invokevirtual 74	fhh:a	()Z
    //   52: ifne +9 -> 61
    //   55: iconst_3
    //   56: invokestatic 79	fhe:a	(I)Z
    //   59: pop
    //   60: return
    //   61: iload_3
    //   62: tableswitch	default:+38->100, 1:+44->106, 2:+38->100, 3:+2479->2541, 4:+2299->2361, 5:+2776->2838, 6:+2885->2947
    //   100: iconst_4
    //   101: invokestatic 79	fhe:a	(I)Z
    //   104: pop
    //   105: return
    //   106: aload_0
    //   107: getfield 53	gns:b	Lgpa;
    //   110: astore 10
    //   112: aload 10
    //   114: getfield 85	gpa:i	Ljava/lang/Object;
    //   117: astore 9
    //   119: aload 9
    //   121: monitorenter
    //   122: aload 10
    //   124: getfield 89	gpa:k	Landroid/app/Activity;
    //   127: ifnonnull +20 -> 147
    //   130: aload 10
    //   132: ldc 91
    //   134: invokevirtual 94	gpa:a	(Ljava/lang/String;)V
    //   137: aload 9
    //   139: monitorexit
    //   140: return
    //   141: astore_1
    //   142: aload 9
    //   144: monitorexit
    //   145: aload_1
    //   146: athrow
    //   147: aload 10
    //   149: getfield 98	gpa:j	Lgrq;
    //   152: invokeinterface 103 1 0
    //   157: ifnonnull +14 -> 171
    //   160: aload 10
    //   162: ldc 105
    //   164: invokevirtual 94	gpa:a	(Ljava/lang/String;)V
    //   167: aload 9
    //   169: monitorexit
    //   170: return
    //   171: aload 10
    //   173: getfield 98	gpa:j	Lgrq;
    //   176: invokeinterface 103 1 0
    //   181: getfield 110	com/google/android/gms/ads/internal/client/AdSizeParcel:b	Z
    //   184: ifeq +14 -> 198
    //   187: aload 10
    //   189: ldc 112
    //   191: invokevirtual 94	gpa:a	(Ljava/lang/String;)V
    //   194: aload 9
    //   196: monitorexit
    //   197: return
    //   198: aload 10
    //   200: getfield 98	gpa:j	Lgrq;
    //   203: invokeinterface 115 1 0
    //   208: ifeq +14 -> 222
    //   211: aload 10
    //   213: ldc 117
    //   215: invokevirtual 94	gpa:a	(Ljava/lang/String;)V
    //   218: aload 9
    //   220: monitorexit
    //   221: return
    //   222: aload_2
    //   223: ldc 119
    //   225: invokeinterface 63 2 0
    //   230: checkcast 121	java/lang/CharSequence
    //   233: invokestatic 127	android/text/TextUtils:isEmpty	(Ljava/lang/CharSequence;)Z
    //   236: ifne +29 -> 265
    //   239: invokestatic 132	fhk:a	()Lfhk;
    //   242: getfield 135	fhk:c	Lgqs;
    //   245: astore_1
    //   246: aload 10
    //   248: aload_2
    //   249: ldc 119
    //   251: invokeinterface 63 2 0
    //   256: checkcast 65	java/lang/String
    //   259: invokestatic 140	gqs:a	(Ljava/lang/String;)I
    //   262: putfield 144	gpa:h	I
    //   265: aload_2
    //   266: ldc -110
    //   268: invokeinterface 63 2 0
    //   273: checkcast 121	java/lang/CharSequence
    //   276: invokestatic 127	android/text/TextUtils:isEmpty	(Ljava/lang/CharSequence;)Z
    //   279: ifne +29 -> 308
    //   282: invokestatic 132	fhk:a	()Lfhk;
    //   285: getfield 135	fhk:c	Lgqs;
    //   288: astore_1
    //   289: aload 10
    //   291: aload_2
    //   292: ldc -110
    //   294: invokeinterface 63 2 0
    //   299: checkcast 65	java/lang/String
    //   302: invokestatic 140	gqs:a	(Ljava/lang/String;)I
    //   305: putfield 149	gpa:e	I
    //   308: aload_2
    //   309: ldc -105
    //   311: invokeinterface 63 2 0
    //   316: checkcast 121	java/lang/CharSequence
    //   319: invokestatic 127	android/text/TextUtils:isEmpty	(Ljava/lang/CharSequence;)Z
    //   322: ifne +29 -> 351
    //   325: invokestatic 132	fhk:a	()Lfhk;
    //   328: getfield 135	fhk:c	Lgqs;
    //   331: astore_1
    //   332: aload 10
    //   334: aload_2
    //   335: ldc -105
    //   337: invokeinterface 63 2 0
    //   342: checkcast 65	java/lang/String
    //   345: invokestatic 140	gqs:a	(Ljava/lang/String;)I
    //   348: putfield 154	gpa:f	I
    //   351: aload_2
    //   352: ldc -100
    //   354: invokeinterface 63 2 0
    //   359: checkcast 121	java/lang/CharSequence
    //   362: invokestatic 127	android/text/TextUtils:isEmpty	(Ljava/lang/CharSequence;)Z
    //   365: ifne +29 -> 394
    //   368: invokestatic 132	fhk:a	()Lfhk;
    //   371: getfield 135	fhk:c	Lgqs;
    //   374: astore_1
    //   375: aload 10
    //   377: aload_2
    //   378: ldc -100
    //   380: invokeinterface 63 2 0
    //   385: checkcast 65	java/lang/String
    //   388: invokestatic 140	gqs:a	(Ljava/lang/String;)I
    //   391: putfield 159	gpa:g	I
    //   394: aload_2
    //   395: ldc -95
    //   397: invokeinterface 63 2 0
    //   402: checkcast 121	java/lang/CharSequence
    //   405: invokestatic 127	android/text/TextUtils:isEmpty	(Ljava/lang/CharSequence;)Z
    //   408: ifne +22 -> 430
    //   411: aload 10
    //   413: aload_2
    //   414: ldc -95
    //   416: invokeinterface 63 2 0
    //   421: checkcast 65	java/lang/String
    //   424: invokestatic 167	java/lang/Boolean:parseBoolean	(Ljava/lang/String;)Z
    //   427: putfield 168	gpa:b	Z
    //   430: aload_2
    //   431: ldc -86
    //   433: invokeinterface 63 2 0
    //   438: checkcast 65	java/lang/String
    //   441: astore_1
    //   442: aload_1
    //   443: invokestatic 127	android/text/TextUtils:isEmpty	(Ljava/lang/CharSequence;)Z
    //   446: ifne +9 -> 455
    //   449: aload 10
    //   451: aload_1
    //   452: putfield 173	gpa:a	Ljava/lang/String;
    //   455: aload 10
    //   457: getfield 144	gpa:h	I
    //   460: iflt +2502 -> 2962
    //   463: aload 10
    //   465: getfield 149	gpa:e	I
    //   468: iflt +2494 -> 2962
    //   471: iconst_1
    //   472: istore_3
    //   473: iload_3
    //   474: ifne +14 -> 488
    //   477: aload 10
    //   479: ldc -81
    //   481: invokevirtual 94	gpa:a	(Ljava/lang/String;)V
    //   484: aload 9
    //   486: monitorexit
    //   487: return
    //   488: aload 10
    //   490: getfield 89	gpa:k	Landroid/app/Activity;
    //   493: invokevirtual 181	android/app/Activity:getWindow	()Landroid/view/Window;
    //   496: astore_2
    //   497: aload_2
    //   498: ifnull +10 -> 508
    //   501: aload_2
    //   502: invokevirtual 187	android/view/Window:getDecorView	()Landroid/view/View;
    //   505: ifnonnull +14 -> 519
    //   508: aload 10
    //   510: ldc -67
    //   512: invokevirtual 94	gpa:a	(Ljava/lang/String;)V
    //   515: aload 9
    //   517: monitorexit
    //   518: return
    //   519: invokestatic 132	fhk:a	()Lfhk;
    //   522: getfield 135	fhk:c	Lgqs;
    //   525: aload 10
    //   527: getfield 89	gpa:k	Landroid/app/Activity;
    //   530: invokevirtual 192	gqs:b	(Landroid/app/Activity;)[I
    //   533: astore 11
    //   535: invokestatic 132	fhk:a	()Lfhk;
    //   538: getfield 135	fhk:c	Lgqs;
    //   541: aload 10
    //   543: getfield 89	gpa:k	Landroid/app/Activity;
    //   546: invokevirtual 194	gqs:c	(Landroid/app/Activity;)[I
    //   549: astore_1
    //   550: aload 11
    //   552: iconst_0
    //   553: iaload
    //   554: istore 6
    //   556: aload 11
    //   558: iconst_1
    //   559: iaload
    //   560: istore_3
    //   561: aload 10
    //   563: getfield 144	gpa:h	I
    //   566: bipush 50
    //   568: if_icmplt +13 -> 581
    //   571: aload 10
    //   573: getfield 144	gpa:h	I
    //   576: iload 6
    //   578: if_icmple +28 -> 606
    //   581: ldc -60
    //   583: invokestatic 198	fhe:b	(Ljava/lang/String;)V
    //   586: iconst_0
    //   587: istore_3
    //   588: goto +2379 -> 2967
    //   591: aload_1
    //   592: ifnonnull +716 -> 1308
    //   595: aload 10
    //   597: ldc -56
    //   599: invokevirtual 94	gpa:a	(Ljava/lang/String;)V
    //   602: aload 9
    //   604: monitorexit
    //   605: return
    //   606: aload 10
    //   608: getfield 149	gpa:e	I
    //   611: bipush 50
    //   613: if_icmplt +12 -> 625
    //   616: aload 10
    //   618: getfield 149	gpa:e	I
    //   621: iload_3
    //   622: if_icmple +13 -> 635
    //   625: ldc -54
    //   627: invokestatic 198	fhe:b	(Ljava/lang/String;)V
    //   630: iconst_0
    //   631: istore_3
    //   632: goto +2335 -> 2967
    //   635: aload 10
    //   637: getfield 149	gpa:e	I
    //   640: iload_3
    //   641: if_icmpne +23 -> 664
    //   644: aload 10
    //   646: getfield 144	gpa:h	I
    //   649: iload 6
    //   651: if_icmpne +13 -> 664
    //   654: ldc -52
    //   656: invokestatic 198	fhe:b	(Ljava/lang/String;)V
    //   659: iconst_0
    //   660: istore_3
    //   661: goto +2306 -> 2967
    //   664: aload 10
    //   666: getfield 168	gpa:b	Z
    //   669: ifeq +2387 -> 3056
    //   672: aload 10
    //   674: getfield 173	gpa:a	Ljava/lang/String;
    //   677: astore 11
    //   679: aload 11
    //   681: invokevirtual 207	java/lang/String:hashCode	()I
    //   684: lookupswitch	default:+2292->2976, -1364013995:+127->811, -1012429441:+97->781, -655373719:+142->826, 1163912186:+172->856, 1288627767:+157->841, 1755462605:+112->796
    //   744: aload 10
    //   746: getfield 209	gpa:c	I
    //   749: aload 10
    //   751: getfield 154	gpa:f	I
    //   754: iadd
    //   755: aload 10
    //   757: getfield 144	gpa:h	I
    //   760: iadd
    //   761: bipush 50
    //   763: isub
    //   764: istore 4
    //   766: aload 10
    //   768: getfield 212	gpa:d	I
    //   771: aload 10
    //   773: getfield 159	gpa:g	I
    //   776: iadd
    //   777: istore_3
    //   778: goto +2241 -> 3019
    //   781: aload 11
    //   783: ldc -42
    //   785: invokevirtual 218	java/lang/String:equals	(Ljava/lang/Object;)Z
    //   788: ifeq +2188 -> 2976
    //   791: iconst_0
    //   792: istore_3
    //   793: goto +2185 -> 2978
    //   796: aload 11
    //   798: ldc -36
    //   800: invokevirtual 218	java/lang/String:equals	(Ljava/lang/Object;)Z
    //   803: ifeq +2173 -> 2976
    //   806: iconst_1
    //   807: istore_3
    //   808: goto +2170 -> 2978
    //   811: aload 11
    //   813: ldc -34
    //   815: invokevirtual 218	java/lang/String:equals	(Ljava/lang/Object;)Z
    //   818: ifeq +2158 -> 2976
    //   821: iconst_2
    //   822: istore_3
    //   823: goto +2155 -> 2978
    //   826: aload 11
    //   828: ldc -32
    //   830: invokevirtual 218	java/lang/String:equals	(Ljava/lang/Object;)Z
    //   833: ifeq +2143 -> 2976
    //   836: iconst_3
    //   837: istore_3
    //   838: goto +2140 -> 2978
    //   841: aload 11
    //   843: ldc -30
    //   845: invokevirtual 218	java/lang/String:equals	(Ljava/lang/Object;)Z
    //   848: ifeq +2128 -> 2976
    //   851: iconst_4
    //   852: istore_3
    //   853: goto +2125 -> 2978
    //   856: aload 11
    //   858: ldc -28
    //   860: invokevirtual 218	java/lang/String:equals	(Ljava/lang/Object;)Z
    //   863: ifeq +2113 -> 2976
    //   866: iconst_5
    //   867: istore_3
    //   868: goto +2110 -> 2978
    //   871: aload 10
    //   873: getfield 209	gpa:c	I
    //   876: istore_3
    //   877: aload 10
    //   879: getfield 154	gpa:f	I
    //   882: iload_3
    //   883: iadd
    //   884: istore 4
    //   886: aload 10
    //   888: getfield 212	gpa:d	I
    //   891: aload 10
    //   893: getfield 159	gpa:g	I
    //   896: iadd
    //   897: istore_3
    //   898: goto +2121 -> 3019
    //   901: aload 10
    //   903: getfield 209	gpa:c	I
    //   906: aload 10
    //   908: getfield 154	gpa:f	I
    //   911: iadd
    //   912: aload 10
    //   914: getfield 144	gpa:h	I
    //   917: iconst_2
    //   918: idiv
    //   919: iadd
    //   920: bipush 25
    //   922: isub
    //   923: istore 4
    //   925: aload 10
    //   927: getfield 212	gpa:d	I
    //   930: aload 10
    //   932: getfield 159	gpa:g	I
    //   935: iadd
    //   936: istore_3
    //   937: goto +2082 -> 3019
    //   940: aload 10
    //   942: getfield 209	gpa:c	I
    //   945: aload 10
    //   947: getfield 154	gpa:f	I
    //   950: iadd
    //   951: aload 10
    //   953: getfield 144	gpa:h	I
    //   956: iconst_2
    //   957: idiv
    //   958: iadd
    //   959: bipush 25
    //   961: isub
    //   962: istore 4
    //   964: aload 10
    //   966: getfield 212	gpa:d	I
    //   969: aload 10
    //   971: getfield 159	gpa:g	I
    //   974: iadd
    //   975: aload 10
    //   977: getfield 149	gpa:e	I
    //   980: iconst_2
    //   981: idiv
    //   982: iadd
    //   983: bipush 25
    //   985: isub
    //   986: istore_3
    //   987: goto +2032 -> 3019
    //   990: aload 10
    //   992: getfield 209	gpa:c	I
    //   995: istore_3
    //   996: aload 10
    //   998: getfield 154	gpa:f	I
    //   1001: iload_3
    //   1002: iadd
    //   1003: istore 4
    //   1005: aload 10
    //   1007: getfield 212	gpa:d	I
    //   1010: aload 10
    //   1012: getfield 159	gpa:g	I
    //   1015: iadd
    //   1016: aload 10
    //   1018: getfield 149	gpa:e	I
    //   1021: iadd
    //   1022: bipush 50
    //   1024: isub
    //   1025: istore_3
    //   1026: goto +1993 -> 3019
    //   1029: aload 10
    //   1031: getfield 209	gpa:c	I
    //   1034: aload 10
    //   1036: getfield 154	gpa:f	I
    //   1039: iadd
    //   1040: aload 10
    //   1042: getfield 144	gpa:h	I
    //   1045: iconst_2
    //   1046: idiv
    //   1047: iadd
    //   1048: bipush 25
    //   1050: isub
    //   1051: istore 4
    //   1053: aload 10
    //   1055: getfield 212	gpa:d	I
    //   1058: aload 10
    //   1060: getfield 159	gpa:g	I
    //   1063: iadd
    //   1064: aload 10
    //   1066: getfield 149	gpa:e	I
    //   1069: iadd
    //   1070: bipush 50
    //   1072: isub
    //   1073: istore_3
    //   1074: goto +1945 -> 3019
    //   1077: aload 10
    //   1079: getfield 209	gpa:c	I
    //   1082: aload 10
    //   1084: getfield 154	gpa:f	I
    //   1087: iadd
    //   1088: aload 10
    //   1090: getfield 144	gpa:h	I
    //   1093: iadd
    //   1094: bipush 50
    //   1096: isub
    //   1097: istore 4
    //   1099: aload 10
    //   1101: getfield 212	gpa:d	I
    //   1104: aload 10
    //   1106: getfield 159	gpa:g	I
    //   1109: iadd
    //   1110: aload 10
    //   1112: getfield 149	gpa:e	I
    //   1115: iadd
    //   1116: bipush 50
    //   1118: isub
    //   1119: istore_3
    //   1120: goto +1899 -> 3019
    //   1123: aload 10
    //   1125: getfield 168	gpa:b	Z
    //   1128: ifeq +38 -> 1166
    //   1131: iconst_2
    //   1132: newarray <illegal type>
    //   1134: dup
    //   1135: iconst_0
    //   1136: aload 10
    //   1138: getfield 209	gpa:c	I
    //   1141: aload 10
    //   1143: getfield 154	gpa:f	I
    //   1146: iadd
    //   1147: iastore
    //   1148: dup
    //   1149: iconst_1
    //   1150: aload 10
    //   1152: getfield 212	gpa:d	I
    //   1155: aload 10
    //   1157: getfield 159	gpa:g	I
    //   1160: iadd
    //   1161: iastore
    //   1162: astore_1
    //   1163: goto -572 -> 591
    //   1166: invokestatic 132	fhk:a	()Lfhk;
    //   1169: getfield 135	fhk:c	Lgqs;
    //   1172: aload 10
    //   1174: getfield 89	gpa:k	Landroid/app/Activity;
    //   1177: invokevirtual 192	gqs:b	(Landroid/app/Activity;)[I
    //   1180: astore_1
    //   1181: invokestatic 132	fhk:a	()Lfhk;
    //   1184: getfield 135	fhk:c	Lgqs;
    //   1187: aload 10
    //   1189: getfield 89	gpa:k	Landroid/app/Activity;
    //   1192: invokevirtual 194	gqs:c	(Landroid/app/Activity;)[I
    //   1195: astore 11
    //   1197: aload_1
    //   1198: iconst_0
    //   1199: iaload
    //   1200: istore 6
    //   1202: aload 10
    //   1204: getfield 209	gpa:c	I
    //   1207: istore_3
    //   1208: aload 10
    //   1210: getfield 154	gpa:f	I
    //   1213: iload_3
    //   1214: iadd
    //   1215: istore_3
    //   1216: aload 10
    //   1218: getfield 212	gpa:d	I
    //   1221: aload 10
    //   1223: getfield 159	gpa:g	I
    //   1226: iadd
    //   1227: istore 4
    //   1229: iload_3
    //   1230: ifge +24 -> 1254
    //   1233: iconst_0
    //   1234: istore_3
    //   1235: goto +1826 -> 3061
    //   1238: iconst_2
    //   1239: newarray <illegal type>
    //   1241: dup
    //   1242: iconst_0
    //   1243: iload_3
    //   1244: iastore
    //   1245: dup
    //   1246: iconst_1
    //   1247: iload 4
    //   1249: iastore
    //   1250: astore_1
    //   1251: goto -660 -> 591
    //   1254: aload 10
    //   1256: getfield 144	gpa:h	I
    //   1259: iload_3
    //   1260: iadd
    //   1261: iload 6
    //   1263: if_icmple +1696 -> 2959
    //   1266: iload 6
    //   1268: aload 10
    //   1270: getfield 144	gpa:h	I
    //   1273: isub
    //   1274: istore_3
    //   1275: goto +1786 -> 3061
    //   1278: aload 10
    //   1280: getfield 149	gpa:e	I
    //   1283: iload 4
    //   1285: iadd
    //   1286: aload 11
    //   1288: iconst_1
    //   1289: iaload
    //   1290: if_icmple +1666 -> 2956
    //   1293: aload 11
    //   1295: iconst_1
    //   1296: iaload
    //   1297: aload 10
    //   1299: getfield 149	gpa:e	I
    //   1302: isub
    //   1303: istore 4
    //   1305: goto -67 -> 1238
    //   1308: invokestatic 233	ffh:a	()Lffh;
    //   1311: getfield 236	ffh:a	Lfhd;
    //   1314: astore 11
    //   1316: aload 10
    //   1318: getfield 89	gpa:k	Landroid/app/Activity;
    //   1321: aload 10
    //   1323: getfield 144	gpa:h	I
    //   1326: invokestatic 241	fhd:a	(Landroid/content/Context;I)I
    //   1329: istore_3
    //   1330: invokestatic 233	ffh:a	()Lffh;
    //   1333: getfield 236	ffh:a	Lfhd;
    //   1336: astore 11
    //   1338: aload 10
    //   1340: getfield 89	gpa:k	Landroid/app/Activity;
    //   1343: aload 10
    //   1345: getfield 149	gpa:e	I
    //   1348: invokestatic 241	fhd:a	(Landroid/content/Context;I)I
    //   1351: istore 4
    //   1353: aload 10
    //   1355: getfield 98	gpa:j	Lgrq;
    //   1358: invokeinterface 244 1 0
    //   1363: invokevirtual 250	android/webkit/WebView:getParent	()Landroid/view/ViewParent;
    //   1366: astore 11
    //   1368: aload 11
    //   1370: ifnull +663 -> 2033
    //   1373: aload 11
    //   1375: instanceof 252
    //   1378: ifeq +655 -> 2033
    //   1381: aload 11
    //   1383: checkcast 252	android/view/ViewGroup
    //   1386: aload 10
    //   1388: getfield 98	gpa:j	Lgrq;
    //   1391: invokeinterface 244 1 0
    //   1396: invokevirtual 256	android/view/ViewGroup:removeView	(Landroid/view/View;)V
    //   1399: aload 10
    //   1401: getfield 260	gpa:o	Landroid/widget/PopupWindow;
    //   1404: ifnonnull +618 -> 2022
    //   1407: aload 10
    //   1409: aload 11
    //   1411: checkcast 252	android/view/ViewGroup
    //   1414: putfield 264	gpa:q	Landroid/view/ViewGroup;
    //   1417: invokestatic 132	fhk:a	()Lfhk;
    //   1420: getfield 135	fhk:c	Lgqs;
    //   1423: astore 11
    //   1425: aload 10
    //   1427: getfield 98	gpa:j	Lgrq;
    //   1430: invokeinterface 244 1 0
    //   1435: invokestatic 267	gqs:a	(Landroid/view/View;)Landroid/graphics/Bitmap;
    //   1438: astore 11
    //   1440: aload 10
    //   1442: new 269	android/widget/ImageView
    //   1445: dup
    //   1446: aload 10
    //   1448: getfield 89	gpa:k	Landroid/app/Activity;
    //   1451: invokespecial 272	android/widget/ImageView:<init>	(Landroid/content/Context;)V
    //   1454: putfield 276	gpa:m	Landroid/widget/ImageView;
    //   1457: aload 10
    //   1459: getfield 276	gpa:m	Landroid/widget/ImageView;
    //   1462: aload 11
    //   1464: invokevirtual 280	android/widget/ImageView:setImageBitmap	(Landroid/graphics/Bitmap;)V
    //   1467: aload 10
    //   1469: aload 10
    //   1471: getfield 98	gpa:j	Lgrq;
    //   1474: invokeinterface 103 1 0
    //   1479: putfield 284	gpa:l	Lcom/google/android/gms/ads/internal/client/AdSizeParcel;
    //   1482: aload 10
    //   1484: getfield 264	gpa:q	Landroid/view/ViewGroup;
    //   1487: aload 10
    //   1489: getfield 276	gpa:m	Landroid/widget/ImageView;
    //   1492: invokevirtual 287	android/view/ViewGroup:addView	(Landroid/view/View;)V
    //   1495: aload 10
    //   1497: new 289	android/widget/RelativeLayout
    //   1500: dup
    //   1501: aload 10
    //   1503: getfield 89	gpa:k	Landroid/app/Activity;
    //   1506: invokespecial 290	android/widget/RelativeLayout:<init>	(Landroid/content/Context;)V
    //   1509: putfield 294	gpa:p	Landroid/widget/RelativeLayout;
    //   1512: aload 10
    //   1514: getfield 294	gpa:p	Landroid/widget/RelativeLayout;
    //   1517: iconst_0
    //   1518: invokevirtual 298	android/widget/RelativeLayout:setBackgroundColor	(I)V
    //   1521: aload 10
    //   1523: getfield 294	gpa:p	Landroid/widget/RelativeLayout;
    //   1526: new 300	android/view/ViewGroup$LayoutParams
    //   1529: dup
    //   1530: iload_3
    //   1531: iload 4
    //   1533: invokespecial 303	android/view/ViewGroup$LayoutParams:<init>	(II)V
    //   1536: invokevirtual 307	android/widget/RelativeLayout:setLayoutParams	(Landroid/view/ViewGroup$LayoutParams;)V
    //   1539: invokestatic 132	fhk:a	()Lfhk;
    //   1542: getfield 135	fhk:c	Lgqs;
    //   1545: astore 11
    //   1547: aload 10
    //   1549: aload 10
    //   1551: getfield 294	gpa:p	Landroid/widget/RelativeLayout;
    //   1554: iload_3
    //   1555: iload 4
    //   1557: invokestatic 310	gqs:a	(Landroid/view/View;II)Landroid/widget/PopupWindow;
    //   1560: putfield 260	gpa:o	Landroid/widget/PopupWindow;
    //   1563: aload 10
    //   1565: getfield 260	gpa:o	Landroid/widget/PopupWindow;
    //   1568: iconst_1
    //   1569: invokevirtual 316	android/widget/PopupWindow:setOutsideTouchable	(Z)V
    //   1572: aload 10
    //   1574: getfield 260	gpa:o	Landroid/widget/PopupWindow;
    //   1577: iconst_1
    //   1578: invokevirtual 319	android/widget/PopupWindow:setTouchable	(Z)V
    //   1581: aload 10
    //   1583: getfield 260	gpa:o	Landroid/widget/PopupWindow;
    //   1586: astore 11
    //   1588: aload 10
    //   1590: getfield 168	gpa:b	Z
    //   1593: ifne +1530 -> 3123
    //   1596: iconst_1
    //   1597: istore 8
    //   1599: aload 11
    //   1601: iload 8
    //   1603: invokevirtual 322	android/widget/PopupWindow:setClippingEnabled	(Z)V
    //   1606: aload 10
    //   1608: getfield 294	gpa:p	Landroid/widget/RelativeLayout;
    //   1611: aload 10
    //   1613: getfield 98	gpa:j	Lgrq;
    //   1616: invokeinterface 244 1 0
    //   1621: iconst_m1
    //   1622: iconst_m1
    //   1623: invokevirtual 325	android/widget/RelativeLayout:addView	(Landroid/view/View;II)V
    //   1626: aload 10
    //   1628: new 327	android/widget/LinearLayout
    //   1631: dup
    //   1632: aload 10
    //   1634: getfield 89	gpa:k	Landroid/app/Activity;
    //   1637: invokespecial 328	android/widget/LinearLayout:<init>	(Landroid/content/Context;)V
    //   1640: putfield 331	gpa:n	Landroid/widget/LinearLayout;
    //   1643: invokestatic 233	ffh:a	()Lffh;
    //   1646: getfield 236	ffh:a	Lfhd;
    //   1649: astore 11
    //   1651: aload 10
    //   1653: getfield 89	gpa:k	Landroid/app/Activity;
    //   1656: bipush 50
    //   1658: invokestatic 241	fhd:a	(Landroid/content/Context;I)I
    //   1661: istore_3
    //   1662: invokestatic 233	ffh:a	()Lffh;
    //   1665: getfield 236	ffh:a	Lfhd;
    //   1668: astore 11
    //   1670: new 333	android/widget/RelativeLayout$LayoutParams
    //   1673: dup
    //   1674: iload_3
    //   1675: aload 10
    //   1677: getfield 89	gpa:k	Landroid/app/Activity;
    //   1680: bipush 50
    //   1682: invokestatic 241	fhd:a	(Landroid/content/Context;I)I
    //   1685: invokespecial 334	android/widget/RelativeLayout$LayoutParams:<init>	(II)V
    //   1688: astore 11
    //   1690: aload 10
    //   1692: getfield 173	gpa:a	Ljava/lang/String;
    //   1695: astore 12
    //   1697: aload 12
    //   1699: invokevirtual 207	java/lang/String:hashCode	()I
    //   1702: lookupswitch	default:+1377->3079, -1364013995:+379->2081, -1012429441:+343->2045, -655373719:+397->2099, 1163912186:+433->2135, 1288627767:+415->2117, 1755462605:+361->2063
    //   1760: aload 11
    //   1762: bipush 10
    //   1764: invokevirtual 337	android/widget/RelativeLayout$LayoutParams:addRule	(I)V
    //   1767: aload 11
    //   1769: bipush 11
    //   1771: invokevirtual 337	android/widget/RelativeLayout$LayoutParams:addRule	(I)V
    //   1774: aload 10
    //   1776: getfield 331	gpa:n	Landroid/widget/LinearLayout;
    //   1779: new 339	gpb
    //   1782: dup
    //   1783: aload 10
    //   1785: invokespecial 342	gpb:<init>	(Lgpa;)V
    //   1788: invokevirtual 346	android/widget/LinearLayout:setOnClickListener	(Landroid/view/View$OnClickListener;)V
    //   1791: aload 10
    //   1793: getfield 331	gpa:n	Landroid/widget/LinearLayout;
    //   1796: ldc_w 348
    //   1799: invokevirtual 352	android/widget/LinearLayout:setContentDescription	(Ljava/lang/CharSequence;)V
    //   1802: aload 10
    //   1804: getfield 294	gpa:p	Landroid/widget/RelativeLayout;
    //   1807: aload 10
    //   1809: getfield 331	gpa:n	Landroid/widget/LinearLayout;
    //   1812: aload 11
    //   1814: invokevirtual 355	android/widget/RelativeLayout:addView	(Landroid/view/View;Landroid/view/ViewGroup$LayoutParams;)V
    //   1817: aload 10
    //   1819: getfield 260	gpa:o	Landroid/widget/PopupWindow;
    //   1822: astore 11
    //   1824: aload_2
    //   1825: invokevirtual 187	android/view/Window:getDecorView	()Landroid/view/View;
    //   1828: astore_2
    //   1829: invokestatic 233	ffh:a	()Lffh;
    //   1832: getfield 236	ffh:a	Lfhd;
    //   1835: astore 12
    //   1837: aload 10
    //   1839: getfield 89	gpa:k	Landroid/app/Activity;
    //   1842: aload_1
    //   1843: iconst_0
    //   1844: iaload
    //   1845: invokestatic 241	fhd:a	(Landroid/content/Context;I)I
    //   1848: istore_3
    //   1849: invokestatic 233	ffh:a	()Lffh;
    //   1852: getfield 236	ffh:a	Lfhd;
    //   1855: astore 12
    //   1857: aload 11
    //   1859: aload_2
    //   1860: iconst_0
    //   1861: iload_3
    //   1862: aload 10
    //   1864: getfield 89	gpa:k	Landroid/app/Activity;
    //   1867: aload_1
    //   1868: iconst_1
    //   1869: iaload
    //   1870: invokestatic 241	fhd:a	(Landroid/content/Context;I)I
    //   1873: invokevirtual 359	android/widget/PopupWindow:showAtLocation	(Landroid/view/View;III)V
    //   1876: aload 10
    //   1878: getfield 98	gpa:j	Lgrq;
    //   1881: new 107	com/google/android/gms/ads/internal/client/AdSizeParcel
    //   1884: dup
    //   1885: aload 10
    //   1887: getfield 89	gpa:k	Landroid/app/Activity;
    //   1890: new 361	fel
    //   1893: dup
    //   1894: aload 10
    //   1896: getfield 144	gpa:h	I
    //   1899: aload 10
    //   1901: getfield 149	gpa:e	I
    //   1904: invokespecial 362	fel:<init>	(II)V
    //   1907: invokespecial 365	com/google/android/gms/ads/internal/client/AdSizeParcel:<init>	(Landroid/content/Context;Lfel;)V
    //   1910: invokeinterface 368 2 0
    //   1915: aload_1
    //   1916: iconst_0
    //   1917: iaload
    //   1918: istore_3
    //   1919: aload_1
    //   1920: iconst_1
    //   1921: iaload
    //   1922: istore 4
    //   1924: invokestatic 132	fhk:a	()Lfhk;
    //   1927: getfield 135	fhk:c	Lgqs;
    //   1930: aload 10
    //   1932: getfield 89	gpa:k	Landroid/app/Activity;
    //   1935: invokevirtual 194	gqs:c	(Landroid/app/Activity;)[I
    //   1938: iconst_0
    //   1939: iaload
    //   1940: istore 5
    //   1942: aload 10
    //   1944: getfield 144	gpa:h	I
    //   1947: istore 6
    //   1949: aload 10
    //   1951: getfield 149	gpa:e	I
    //   1954: istore 7
    //   1956: new 370	org/json/JSONObject
    //   1959: dup
    //   1960: invokespecial 371	org/json/JSONObject:<init>	()V
    //   1963: ldc_w 373
    //   1966: iload_3
    //   1967: invokevirtual 376	org/json/JSONObject:put	(Ljava/lang/String;I)Lorg/json/JSONObject;
    //   1970: ldc_w 378
    //   1973: iload 4
    //   1975: iload 5
    //   1977: isub
    //   1978: invokevirtual 376	org/json/JSONObject:put	(Ljava/lang/String;I)Lorg/json/JSONObject;
    //   1981: ldc 119
    //   1983: iload 6
    //   1985: invokevirtual 376	org/json/JSONObject:put	(Ljava/lang/String;I)Lorg/json/JSONObject;
    //   1988: ldc -110
    //   1990: iload 7
    //   1992: invokevirtual 376	org/json/JSONObject:put	(Ljava/lang/String;I)Lorg/json/JSONObject;
    //   1995: astore_1
    //   1996: aload 10
    //   1998: getfield 383	gpj:r	Lgrq;
    //   2001: ldc_w 385
    //   2004: aload_1
    //   2005: invokeinterface 388 3 0
    //   2010: aload 10
    //   2012: ldc_w 390
    //   2015: invokevirtual 391	gpa:b	(Ljava/lang/String;)V
    //   2018: aload 9
    //   2020: monitorexit
    //   2021: return
    //   2022: aload 10
    //   2024: getfield 260	gpa:o	Landroid/widget/PopupWindow;
    //   2027: invokevirtual 394	android/widget/PopupWindow:dismiss	()V
    //   2030: goto -535 -> 1495
    //   2033: aload 10
    //   2035: ldc_w 396
    //   2038: invokevirtual 94	gpa:a	(Ljava/lang/String;)V
    //   2041: aload 9
    //   2043: monitorexit
    //   2044: return
    //   2045: iload 5
    //   2047: istore_3
    //   2048: aload 12
    //   2050: ldc -42
    //   2052: invokevirtual 218	java/lang/String:equals	(Ljava/lang/Object;)Z
    //   2055: ifeq +1027 -> 3082
    //   2058: iconst_0
    //   2059: istore_3
    //   2060: goto +1022 -> 3082
    //   2063: iload 5
    //   2065: istore_3
    //   2066: aload 12
    //   2068: ldc -36
    //   2070: invokevirtual 218	java/lang/String:equals	(Ljava/lang/Object;)Z
    //   2073: ifeq +1009 -> 3082
    //   2076: iconst_1
    //   2077: istore_3
    //   2078: goto +1004 -> 3082
    //   2081: iload 5
    //   2083: istore_3
    //   2084: aload 12
    //   2086: ldc -34
    //   2088: invokevirtual 218	java/lang/String:equals	(Ljava/lang/Object;)Z
    //   2091: ifeq +991 -> 3082
    //   2094: iconst_2
    //   2095: istore_3
    //   2096: goto +986 -> 3082
    //   2099: iload 5
    //   2101: istore_3
    //   2102: aload 12
    //   2104: ldc -32
    //   2106: invokevirtual 218	java/lang/String:equals	(Ljava/lang/Object;)Z
    //   2109: ifeq +973 -> 3082
    //   2112: iconst_3
    //   2113: istore_3
    //   2114: goto +968 -> 3082
    //   2117: iload 5
    //   2119: istore_3
    //   2120: aload 12
    //   2122: ldc -30
    //   2124: invokevirtual 218	java/lang/String:equals	(Ljava/lang/Object;)Z
    //   2127: ifeq +955 -> 3082
    //   2130: iconst_4
    //   2131: istore_3
    //   2132: goto +950 -> 3082
    //   2135: iload 5
    //   2137: istore_3
    //   2138: aload 12
    //   2140: ldc -28
    //   2142: invokevirtual 218	java/lang/String:equals	(Ljava/lang/Object;)Z
    //   2145: ifeq +937 -> 3082
    //   2148: iconst_5
    //   2149: istore_3
    //   2150: goto +932 -> 3082
    //   2153: aload 11
    //   2155: bipush 10
    //   2157: invokevirtual 337	android/widget/RelativeLayout$LayoutParams:addRule	(I)V
    //   2160: aload 11
    //   2162: bipush 9
    //   2164: invokevirtual 337	android/widget/RelativeLayout$LayoutParams:addRule	(I)V
    //   2167: goto -393 -> 1774
    //   2170: aload 11
    //   2172: bipush 10
    //   2174: invokevirtual 337	android/widget/RelativeLayout$LayoutParams:addRule	(I)V
    //   2177: aload 11
    //   2179: bipush 14
    //   2181: invokevirtual 337	android/widget/RelativeLayout$LayoutParams:addRule	(I)V
    //   2184: goto -410 -> 1774
    //   2187: aload 11
    //   2189: bipush 13
    //   2191: invokevirtual 337	android/widget/RelativeLayout$LayoutParams:addRule	(I)V
    //   2194: goto -420 -> 1774
    //   2197: aload 11
    //   2199: bipush 12
    //   2201: invokevirtual 337	android/widget/RelativeLayout$LayoutParams:addRule	(I)V
    //   2204: aload 11
    //   2206: bipush 9
    //   2208: invokevirtual 337	android/widget/RelativeLayout$LayoutParams:addRule	(I)V
    //   2211: goto -437 -> 1774
    //   2214: aload 11
    //   2216: bipush 12
    //   2218: invokevirtual 337	android/widget/RelativeLayout$LayoutParams:addRule	(I)V
    //   2221: aload 11
    //   2223: bipush 14
    //   2225: invokevirtual 337	android/widget/RelativeLayout$LayoutParams:addRule	(I)V
    //   2228: goto -454 -> 1774
    //   2231: aload 11
    //   2233: bipush 12
    //   2235: invokevirtual 337	android/widget/RelativeLayout$LayoutParams:addRule	(I)V
    //   2238: aload 11
    //   2240: bipush 11
    //   2242: invokevirtual 337	android/widget/RelativeLayout$LayoutParams:addRule	(I)V
    //   2245: goto -471 -> 1774
    //   2248: astore_1
    //   2249: aload 10
    //   2251: new 398	java/lang/StringBuilder
    //   2254: dup
    //   2255: ldc_w 400
    //   2258: invokespecial 402	java/lang/StringBuilder:<init>	(Ljava/lang/String;)V
    //   2261: aload_1
    //   2262: invokevirtual 406	java/lang/RuntimeException:getMessage	()Ljava/lang/String;
    //   2265: invokevirtual 410	java/lang/StringBuilder:append	(Ljava/lang/String;)Ljava/lang/StringBuilder;
    //   2268: invokevirtual 413	java/lang/StringBuilder:toString	()Ljava/lang/String;
    //   2271: invokevirtual 94	gpa:a	(Ljava/lang/String;)V
    //   2274: aload 10
    //   2276: getfield 294	gpa:p	Landroid/widget/RelativeLayout;
    //   2279: aload 10
    //   2281: getfield 98	gpa:j	Lgrq;
    //   2284: invokeinterface 244 1 0
    //   2289: invokevirtual 414	android/widget/RelativeLayout:removeView	(Landroid/view/View;)V
    //   2292: aload 10
    //   2294: getfield 264	gpa:q	Landroid/view/ViewGroup;
    //   2297: ifnull +49 -> 2346
    //   2300: aload 10
    //   2302: getfield 264	gpa:q	Landroid/view/ViewGroup;
    //   2305: aload 10
    //   2307: getfield 276	gpa:m	Landroid/widget/ImageView;
    //   2310: invokevirtual 256	android/view/ViewGroup:removeView	(Landroid/view/View;)V
    //   2313: aload 10
    //   2315: getfield 264	gpa:q	Landroid/view/ViewGroup;
    //   2318: aload 10
    //   2320: getfield 98	gpa:j	Lgrq;
    //   2323: invokeinterface 244 1 0
    //   2328: invokevirtual 287	android/view/ViewGroup:addView	(Landroid/view/View;)V
    //   2331: aload 10
    //   2333: getfield 98	gpa:j	Lgrq;
    //   2336: aload 10
    //   2338: getfield 284	gpa:l	Lcom/google/android/gms/ads/internal/client/AdSizeParcel;
    //   2341: invokeinterface 368 2 0
    //   2346: aload 9
    //   2348: monitorexit
    //   2349: return
    //   2350: astore_1
    //   2351: ldc_w 416
    //   2354: aload_1
    //   2355: invokestatic 419	fhe:a	(Ljava/lang/String;Ljava/lang/Throwable;)V
    //   2358: goto -348 -> 2010
    //   2361: new 421	gox
    //   2364: dup
    //   2365: aload_1
    //   2366: aload_2
    //   2367: invokespecial 423	gox:<init>	(Lgrq;Ljava/util/Map;)V
    //   2370: astore_1
    //   2371: aload_1
    //   2372: getfield 426	gox:a	Landroid/content/Context;
    //   2375: ifnonnull +11 -> 2386
    //   2378: aload_1
    //   2379: ldc_w 428
    //   2382: invokevirtual 429	gox:a	(Ljava/lang/String;)V
    //   2385: return
    //   2386: invokestatic 132	fhk:a	()Lfhk;
    //   2389: getfield 135	fhk:c	Lgqs;
    //   2392: astore_2
    //   2393: aload_1
    //   2394: getfield 426	gox:a	Landroid/content/Context;
    //   2397: invokestatic 432	gqs:c	(Landroid/content/Context;)Lgmf;
    //   2400: invokevirtual 436	gmf:b	()Z
    //   2403: ifne +11 -> 2414
    //   2406: aload_1
    //   2407: ldc_w 438
    //   2410: invokevirtual 429	gox:a	(Ljava/lang/String;)V
    //   2413: return
    //   2414: invokestatic 132	fhk:a	()Lfhk;
    //   2417: getfield 135	fhk:c	Lgqs;
    //   2420: astore_2
    //   2421: aload_1
    //   2422: getfield 426	gox:a	Landroid/content/Context;
    //   2425: invokestatic 441	gqs:b	(Landroid/content/Context;)Landroid/app/AlertDialog$Builder;
    //   2428: astore_2
    //   2429: invokestatic 132	fhk:a	()Lfhk;
    //   2432: getfield 444	fhk:f	Lgqi;
    //   2435: astore 9
    //   2437: aload_2
    //   2438: getstatic 447	fep:c	I
    //   2441: ldc_w 449
    //   2444: invokestatic 454	gqi:a	(ILjava/lang/String;)Ljava/lang/String;
    //   2447: invokevirtual 460	android/app/AlertDialog$Builder:setTitle	(Ljava/lang/CharSequence;)Landroid/app/AlertDialog$Builder;
    //   2450: pop
    //   2451: invokestatic 132	fhk:a	()Lfhk;
    //   2454: getfield 444	fhk:f	Lgqi;
    //   2457: astore 9
    //   2459: aload_2
    //   2460: getstatic 462	fep:b	I
    //   2463: ldc_w 464
    //   2466: invokestatic 454	gqi:a	(ILjava/lang/String;)Ljava/lang/String;
    //   2469: invokevirtual 467	android/app/AlertDialog$Builder:setMessage	(Ljava/lang/CharSequence;)Landroid/app/AlertDialog$Builder;
    //   2472: pop
    //   2473: invokestatic 132	fhk:a	()Lfhk;
    //   2476: getfield 444	fhk:f	Lgqi;
    //   2479: astore 9
    //   2481: aload_2
    //   2482: getstatic 469	fep:a	I
    //   2485: ldc_w 471
    //   2488: invokestatic 454	gqi:a	(ILjava/lang/String;)Ljava/lang/String;
    //   2491: new 473	goy
    //   2494: dup
    //   2495: aload_1
    //   2496: invokespecial 476	goy:<init>	(Lgox;)V
    //   2499: invokevirtual 480	android/app/AlertDialog$Builder:setPositiveButton	(Ljava/lang/CharSequence;Landroid/content/DialogInterface$OnClickListener;)Landroid/app/AlertDialog$Builder;
    //   2502: pop
    //   2503: invokestatic 132	fhk:a	()Lfhk;
    //   2506: getfield 444	fhk:f	Lgqi;
    //   2509: astore 9
    //   2511: aload_2
    //   2512: getstatic 481	fep:d	I
    //   2515: ldc_w 483
    //   2518: invokestatic 454	gqi:a	(ILjava/lang/String;)Ljava/lang/String;
    //   2521: new 485	goz
    //   2524: dup
    //   2525: aload_1
    //   2526: invokespecial 486	goz:<init>	(Lgox;)V
    //   2529: invokevirtual 489	android/app/AlertDialog$Builder:setNegativeButton	(Ljava/lang/CharSequence;Landroid/content/DialogInterface$OnClickListener;)Landroid/app/AlertDialog$Builder;
    //   2532: pop
    //   2533: aload_2
    //   2534: invokevirtual 493	android/app/AlertDialog$Builder:create	()Landroid/app/AlertDialog;
    //   2537: invokevirtual 498	android/app/AlertDialog:show	()V
    //   2540: return
    //   2541: new 500	gpd
    //   2544: dup
    //   2545: aload_1
    //   2546: aload_2
    //   2547: invokespecial 501	gpd:<init>	(Lgrq;Ljava/util/Map;)V
    //   2550: astore_1
    //   2551: aload_1
    //   2552: getfield 503	gpd:b	Landroid/content/Context;
    //   2555: ifnonnull +11 -> 2566
    //   2558: aload_1
    //   2559: ldc_w 505
    //   2562: invokevirtual 506	gpd:a	(Ljava/lang/String;)V
    //   2565: return
    //   2566: invokestatic 132	fhk:a	()Lfhk;
    //   2569: getfield 135	fhk:c	Lgqs;
    //   2572: astore_2
    //   2573: aload_1
    //   2574: getfield 503	gpd:b	Landroid/content/Context;
    //   2577: invokestatic 432	gqs:c	(Landroid/content/Context;)Lgmf;
    //   2580: invokevirtual 507	gmf:a	()Z
    //   2583: ifne +11 -> 2594
    //   2586: aload_1
    //   2587: ldc_w 509
    //   2590: invokevirtual 506	gpd:a	(Ljava/lang/String;)V
    //   2593: return
    //   2594: aload_1
    //   2595: getfield 511	gpd:a	Ljava/util/Map;
    //   2598: ldc_w 513
    //   2601: invokeinterface 63 2 0
    //   2606: checkcast 65	java/lang/String
    //   2609: astore_2
    //   2610: aload_2
    //   2611: invokestatic 127	android/text/TextUtils:isEmpty	(Ljava/lang/CharSequence;)Z
    //   2614: ifeq +11 -> 2625
    //   2617: aload_1
    //   2618: ldc_w 515
    //   2621: invokevirtual 506	gpd:a	(Ljava/lang/String;)V
    //   2624: return
    //   2625: aload_2
    //   2626: invokestatic 520	android/webkit/URLUtil:isValidUrl	(Ljava/lang/String;)Z
    //   2629: ifne +25 -> 2654
    //   2632: aload_1
    //   2633: new 398	java/lang/StringBuilder
    //   2636: dup
    //   2637: ldc_w 522
    //   2640: invokespecial 402	java/lang/StringBuilder:<init>	(Ljava/lang/String;)V
    //   2643: aload_2
    //   2644: invokevirtual 410	java/lang/StringBuilder:append	(Ljava/lang/String;)Ljava/lang/StringBuilder;
    //   2647: invokevirtual 413	java/lang/StringBuilder:toString	()Ljava/lang/String;
    //   2650: invokevirtual 506	gpd:a	(Ljava/lang/String;)V
    //   2653: return
    //   2654: aload_2
    //   2655: invokestatic 528	android/net/Uri:parse	(Ljava/lang/String;)Landroid/net/Uri;
    //   2658: invokevirtual 531	android/net/Uri:getLastPathSegment	()Ljava/lang/String;
    //   2661: astore 9
    //   2663: invokestatic 132	fhk:a	()Lfhk;
    //   2666: getfield 135	fhk:c	Lgqs;
    //   2669: astore 10
    //   2671: aload 9
    //   2673: invokestatic 533	gqs:b	(Ljava/lang/String;)Z
    //   2676: ifne +26 -> 2702
    //   2679: aload_1
    //   2680: new 398	java/lang/StringBuilder
    //   2683: dup
    //   2684: ldc_w 535
    //   2687: invokespecial 402	java/lang/StringBuilder:<init>	(Ljava/lang/String;)V
    //   2690: aload 9
    //   2692: invokevirtual 410	java/lang/StringBuilder:append	(Ljava/lang/String;)Ljava/lang/StringBuilder;
    //   2695: invokevirtual 413	java/lang/StringBuilder:toString	()Ljava/lang/String;
    //   2698: invokevirtual 506	gpd:a	(Ljava/lang/String;)V
    //   2701: return
    //   2702: invokestatic 132	fhk:a	()Lfhk;
    //   2705: getfield 135	fhk:c	Lgqs;
    //   2708: astore 10
    //   2710: aload_1
    //   2711: getfield 503	gpd:b	Landroid/content/Context;
    //   2714: invokestatic 441	gqs:b	(Landroid/content/Context;)Landroid/app/AlertDialog$Builder;
    //   2717: astore 10
    //   2719: invokestatic 132	fhk:a	()Lfhk;
    //   2722: getfield 444	fhk:f	Lgqi;
    //   2725: astore 11
    //   2727: aload 10
    //   2729: getstatic 536	fep:f	I
    //   2732: ldc_w 538
    //   2735: invokestatic 454	gqi:a	(ILjava/lang/String;)Ljava/lang/String;
    //   2738: invokevirtual 460	android/app/AlertDialog$Builder:setTitle	(Ljava/lang/CharSequence;)Landroid/app/AlertDialog$Builder;
    //   2741: pop
    //   2742: invokestatic 132	fhk:a	()Lfhk;
    //   2745: getfield 444	fhk:f	Lgqi;
    //   2748: astore 11
    //   2750: aload 10
    //   2752: getstatic 539	fep:e	I
    //   2755: ldc_w 541
    //   2758: invokestatic 454	gqi:a	(ILjava/lang/String;)Ljava/lang/String;
    //   2761: invokevirtual 467	android/app/AlertDialog$Builder:setMessage	(Ljava/lang/CharSequence;)Landroid/app/AlertDialog$Builder;
    //   2764: pop
    //   2765: invokestatic 132	fhk:a	()Lfhk;
    //   2768: getfield 444	fhk:f	Lgqi;
    //   2771: astore 11
    //   2773: aload 10
    //   2775: getstatic 469	fep:a	I
    //   2778: ldc_w 471
    //   2781: invokestatic 454	gqi:a	(ILjava/lang/String;)Ljava/lang/String;
    //   2784: new 543	gpe
    //   2787: dup
    //   2788: aload_1
    //   2789: aload_2
    //   2790: aload 9
    //   2792: invokespecial 546	gpe:<init>	(Lgpd;Ljava/lang/String;Ljava/lang/String;)V
    //   2795: invokevirtual 480	android/app/AlertDialog$Builder:setPositiveButton	(Ljava/lang/CharSequence;Landroid/content/DialogInterface$OnClickListener;)Landroid/app/AlertDialog$Builder;
    //   2798: pop
    //   2799: invokestatic 132	fhk:a	()Lfhk;
    //   2802: getfield 444	fhk:f	Lgqi;
    //   2805: astore_2
    //   2806: aload 10
    //   2808: getstatic 481	fep:d	I
    //   2811: ldc_w 483
    //   2814: invokestatic 454	gqi:a	(ILjava/lang/String;)Ljava/lang/String;
    //   2817: new 548	gpf
    //   2820: dup
    //   2821: aload_1
    //   2822: invokespecial 551	gpf:<init>	(Lgpd;)V
    //   2825: invokevirtual 489	android/app/AlertDialog$Builder:setNegativeButton	(Ljava/lang/CharSequence;Landroid/content/DialogInterface$OnClickListener;)Landroid/app/AlertDialog$Builder;
    //   2828: pop
    //   2829: aload 10
    //   2831: invokevirtual 493	android/app/AlertDialog$Builder:create	()Landroid/app/AlertDialog;
    //   2834: invokevirtual 498	android/app/AlertDialog:show	()V
    //   2837: return
    //   2838: new 553	gpc
    //   2841: dup
    //   2842: aload_1
    //   2843: aload_2
    //   2844: invokespecial 554	gpc:<init>	(Lgrq;Ljava/util/Map;)V
    //   2847: astore_1
    //   2848: aload_1
    //   2849: getfield 556	gpc:a	Lgrq;
    //   2852: ifnonnull +10 -> 2862
    //   2855: ldc_w 558
    //   2858: invokestatic 198	fhe:b	(Ljava/lang/String;)V
    //   2861: return
    //   2862: ldc_w 560
    //   2865: aload_1
    //   2866: getfield 562	gpc:c	Ljava/lang/String;
    //   2869: invokevirtual 565	java/lang/String:equalsIgnoreCase	(Ljava/lang/String;)Z
    //   2872: ifeq +24 -> 2896
    //   2875: invokestatic 132	fhk:a	()Lfhk;
    //   2878: getfield 568	fhk:e	Lgqu;
    //   2881: invokevirtual 572	gqu:b	()I
    //   2884: istore_3
    //   2885: aload_1
    //   2886: getfield 556	gpc:a	Lgrq;
    //   2889: iload_3
    //   2890: invokeinterface 574 2 0
    //   2895: return
    //   2896: ldc_w 576
    //   2899: aload_1
    //   2900: getfield 562	gpc:c	Ljava/lang/String;
    //   2903: invokevirtual 565	java/lang/String:equalsIgnoreCase	(Ljava/lang/String;)Z
    //   2906: ifeq +16 -> 2922
    //   2909: invokestatic 132	fhk:a	()Lfhk;
    //   2912: getfield 568	fhk:e	Lgqu;
    //   2915: invokevirtual 578	gqu:a	()I
    //   2918: istore_3
    //   2919: goto -34 -> 2885
    //   2922: aload_1
    //   2923: getfield 579	gpc:b	Z
    //   2926: ifeq +8 -> 2934
    //   2929: iconst_m1
    //   2930: istore_3
    //   2931: goto -46 -> 2885
    //   2934: invokestatic 132	fhk:a	()Lfhk;
    //   2937: getfield 568	fhk:e	Lgqu;
    //   2940: invokevirtual 581	gqu:c	()I
    //   2943: istore_3
    //   2944: goto -59 -> 2885
    //   2947: aload_0
    //   2948: getfield 53	gns:b	Lgpa;
    //   2951: iconst_1
    //   2952: invokevirtual 583	gpa:a	(Z)V
    //   2955: return
    //   2956: goto -1718 -> 1238
    //   2959: goto +102 -> 3061
    //   2962: iconst_0
    //   2963: istore_3
    //   2964: goto -2491 -> 473
    //   2967: iload_3
    //   2968: ifne -1845 -> 1123
    //   2971: aconst_null
    //   2972: astore_1
    //   2973: goto -2382 -> 591
    //   2976: iconst_m1
    //   2977: istore_3
    //   2978: iload_3
    //   2979: tableswitch	default:+37->3016, 0:+-2108->871, 1:+-2078->901, 2:+-2039->940, 3:+-1989->990, 4:+-1950->1029, 5:+-1902->1077
    //   3016: goto -2272 -> 744
    //   3019: iload 4
    //   3021: iflt +30 -> 3051
    //   3024: iload 4
    //   3026: bipush 50
    //   3028: iadd
    //   3029: iload 6
    //   3031: if_icmpgt +20 -> 3051
    //   3034: iload_3
    //   3035: aload_1
    //   3036: iconst_0
    //   3037: iaload
    //   3038: if_icmplt +13 -> 3051
    //   3041: iload_3
    //   3042: bipush 50
    //   3044: iadd
    //   3045: aload_1
    //   3046: iconst_1
    //   3047: iaload
    //   3048: if_icmple +8 -> 3056
    //   3051: iconst_0
    //   3052: istore_3
    //   3053: goto -86 -> 2967
    //   3056: iconst_1
    //   3057: istore_3
    //   3058: goto -91 -> 2967
    //   3061: iload 4
    //   3063: aload 11
    //   3065: iconst_0
    //   3066: iaload
    //   3067: if_icmpge -1789 -> 1278
    //   3070: aload 11
    //   3072: iconst_0
    //   3073: iaload
    //   3074: istore 4
    //   3076: goto -1838 -> 1238
    //   3079: iload 5
    //   3081: istore_3
    //   3082: iload_3
    //   3083: tableswitch	default:+37->3120, 0:+-930->2153, 1:+-913->2170, 2:+-896->2187, 3:+-886->2197, 4:+-869->2214, 5:+-852->2231
    //   3120: goto -1360 -> 1760
    //   3123: iconst_0
    //   3124: istore 8
    //   3126: goto -1527 -> 1599
    // Local variable table:
    //   start	length	slot	name	signature
    //   0	3129	0	this	gns
    //   0	3129	1	paramgrq	grq
    //   0	3129	2	paramMap	Map
    //   32	3051	3	i	int
    //   764	2311	4	j	int
    //   1	3079	5	k	int
    //   554	2478	6	m	int
    //   1954	37	7	n	int
    //   1597	1528	8	bool	boolean
    //   14	2777	9	localObject1	Object
    //   110	2720	10	localObject2	Object
    //   533	2538	11	localObject3	Object
    //   1695	444	12	localObject4	Object
    // Exception table:
    //   from	to	target	type
    //   122	140	141	finally
    //   142	145	141	finally
    //   147	170	141	finally
    //   171	197	141	finally
    //   198	221	141	finally
    //   222	265	141	finally
    //   265	308	141	finally
    //   308	351	141	finally
    //   351	394	141	finally
    //   394	430	141	finally
    //   430	455	141	finally
    //   455	471	141	finally
    //   477	487	141	finally
    //   488	497	141	finally
    //   501	508	141	finally
    //   508	518	141	finally
    //   519	550	141	finally
    //   561	581	141	finally
    //   581	586	141	finally
    //   595	605	141	finally
    //   606	625	141	finally
    //   625	630	141	finally
    //   635	659	141	finally
    //   664	744	141	finally
    //   744	778	141	finally
    //   781	791	141	finally
    //   796	806	141	finally
    //   811	821	141	finally
    //   826	836	141	finally
    //   841	851	141	finally
    //   856	866	141	finally
    //   871	898	141	finally
    //   901	937	141	finally
    //   940	987	141	finally
    //   990	1026	141	finally
    //   1029	1074	141	finally
    //   1077	1120	141	finally
    //   1123	1163	141	finally
    //   1166	1197	141	finally
    //   1202	1229	141	finally
    //   1238	1251	141	finally
    //   1254	1275	141	finally
    //   1278	1305	141	finally
    //   1308	1368	141	finally
    //   1373	1495	141	finally
    //   1495	1596	141	finally
    //   1599	1760	141	finally
    //   1760	1774	141	finally
    //   1774	1817	141	finally
    //   1817	1876	141	finally
    //   1876	1915	141	finally
    //   1924	1956	141	finally
    //   1956	2010	141	finally
    //   2010	2021	141	finally
    //   2022	2030	141	finally
    //   2033	2044	141	finally
    //   2048	2058	141	finally
    //   2066	2076	141	finally
    //   2084	2094	141	finally
    //   2102	2112	141	finally
    //   2120	2130	141	finally
    //   2138	2148	141	finally
    //   2153	2167	141	finally
    //   2170	2184	141	finally
    //   2187	2194	141	finally
    //   2197	2211	141	finally
    //   2214	2228	141	finally
    //   2231	2245	141	finally
    //   2249	2346	141	finally
    //   2346	2349	141	finally
    //   2351	2358	141	finally
    //   1817	1876	2248	java/lang/RuntimeException
    //   1956	2010	2350	org/json/JSONException
  }
}

/* Location:
 * Qualified Name:     gns
 * Java Class Version: 6 (50.0)
 * JD-Core Version:    0.7.1
 */