import android.content.Context;

@gqf
public final class grl
  extends gqk
{
  private final String a;
  private final Context d;
  private final String e;
  private String f = null;
  
  public grl(Context paramContext, String paramString1, String paramString2)
  {
    d = paramContext;
    a = paramString1;
    e = paramString2;
  }
  
  public grl(Context paramContext, String paramString1, String paramString2, String paramString3)
  {
    d = paramContext;
    a = paramString1;
    e = paramString2;
    f = paramString3;
  }
  
  /* Error */
  public final void a()
  {
    // Byte code:
    //   0: new 34	java/lang/StringBuilder
    //   3: dup
    //   4: ldc 36
    //   6: invokespecial 39	java/lang/StringBuilder:<init>	(Ljava/lang/String;)V
    //   9: aload_0
    //   10: getfield 24	grl:e	Ljava/lang/String;
    //   13: invokevirtual 43	java/lang/StringBuilder:append	(Ljava/lang/String;)Ljava/lang/StringBuilder;
    //   16: pop
    //   17: iconst_2
    //   18: invokestatic 48	fhe:a	(I)Z
    //   21: pop
    //   22: new 50	java/net/URL
    //   25: dup
    //   26: aload_0
    //   27: getfield 24	grl:e	Ljava/lang/String;
    //   30: invokespecial 51	java/net/URL:<init>	(Ljava/lang/String;)V
    //   33: invokevirtual 55	java/net/URL:openConnection	()Ljava/net/URLConnection;
    //   36: checkcast 57	java/net/HttpURLConnection
    //   39: astore_2
    //   40: aload_0
    //   41: getfield 18	grl:f	Ljava/lang/String;
    //   44: invokestatic 63	android/text/TextUtils:isEmpty	(Ljava/lang/CharSequence;)Z
    //   47: ifeq +77 -> 124
    //   50: invokestatic 68	fhk:a	()Lfhk;
    //   53: getfield 72	fhk:c	Lgqs;
    //   56: aload_0
    //   57: getfield 20	grl:d	Landroid/content/Context;
    //   60: aload_0
    //   61: getfield 22	grl:a	Ljava/lang/String;
    //   64: iconst_1
    //   65: aload_2
    //   66: invokevirtual 77	gqs:a	(Landroid/content/Context;Ljava/lang/String;ZLjava/net/HttpURLConnection;)V
    //   69: aload_2
    //   70: invokevirtual 81	java/net/HttpURLConnection:getResponseCode	()I
    //   73: istore_1
    //   74: iload_1
    //   75: sipush 200
    //   78: if_icmplt +10 -> 88
    //   81: iload_1
    //   82: sipush 300
    //   85: if_icmplt +34 -> 119
    //   88: new 34	java/lang/StringBuilder
    //   91: dup
    //   92: ldc 83
    //   94: invokespecial 39	java/lang/StringBuilder:<init>	(Ljava/lang/String;)V
    //   97: iload_1
    //   98: invokevirtual 86	java/lang/StringBuilder:append	(I)Ljava/lang/StringBuilder;
    //   101: ldc 88
    //   103: invokevirtual 43	java/lang/StringBuilder:append	(Ljava/lang/String;)Ljava/lang/StringBuilder;
    //   106: aload_0
    //   107: getfield 24	grl:e	Ljava/lang/String;
    //   110: invokevirtual 43	java/lang/StringBuilder:append	(Ljava/lang/String;)Ljava/lang/StringBuilder;
    //   113: invokevirtual 92	java/lang/StringBuilder:toString	()Ljava/lang/String;
    //   116: invokestatic 95	fhe:b	(Ljava/lang/String;)V
    //   119: aload_2
    //   120: invokevirtual 98	java/net/HttpURLConnection:disconnect	()V
    //   123: return
    //   124: invokestatic 68	fhk:a	()Lfhk;
    //   127: getfield 72	fhk:c	Lgqs;
    //   130: astore_3
    //   131: aload_2
    //   132: aload_0
    //   133: getfield 18	grl:f	Ljava/lang/String;
    //   136: invokestatic 101	gqs:a	(Ljava/net/HttpURLConnection;Ljava/lang/String;)V
    //   139: goto -70 -> 69
    //   142: astore_3
    //   143: aload_2
    //   144: invokevirtual 98	java/net/HttpURLConnection:disconnect	()V
    //   147: aload_3
    //   148: athrow
    //   149: astore_2
    //   150: new 34	java/lang/StringBuilder
    //   153: dup
    //   154: ldc 103
    //   156: invokespecial 39	java/lang/StringBuilder:<init>	(Ljava/lang/String;)V
    //   159: aload_0
    //   160: getfield 24	grl:e	Ljava/lang/String;
    //   163: invokevirtual 43	java/lang/StringBuilder:append	(Ljava/lang/String;)Ljava/lang/StringBuilder;
    //   166: ldc 105
    //   168: invokevirtual 43	java/lang/StringBuilder:append	(Ljava/lang/String;)Ljava/lang/StringBuilder;
    //   171: aload_2
    //   172: invokevirtual 108	java/lang/IndexOutOfBoundsException:getMessage	()Ljava/lang/String;
    //   175: invokevirtual 43	java/lang/StringBuilder:append	(Ljava/lang/String;)Ljava/lang/StringBuilder;
    //   178: invokevirtual 92	java/lang/StringBuilder:toString	()Ljava/lang/String;
    //   181: invokestatic 95	fhe:b	(Ljava/lang/String;)V
    //   184: return
    //   185: astore_2
    //   186: new 34	java/lang/StringBuilder
    //   189: dup
    //   190: ldc 110
    //   192: invokespecial 39	java/lang/StringBuilder:<init>	(Ljava/lang/String;)V
    //   195: aload_0
    //   196: getfield 24	grl:e	Ljava/lang/String;
    //   199: invokevirtual 43	java/lang/StringBuilder:append	(Ljava/lang/String;)Ljava/lang/StringBuilder;
    //   202: ldc 105
    //   204: invokevirtual 43	java/lang/StringBuilder:append	(Ljava/lang/String;)Ljava/lang/StringBuilder;
    //   207: aload_2
    //   208: invokevirtual 111	java/io/IOException:getMessage	()Ljava/lang/String;
    //   211: invokevirtual 43	java/lang/StringBuilder:append	(Ljava/lang/String;)Ljava/lang/StringBuilder;
    //   214: invokevirtual 92	java/lang/StringBuilder:toString	()Ljava/lang/String;
    //   217: invokestatic 95	fhe:b	(Ljava/lang/String;)V
    //   220: return
    //   221: astore_2
    //   222: new 34	java/lang/StringBuilder
    //   225: dup
    //   226: ldc 110
    //   228: invokespecial 39	java/lang/StringBuilder:<init>	(Ljava/lang/String;)V
    //   231: aload_0
    //   232: getfield 24	grl:e	Ljava/lang/String;
    //   235: invokevirtual 43	java/lang/StringBuilder:append	(Ljava/lang/String;)Ljava/lang/StringBuilder;
    //   238: ldc 105
    //   240: invokevirtual 43	java/lang/StringBuilder:append	(Ljava/lang/String;)Ljava/lang/StringBuilder;
    //   243: aload_2
    //   244: invokevirtual 112	java/lang/RuntimeException:getMessage	()Ljava/lang/String;
    //   247: invokevirtual 43	java/lang/StringBuilder:append	(Ljava/lang/String;)Ljava/lang/StringBuilder;
    //   250: invokevirtual 92	java/lang/StringBuilder:toString	()Ljava/lang/String;
    //   253: invokestatic 95	fhe:b	(Ljava/lang/String;)V
    //   256: return
    // Local variable table:
    //   start	length	slot	name	signature
    //   0	257	0	this	grl
    //   73	25	1	i	int
    //   39	105	2	localHttpURLConnection	java.net.HttpURLConnection
    //   149	23	2	localIndexOutOfBoundsException	IndexOutOfBoundsException
    //   185	23	2	localIOException	java.io.IOException
    //   221	23	2	localRuntimeException	RuntimeException
    //   130	1	3	localgqs	gqs
    //   142	6	3	localObject	Object
    // Exception table:
    //   from	to	target	type
    //   40	69	142	finally
    //   69	74	142	finally
    //   88	119	142	finally
    //   124	139	142	finally
    //   0	40	149	java/lang/IndexOutOfBoundsException
    //   119	123	149	java/lang/IndexOutOfBoundsException
    //   143	149	149	java/lang/IndexOutOfBoundsException
    //   0	40	185	java/io/IOException
    //   119	123	185	java/io/IOException
    //   143	149	185	java/io/IOException
    //   0	40	221	java/lang/RuntimeException
    //   119	123	221	java/lang/RuntimeException
    //   143	149	221	java/lang/RuntimeException
  }
}

/* Location:
 * Qualified Name:     grl
 * Java Class Version: 6 (50.0)
 * JD-Core Version:    0.7.1
 */