final class gwp
  implements Runnable
{
  gwp(gwn paramgwn, String paramString, byte[] paramArrayOfByte) {}
  
  /* Error */
  public final void run()
  {
    // Byte code:
    //   0: aload_0
    //   1: getfield 16	gwp:c	Lgwn;
    //   4: astore_2
    //   5: aload_0
    //   6: getfield 18	gwp:a	Ljava/lang/String;
    //   9: astore_1
    //   10: aload_0
    //   11: getfield 20	gwp:b	[B
    //   14: astore_3
    //   15: aload_2
    //   16: aload_1
    //   17: invokevirtual 34	gwn:b	(Ljava/lang/String;)Ljava/io/File;
    //   20: astore 4
    //   22: new 36	java/io/FileOutputStream
    //   25: dup
    //   26: aload 4
    //   28: invokespecial 39	java/io/FileOutputStream:<init>	(Ljava/io/File;)V
    //   31: astore_2
    //   32: aload_2
    //   33: aload_3
    //   34: invokevirtual 43	java/io/FileOutputStream:write	([B)V
    //   37: aload_2
    //   38: invokevirtual 46	java/io/FileOutputStream:close	()V
    //   41: new 48	java/lang/StringBuilder
    //   44: dup
    //   45: ldc 50
    //   47: invokespecial 53	java/lang/StringBuilder:<init>	(Ljava/lang/String;)V
    //   50: aload_1
    //   51: invokevirtual 57	java/lang/StringBuilder:append	(Ljava/lang/String;)Ljava/lang/StringBuilder;
    //   54: ldc 59
    //   56: invokevirtual 57	java/lang/StringBuilder:append	(Ljava/lang/String;)Ljava/lang/StringBuilder;
    //   59: pop
    //   60: invokestatic 63	hav:b	()V
    //   63: return
    //   64: astore_1
    //   65: ldc 65
    //   67: invokestatic 67	hav:a	(Ljava/lang/String;)V
    //   70: return
    //   71: astore_1
    //   72: ldc 69
    //   74: invokestatic 67	hav:a	(Ljava/lang/String;)V
    //   77: return
    //   78: astore_3
    //   79: ldc 71
    //   81: invokestatic 67	hav:a	(Ljava/lang/String;)V
    //   84: aload 4
    //   86: invokevirtual 77	java/io/File:delete	()Z
    //   89: pop
    //   90: aload_2
    //   91: invokevirtual 46	java/io/FileOutputStream:close	()V
    //   94: new 48	java/lang/StringBuilder
    //   97: dup
    //   98: ldc 50
    //   100: invokespecial 53	java/lang/StringBuilder:<init>	(Ljava/lang/String;)V
    //   103: aload_1
    //   104: invokevirtual 57	java/lang/StringBuilder:append	(Ljava/lang/String;)Ljava/lang/StringBuilder;
    //   107: ldc 59
    //   109: invokevirtual 57	java/lang/StringBuilder:append	(Ljava/lang/String;)Ljava/lang/StringBuilder;
    //   112: pop
    //   113: invokestatic 63	hav:b	()V
    //   116: return
    //   117: astore_1
    //   118: ldc 69
    //   120: invokestatic 67	hav:a	(Ljava/lang/String;)V
    //   123: return
    //   124: astore_3
    //   125: aload_2
    //   126: invokevirtual 46	java/io/FileOutputStream:close	()V
    //   129: new 48	java/lang/StringBuilder
    //   132: dup
    //   133: ldc 50
    //   135: invokespecial 53	java/lang/StringBuilder:<init>	(Ljava/lang/String;)V
    //   138: aload_1
    //   139: invokevirtual 57	java/lang/StringBuilder:append	(Ljava/lang/String;)Ljava/lang/StringBuilder;
    //   142: ldc 59
    //   144: invokevirtual 57	java/lang/StringBuilder:append	(Ljava/lang/String;)Ljava/lang/StringBuilder;
    //   147: pop
    //   148: invokestatic 63	hav:b	()V
    //   151: aload_3
    //   152: athrow
    //   153: astore_1
    //   154: ldc 69
    //   156: invokestatic 67	hav:a	(Ljava/lang/String;)V
    //   159: goto -8 -> 151
    // Local variable table:
    //   start	length	slot	name	signature
    //   0	162	0	this	gwp
    //   9	42	1	str	String
    //   64	1	1	localFileNotFoundException	java.io.FileNotFoundException
    //   71	33	1	localIOException1	java.io.IOException
    //   117	22	1	localIOException2	java.io.IOException
    //   153	1	1	localIOException3	java.io.IOException
    //   4	122	2	localObject1	Object
    //   14	20	3	arrayOfByte	byte[]
    //   78	1	3	localIOException4	java.io.IOException
    //   124	28	3	localObject2	Object
    //   20	65	4	localFile	java.io.File
    // Exception table:
    //   from	to	target	type
    //   22	32	64	java/io/FileNotFoundException
    //   37	63	71	java/io/IOException
    //   32	37	78	java/io/IOException
    //   90	116	117	java/io/IOException
    //   32	37	124	finally
    //   79	90	124	finally
    //   125	151	153	java/io/IOException
  }
}

/* Location:
 * Qualified Name:     gwp
 * Java Class Version: 6 (50.0)
 * JD-Core Version:    0.7.1
 */