import android.text.TextUtils;
import java.util.regex.Pattern;

public final class ivf
{
  private Pattern a;
  private boolean b;
  private boolean c;
  private boolean d;
  private boolean e;
  private boolean f;
  private int g;
  private boolean h;
  private boolean i;
  
  public final Pattern a()
  {
    try
    {
      Pattern localPattern = a;
      return localPattern;
    }
    finally
    {
      localObject = finally;
      throw ((Throwable)localObject);
    }
  }
  
  public final void a(pwd parampwd)
  {
    if (parampwd == null) {}
    for (;;)
    {
      return;
      try
      {
        if (!TextUtils.isEmpty(a)) {
          a = Pattern.compile(a);
        }
        b = b;
        c = c;
        f = f;
        d = g;
        e = h;
        g = e;
        h = d;
        i = i;
      }
      finally {}
    }
  }
  
  /* Error */
  public final boolean b()
  {
    // Byte code:
    //   0: aload_0
    //   1: monitorenter
    //   2: aload_0
    //   3: getfield 45	ivf:b	Z
    //   6: ifeq +18 -> 24
    //   9: aload_0
    //   10: getfield 48	ivf:c	Z
    //   13: istore_1
    //   14: iload_1
    //   15: ifeq +9 -> 24
    //   18: iconst_1
    //   19: istore_1
    //   20: aload_0
    //   21: monitorexit
    //   22: iload_1
    //   23: ireturn
    //   24: iconst_0
    //   25: istore_1
    //   26: goto -6 -> 20
    //   29: astore_2
    //   30: aload_0
    //   31: monitorexit
    //   32: aload_2
    //   33: athrow
    // Local variable table:
    //   start	length	slot	name	signature
    //   0	34	0	this	ivf
    //   13	13	1	bool	boolean
    //   29	4	2	localObject	Object
    // Exception table:
    //   from	to	target	type
    //   2	14	29	finally
  }
  
  public final boolean c()
  {
    try
    {
      boolean bool = d;
      return bool;
    }
    finally
    {
      localObject = finally;
      throw ((Throwable)localObject);
    }
  }
  
  public final boolean d()
  {
    try
    {
      boolean bool = e;
      return bool;
    }
    finally
    {
      localObject = finally;
      throw ((Throwable)localObject);
    }
  }
  
  public final boolean e()
  {
    try
    {
      boolean bool = f;
      return bool;
    }
    finally
    {
      localObject = finally;
      throw ((Throwable)localObject);
    }
  }
  
  public final int f()
  {
    try
    {
      int j = g;
      return j;
    }
    finally
    {
      localObject = finally;
      throw ((Throwable)localObject);
    }
  }
  
  public final boolean g()
  {
    try
    {
      boolean bool = h;
      return bool;
    }
    finally
    {
      localObject = finally;
      throw ((Throwable)localObject);
    }
  }
  
  public final boolean h()
  {
    try
    {
      boolean bool = i;
      return bool;
    }
    finally
    {
      localObject = finally;
      throw ((Throwable)localObject);
    }
  }
}

/* Location:
 * Qualified Name:     ivf
 * Java Class Version: 6 (50.0)
 * JD-Core Version:    0.7.1
 */