public final class jlo
{
  private jrp a;
  private jlq b;
  private boolean c;
  
  public jlo(jrp paramjrp)
  {
    a = ((jrp)jju.a(paramjrp));
    b = null;
    c = true;
  }
  
  /* Error */
  public final void a(jlq paramjlq)
  {
    // Byte code:
    //   0: aload_0
    //   1: monitorenter
    //   2: aload_1
    //   3: invokestatic 20	jju:a	(Ljava/lang/Object;)Ljava/lang/Object;
    //   6: pop
    //   7: aload_0
    //   8: getfield 28	jlo:c	Z
    //   11: istore_2
    //   12: iload_2
    //   13: ifne +6 -> 19
    //   16: aload_0
    //   17: monitorexit
    //   18: return
    //   19: aload_0
    //   20: getfield 26	jlo:b	Ljlq;
    //   23: ifnull +20 -> 43
    //   26: aload_1
    //   27: getfield 35	jlq:a	Ljlg;
    //   30: aload_0
    //   31: getfield 26	jlo:b	Ljlq;
    //   34: getfield 35	jlq:a	Ljlg;
    //   37: invokevirtual 41	jlg:equals	(Ljava/lang/Object;)Z
    //   40: ifeq -24 -> 16
    //   43: aload_0
    //   44: aload_1
    //   45: putfield 26	jlo:b	Ljlq;
    //   48: goto -32 -> 16
    //   51: astore_1
    //   52: aload_0
    //   53: monitorexit
    //   54: aload_1
    //   55: athrow
    // Local variable table:
    //   start	length	slot	name	signature
    //   0	56	0	this	jlo
    //   0	56	1	paramjlq	jlq
    //   11	2	2	bool	boolean
    // Exception table:
    //   from	to	target	type
    //   2	12	51	finally
    //   19	43	51	finally
    //   43	48	51	finally
  }
  
  public final boolean a()
  {
    try
    {
      boolean bool = c;
      return bool;
    }
    finally
    {
      localObject = finally;
      throw ((Throwable)localObject);
    }
  }
  
  public final void b()
  {
    try
    {
      c = true;
      return;
    }
    finally
    {
      localObject = finally;
      throw ((Throwable)localObject);
    }
  }
  
  public final void c()
  {
    try
    {
      c = false;
      e();
      return;
    }
    finally
    {
      localObject = finally;
      throw ((Throwable)localObject);
    }
  }
  
  /* Error */
  public final jlq d()
  {
    // Byte code:
    //   0: aload_0
    //   1: monitorenter
    //   2: aload_0
    //   3: getfield 26	jlo:b	Ljlq;
    //   6: ifnull +38 -> 44
    //   9: aload_0
    //   10: getfield 26	jlo:b	Ljlq;
    //   13: getfield 35	jlq:a	Ljlg;
    //   16: astore_2
    //   17: aload_0
    //   18: getfield 24	jlo:a	Ljrp;
    //   21: invokeinterface 50 1 0
    //   26: aload_2
    //   27: getfield 53	jlg:b	J
    //   30: lcmp
    //   31: ifle +22 -> 53
    //   34: iconst_1
    //   35: istore_1
    //   36: iload_1
    //   37: ifeq +7 -> 44
    //   40: aload_0
    //   41: invokevirtual 45	jlo:e	()V
    //   44: aload_0
    //   45: getfield 26	jlo:b	Ljlq;
    //   48: astore_2
    //   49: aload_0
    //   50: monitorexit
    //   51: aload_2
    //   52: areturn
    //   53: iconst_0
    //   54: istore_1
    //   55: goto -19 -> 36
    //   58: astore_2
    //   59: aload_0
    //   60: monitorexit
    //   61: aload_2
    //   62: athrow
    // Local variable table:
    //   start	length	slot	name	signature
    //   0	63	0	this	jlo
    //   35	20	1	i	int
    //   16	36	2	localObject1	Object
    //   58	4	2	localObject2	Object
    // Exception table:
    //   from	to	target	type
    //   2	34	58	finally
    //   40	44	58	finally
    //   44	49	58	finally
  }
  
  public final void e()
  {
    try
    {
      b = null;
      return;
    }
    finally
    {
      localObject = finally;
      throw ((Throwable)localObject);
    }
  }
}

/* Location:
 * Qualified Name:     jlo
 * Java Class Version: 6 (50.0)
 * JD-Core Version:    0.7.1
 */