final class moe
  extends Thread
{
  moe(mod parammod, String paramString)
  {
    super(paramString);
  }
  
  /* Error */
  public final void run()
  {
    // Byte code:
    //   0: aload_0
    //   1: getfield 10	moe:a	Lmod;
    //   4: getfield 26	mod:d	Ljava/util/concurrent/atomic/AtomicBoolean;
    //   7: iconst_0
    //   8: invokevirtual 32	java/util/concurrent/atomic/AtomicBoolean:set	(Z)V
    //   11: aload_0
    //   12: getfield 10	moe:a	Lmod;
    //   15: getfield 36	mod:k	Z
    //   18: ifeq +19 -> 37
    //   21: aload_0
    //   22: getfield 10	moe:a	Lmod;
    //   25: iconst_0
    //   26: putfield 36	mod:k	Z
    //   29: aload_0
    //   30: getfield 10	moe:a	Lmod;
    //   33: iconst_0
    //   34: invokevirtual 39	mod:b	(Z)V
    //   37: new 41	mof
    //   40: dup
    //   41: aload_0
    //   42: getfield 10	moe:a	Lmod;
    //   45: ldc 43
    //   47: aconst_null
    //   48: invokespecial 46	mof:<init>	(Lmod;Ljava/lang/String;Ljava/util/concurrent/CountDownLatch;)V
    //   51: invokevirtual 49	mof:start	()V
    //   54: aload_0
    //   55: getfield 10	moe:a	Lmod;
    //   58: astore_2
    //   59: aload_2
    //   60: aload_2
    //   61: getfield 52	mod:b	Lmnr;
    //   64: aload_2
    //   65: getfield 56	mod:h	Lmnz;
    //   68: invokeinterface 61 2 0
    //   73: putfield 65	mod:g	Lmoo;
    //   76: aload_2
    //   77: getfield 65	mod:g	Lmoo;
    //   80: aload_2
    //   81: getfield 69	mod:e	Lmop;
    //   84: invokeinterface 74 2 0
    //   89: aload_2
    //   90: getfield 65	mod:g	Lmoo;
    //   93: invokeinterface 76 1 0
    //   98: aload_2
    //   99: iconst_1
    //   100: invokevirtual 79	mod:c	(Z)V
    //   103: aload_2
    //   104: invokevirtual 81	mod:b	()V
    //   107: aload_2
    //   108: new 83	mog
    //   111: dup
    //   112: aload_2
    //   113: ldc 85
    //   115: invokespecial 87	mog:<init>	(Lmod;Ljava/lang/String;)V
    //   118: putfield 91	mod:i	Ljava/lang/Thread;
    //   121: aload_2
    //   122: getfield 91	mod:i	Ljava/lang/Thread;
    //   125: invokevirtual 92	java/lang/Thread:start	()V
    //   128: aload_0
    //   129: getfield 10	moe:a	Lmod;
    //   132: getfield 36	mod:k	Z
    //   135: ifeq +10 -> 145
    //   138: aload_0
    //   139: getfield 10	moe:a	Lmod;
    //   142: invokevirtual 94	mod:c	()V
    //   145: aload_0
    //   146: getfield 10	moe:a	Lmod;
    //   149: iconst_0
    //   150: invokevirtual 96	mod:d	(Z)V
    //   153: aload_0
    //   154: getfield 10	moe:a	Lmod;
    //   157: getfield 100	mod:n	Ljava/util/concurrent/CountDownLatch;
    //   160: invokevirtual 105	java/util/concurrent/CountDownLatch:countDown	()V
    //   163: return
    //   164: astore_3
    //   165: aload_3
    //   166: getfield 108	mos:a	I
    //   169: istore_1
    //   170: new 110	java/lang/StringBuilder
    //   173: dup
    //   174: bipush 53
    //   176: invokespecial 113	java/lang/StringBuilder:<init>	(I)V
    //   179: ldc 115
    //   181: invokevirtual 119	java/lang/StringBuilder:append	(Ljava/lang/String;)Ljava/lang/StringBuilder;
    //   184: iload_1
    //   185: invokevirtual 122	java/lang/StringBuilder:append	(I)Ljava/lang/StringBuilder;
    //   188: invokevirtual 126	java/lang/StringBuilder:toString	()Ljava/lang/String;
    //   191: aload_3
    //   192: invokestatic 131	jst:a	(Ljava/lang/String;Ljava/lang/Throwable;)V
    //   195: aload_3
    //   196: getfield 108	mos:a	I
    //   199: tableswitch	default:+75->274, 401:+53->252, 402:+25->224, 403:+53->252
    //   224: aload_2
    //   225: invokevirtual 133	mod:d	()V
    //   228: goto -100 -> 128
    //   231: astore_2
    //   232: aload_0
    //   233: getfield 10	moe:a	Lmod;
    //   236: iconst_0
    //   237: invokevirtual 96	mod:d	(Z)V
    //   240: aload_0
    //   241: getfield 10	moe:a	Lmod;
    //   244: getfield 100	mod:n	Ljava/util/concurrent/CountDownLatch;
    //   247: invokevirtual 105	java/util/concurrent/CountDownLatch:countDown	()V
    //   250: aload_2
    //   251: athrow
    //   252: aload_2
    //   253: iconst_0
    //   254: invokevirtual 135	mod:a	(Z)V
    //   257: goto -33 -> 224
    //   260: astore_3
    //   261: ldc -119
    //   263: aload_3
    //   264: invokestatic 131	jst:a	(Ljava/lang/String;Ljava/lang/Throwable;)V
    //   267: aload_2
    //   268: invokevirtual 133	mod:d	()V
    //   271: goto -143 -> 128
    //   274: goto -50 -> 224
    // Local variable table:
    //   start	length	slot	name	signature
    //   0	277	0	this	moe
    //   169	16	1	i	int
    //   58	167	2	localmod	mod
    //   231	37	2	localObject	Object
    //   164	32	3	localmos	mos
    //   260	4	3	localException	Exception
    // Exception table:
    //   from	to	target	type
    //   59	107	164	mos
    //   0	37	231	finally
    //   37	59	231	finally
    //   59	107	231	finally
    //   107	128	231	finally
    //   128	145	231	finally
    //   165	224	231	finally
    //   224	228	231	finally
    //   252	257	231	finally
    //   261	271	231	finally
    //   59	107	260	java/lang/Exception
  }
}

/* Location:
 * Qualified Name:     moe
 * Java Class Version: 6 (50.0)
 * JD-Core Version:    0.7.1
 */