import java.util.concurrent.Callable;

final class moh
  implements Callable
{
  moh(mod parammod) {}
  
  /* Error */
  private final Void a()
  {
    // Byte code:
    //   0: iconst_1
    //   1: istore_1
    //   2: aload_0
    //   3: getfield 12	moh:a	Lmod;
    //   6: getfield 27	mod:f	Lmok;
    //   9: astore 4
    //   11: invokestatic 33	java/lang/System:currentTimeMillis	()J
    //   14: aload 4
    //   16: getfield 39	mok:e	J
    //   19: lsub
    //   20: getstatic 42	mok:a	I
    //   23: i2l
    //   24: lcmp
    //   25: ifle +96 -> 121
    //   28: iload_1
    //   29: ifeq +97 -> 126
    //   32: getstatic 48	java/util/Locale:US	Ljava/util/Locale;
    //   35: ldc 50
    //   37: iconst_2
    //   38: anewarray 4	java/lang/Object
    //   41: dup
    //   42: iconst_0
    //   43: aload_0
    //   44: getfield 12	moh:a	Lmod;
    //   47: getfield 27	mod:f	Lmok;
    //   50: getfield 54	mok:c	Lmsg;
    //   53: aload_0
    //   54: getfield 12	moh:a	Lmod;
    //   57: getfield 27	mod:f	Lmok;
    //   60: getfield 58	mok:d	Lmsj;
    //   63: invokevirtual 64	msj:toString	()Ljava/lang/String;
    //   66: invokestatic 69	mxy:a	(Lmsg;Ljava/lang/String;)Ljava/lang/String;
    //   69: aastore
    //   70: dup
    //   71: iconst_1
    //   72: getstatic 42	mok:a	I
    //   75: invokestatic 75	java/lang/Integer:valueOf	(I)Ljava/lang/Integer;
    //   78: aastore
    //   79: invokestatic 81	java/lang/String:format	(Ljava/util/Locale;Ljava/lang/String;[Ljava/lang/Object;)Ljava/lang/String;
    //   82: pop
    //   83: aload_0
    //   84: getfield 12	moh:a	Lmod;
    //   87: getfield 84	mod:c	Ljava/util/Queue;
    //   90: invokeinterface 90 1 0
    //   95: pop
    //   96: aload_0
    //   97: getfield 12	moh:a	Lmod;
    //   100: getfield 27	mod:f	Lmok;
    //   103: getfield 94	mok:b	Ljava/util/List;
    //   106: getstatic 98	mny:c	I
    //   109: invokestatic 101	mod:a	(Ljava/util/List;I)V
    //   112: aload_0
    //   113: getfield 12	moh:a	Lmod;
    //   116: invokevirtual 103	mod:c	()V
    //   119: aconst_null
    //   120: areturn
    //   121: iconst_0
    //   122: istore_1
    //   123: goto -95 -> 28
    //   126: aload_0
    //   127: getfield 12	moh:a	Lmod;
    //   130: astore 5
    //   132: aload_0
    //   133: getfield 12	moh:a	Lmod;
    //   136: getfield 27	mod:f	Lmok;
    //   139: getfield 54	mok:c	Lmsg;
    //   142: astore 6
    //   144: aload_0
    //   145: getfield 12	moh:a	Lmod;
    //   148: getfield 27	mod:f	Lmok;
    //   151: getfield 58	mok:d	Lmsj;
    //   154: astore 7
    //   156: aload_0
    //   157: getfield 12	moh:a	Lmod;
    //   160: getfield 27	mod:f	Lmok;
    //   163: getfield 94	mok:b	Ljava/util/List;
    //   166: astore 4
    //   168: aload 5
    //   170: getfield 107	mod:n	Ljava/util/concurrent/CountDownLatch;
    //   173: invokevirtual 112	java/util/concurrent/CountDownLatch:getCount	()J
    //   176: lconst_0
    //   177: lcmp
    //   178: ifne +18 -> 196
    //   181: aload 5
    //   183: getfield 115	mod:o	Ljava/util/concurrent/CountDownLatch;
    //   186: invokevirtual 112	java/util/concurrent/CountDownLatch:getCount	()J
    //   189: lstore_2
    //   190: lload_2
    //   191: lconst_0
    //   192: lcmp
    //   193: ifeq +34 -> 227
    //   196: aload 5
    //   198: getfield 115	mod:o	Ljava/util/concurrent/CountDownLatch;
    //   201: getstatic 42	mok:a	I
    //   204: i2l
    //   205: getstatic 121	java/util/concurrent/TimeUnit:MILLISECONDS	Ljava/util/concurrent/TimeUnit;
    //   208: invokevirtual 125	java/util/concurrent/CountDownLatch:await	(JLjava/util/concurrent/TimeUnit;)Z
    //   211: pop
    //   212: aload 5
    //   214: getfield 107	mod:n	Ljava/util/concurrent/CountDownLatch;
    //   217: ldc2_w 126
    //   220: getstatic 130	java/util/concurrent/TimeUnit:SECONDS	Ljava/util/concurrent/TimeUnit;
    //   223: invokevirtual 125	java/util/concurrent/CountDownLatch:await	(JLjava/util/concurrent/TimeUnit;)Z
    //   226: pop
    //   227: aload 5
    //   229: getfield 134	mod:k	Z
    //   232: ifne +120 -> 352
    //   235: aload 5
    //   237: getfield 84	mod:c	Ljava/util/Queue;
    //   240: invokeinterface 90 1 0
    //   245: pop
    //   246: getstatic 136	mny:b	I
    //   249: istore_1
    //   250: aload 4
    //   252: invokestatic 139	mod:a	(Ljava/util/List;)V
    //   255: getstatic 48	java/util/Locale:US	Ljava/util/Locale;
    //   258: astore 8
    //   260: aload 6
    //   262: aload 7
    //   264: invokevirtual 64	msj:toString	()Ljava/lang/String;
    //   267: invokestatic 69	mxy:a	(Lmsg;Ljava/lang/String;)Ljava/lang/String;
    //   270: astore 6
    //   272: aload 5
    //   274: invokevirtual 142	mod:a	()Z
    //   277: ifeq +68 -> 345
    //   280: ldc -112
    //   282: astore 4
    //   284: aload 8
    //   286: ldc -110
    //   288: iconst_2
    //   289: anewarray 4	java/lang/Object
    //   292: dup
    //   293: iconst_0
    //   294: aload 6
    //   296: aastore
    //   297: dup
    //   298: iconst_1
    //   299: aload 4
    //   301: aastore
    //   302: invokestatic 81	java/lang/String:format	(Ljava/util/Locale;Ljava/lang/String;[Ljava/lang/Object;)Ljava/lang/String;
    //   305: pop
    //   306: aload_0
    //   307: getfield 12	moh:a	Lmod;
    //   310: getfield 150	mod:p	Ljava/util/concurrent/ScheduledFuture;
    //   313: ifnull -201 -> 112
    //   316: aload_0
    //   317: getfield 12	moh:a	Lmod;
    //   320: getfield 150	mod:p	Ljava/util/concurrent/ScheduledFuture;
    //   323: iconst_1
    //   324: invokeinterface 156 2 0
    //   329: pop
    //   330: goto -218 -> 112
    //   333: astore 4
    //   335: aload_0
    //   336: getfield 12	moh:a	Lmod;
    //   339: invokevirtual 103	mod:c	()V
    //   342: aload 4
    //   344: athrow
    //   345: ldc -98
    //   347: astore 4
    //   349: goto -65 -> 284
    //   352: aload 5
    //   354: getfield 162	mod:g	Lmoo;
    //   357: aload 6
    //   359: aload 7
    //   361: invokeinterface 167 3 0
    //   366: sipush 200
    //   369: if_icmpne +145 -> 514
    //   372: aload 5
    //   374: getfield 84	mod:c	Ljava/util/Queue;
    //   377: invokeinterface 90 1 0
    //   382: pop
    //   383: aload 5
    //   385: iconst_0
    //   386: putfield 170	mod:m	I
    //   389: aload 4
    //   391: invokeinterface 176 1 0
    //   396: astore 4
    //   398: aload 4
    //   400: invokeinterface 181 1 0
    //   405: ifeq -99 -> 306
    //   408: aload 4
    //   410: invokeinterface 184 1 0
    //   415: checkcast 186	mnx
    //   418: astore 8
    //   420: getstatic 187	mny:a	I
    //   423: istore_1
    //   424: goto -26 -> 398
    //   427: astore 9
    //   429: aload 8
    //   431: invokestatic 190	java/lang/String:valueOf	(Ljava/lang/Object;)Ljava/lang/String;
    //   434: astore 8
    //   436: new 192	java/lang/StringBuilder
    //   439: dup
    //   440: aload 8
    //   442: invokestatic 190	java/lang/String:valueOf	(Ljava/lang/Object;)Ljava/lang/String;
    //   445: invokevirtual 196	java/lang/String:length	()I
    //   448: bipush 36
    //   450: iadd
    //   451: invokespecial 199	java/lang/StringBuilder:<init>	(I)V
    //   454: ldc -55
    //   456: invokevirtual 205	java/lang/StringBuilder:append	(Ljava/lang/String;)Ljava/lang/StringBuilder;
    //   459: aload 8
    //   461: invokevirtual 205	java/lang/StringBuilder:append	(Ljava/lang/String;)Ljava/lang/StringBuilder;
    //   464: ldc -49
    //   466: invokevirtual 205	java/lang/StringBuilder:append	(Ljava/lang/String;)Ljava/lang/StringBuilder;
    //   469: pop
    //   470: goto -72 -> 398
    //   473: astore 8
    //   475: aload 6
    //   477: aload 7
    //   479: invokevirtual 64	msj:toString	()Ljava/lang/String;
    //   482: invokestatic 69	mxy:a	(Lmsg;Ljava/lang/String;)Ljava/lang/String;
    //   485: invokestatic 190	java/lang/String:valueOf	(Ljava/lang/Object;)Ljava/lang/String;
    //   488: astore 4
    //   490: aload 4
    //   492: invokevirtual 196	java/lang/String:length	()I
    //   495: ifeq +66 -> 561
    //   498: ldc -47
    //   500: aload 4
    //   502: invokevirtual 213	java/lang/String:concat	(Ljava/lang/String;)Ljava/lang/String;
    //   505: astore 4
    //   507: aload 4
    //   509: aload 8
    //   511: invokestatic 218	jst:a	(Ljava/lang/String;Ljava/lang/Throwable;)V
    //   514: aload 5
    //   516: getfield 170	mod:m	I
    //   519: iconst_1
    //   520: iadd
    //   521: istore_1
    //   522: aload 5
    //   524: iload_1
    //   525: putfield 170	mod:m	I
    //   528: iload_1
    //   529: iconst_2
    //   530: if_icmpge +45 -> 575
    //   533: aload 5
    //   535: getfield 170	mod:m	I
    //   538: istore_1
    //   539: new 192	java/lang/StringBuilder
    //   542: dup
    //   543: bipush 50
    //   545: invokespecial 199	java/lang/StringBuilder:<init>	(I)V
    //   548: ldc -36
    //   550: invokevirtual 205	java/lang/StringBuilder:append	(Ljava/lang/String;)Ljava/lang/StringBuilder;
    //   553: iload_1
    //   554: invokevirtual 223	java/lang/StringBuilder:append	(I)Ljava/lang/StringBuilder;
    //   557: pop
    //   558: goto -252 -> 306
    //   561: new 77	java/lang/String
    //   564: dup
    //   565: ldc -47
    //   567: invokespecial 226	java/lang/String:<init>	(Ljava/lang/String;)V
    //   570: astore 4
    //   572: goto -65 -> 507
    //   575: getstatic 48	java/util/Locale:US	Ljava/util/Locale;
    //   578: ldc -28
    //   580: iconst_1
    //   581: anewarray 4	java/lang/Object
    //   584: dup
    //   585: iconst_0
    //   586: aload 6
    //   588: aload 7
    //   590: invokevirtual 64	msj:toString	()Ljava/lang/String;
    //   593: invokestatic 69	mxy:a	(Lmsg;Ljava/lang/String;)Ljava/lang/String;
    //   596: aastore
    //   597: invokestatic 81	java/lang/String:format	(Ljava/util/Locale;Ljava/lang/String;[Ljava/lang/Object;)Ljava/lang/String;
    //   600: pop
    //   601: aload 5
    //   603: invokevirtual 230	mod:d	()V
    //   606: goto -300 -> 306
    //   609: astore 8
    //   611: goto -384 -> 227
    // Local variable table:
    //   start	length	slot	name	signature
    //   0	614	0	this	moh
    //   1	553	1	i	int
    //   189	2	2	l	long
    //   9	291	4	localObject1	Object
    //   333	10	4	localObject2	Object
    //   347	224	4	localObject3	Object
    //   130	472	5	localmod	mod
    //   142	445	6	localObject4	Object
    //   154	435	7	localmsj	msj
    //   258	202	8	localObject5	Object
    //   473	37	8	localException1	Exception
    //   609	1	8	localInterruptedException	InterruptedException
    //   427	1	9	localException2	Exception
    // Exception table:
    //   from	to	target	type
    //   2	28	333	finally
    //   32	112	333	finally
    //   126	190	333	finally
    //   196	227	333	finally
    //   227	280	333	finally
    //   284	306	333	finally
    //   306	330	333	finally
    //   352	398	333	finally
    //   398	420	333	finally
    //   420	424	333	finally
    //   429	470	333	finally
    //   475	507	333	finally
    //   507	514	333	finally
    //   514	528	333	finally
    //   533	558	333	finally
    //   561	572	333	finally
    //   575	606	333	finally
    //   420	424	427	java/lang/Exception
    //   352	398	473	java/lang/Exception
    //   398	420	473	java/lang/Exception
    //   429	470	473	java/lang/Exception
    //   196	227	609	java/lang/InterruptedException
  }
}

/* Location:
 * Qualified Name:     moh
 * Java Class Version: 6 (50.0)
 * JD-Core Version:    0.7.1
 */