import org.xml.sax.XMLReader;

public final class mpe
  implements mpc
{
  private final jml a;
  private final XMLReader b;
  private final boolean c;
  
  private mpe(jml paramjml, boolean paramBoolean)
  {
    a = paramjml;
    b = null;
    c = paramBoolean;
  }
  
  public mpe(jml paramjml, boolean paramBoolean, byte paramByte)
  {
    this(paramjml, paramBoolean);
  }
  
  /* Error */
  public final mrk a(android.net.Uri paramUri)
  {
    // Byte code:
    //   0: aconst_null
    //   1: astore 5
    //   3: new 38	org/apache/http/client/methods/HttpGet
    //   6: dup
    //   7: aload_1
    //   8: invokevirtual 44	android/net/Uri:toString	()Ljava/lang/String;
    //   11: invokespecial 47	org/apache/http/client/methods/HttpGet:<init>	(Ljava/lang/String;)V
    //   14: astore_3
    //   15: aload_3
    //   16: ldc 49
    //   18: ldc 51
    //   20: invokevirtual 55	org/apache/http/client/methods/HttpGet:setHeader	(Ljava/lang/String;Ljava/lang/String;)V
    //   23: aload_0
    //   24: getfield 19	mpe:a	Ljml;
    //   27: aload_3
    //   28: invokeinterface 60 2 0
    //   33: astore 4
    //   35: aload 4
    //   37: astore_3
    //   38: aload 4
    //   40: invokeinterface 66 1 0
    //   45: invokeinterface 72 1 0
    //   50: istore_2
    //   51: iload_2
    //   52: sipush 404
    //   55: if_icmpne +18 -> 73
    //   58: aload 4
    //   60: astore_3
    //   61: iconst_m1
    //   62: invokestatic 77	mrk:a	(I)Lmrk;
    //   65: astore_1
    //   66: aload 4
    //   68: invokestatic 82	myb:a	(Lorg/apache/http/HttpResponse;)V
    //   71: aload_1
    //   72: areturn
    //   73: iload_2
    //   74: sipush 200
    //   77: if_icmpeq +71 -> 148
    //   80: aload 4
    //   82: astore_3
    //   83: aload_1
    //   84: invokestatic 88	java/lang/String:valueOf	(Ljava/lang/Object;)Ljava/lang/String;
    //   87: astore_1
    //   88: aload 4
    //   90: astore_3
    //   91: new 90	java/lang/StringBuilder
    //   94: dup
    //   95: aload_1
    //   96: invokestatic 88	java/lang/String:valueOf	(Ljava/lang/Object;)Ljava/lang/String;
    //   99: invokevirtual 93	java/lang/String:length	()I
    //   102: bipush 57
    //   104: iadd
    //   105: invokespecial 96	java/lang/StringBuilder:<init>	(I)V
    //   108: ldc 98
    //   110: invokevirtual 102	java/lang/StringBuilder:append	(Ljava/lang/String;)Ljava/lang/StringBuilder;
    //   113: aload_1
    //   114: invokevirtual 102	java/lang/StringBuilder:append	(Ljava/lang/String;)Ljava/lang/StringBuilder;
    //   117: ldc 104
    //   119: invokevirtual 102	java/lang/StringBuilder:append	(Ljava/lang/String;)Ljava/lang/StringBuilder;
    //   122: iload_2
    //   123: invokevirtual 107	java/lang/StringBuilder:append	(I)Ljava/lang/StringBuilder;
    //   126: invokevirtual 108	java/lang/StringBuilder:toString	()Ljava/lang/String;
    //   129: invokestatic 112	jst:a	(Ljava/lang/String;)V
    //   132: aload 4
    //   134: astore_3
    //   135: bipush -2
    //   137: invokestatic 77	mrk:a	(I)Lmrk;
    //   140: astore_1
    //   141: aload 4
    //   143: invokestatic 82	myb:a	(Lorg/apache/http/HttpResponse;)V
    //   146: aload_1
    //   147: areturn
    //   148: aload 4
    //   150: astore_3
    //   151: new 114	mpd
    //   154: dup
    //   155: invokespecial 115	mpd:<init>	()V
    //   158: astore 6
    //   160: aload 4
    //   162: astore_3
    //   163: aload 4
    //   165: invokeinterface 119 1 0
    //   170: invokeinterface 125 1 0
    //   175: getstatic 131	android/util/Xml$Encoding:UTF_8	Landroid/util/Xml$Encoding;
    //   178: aload 6
    //   180: invokestatic 137	android/util/Xml:parse	(Ljava/io/InputStream;Landroid/util/Xml$Encoding;Lorg/xml/sax/ContentHandler;)V
    //   183: aload 4
    //   185: astore_3
    //   186: aload 6
    //   188: getfield 141	mpd:e	I
    //   191: istore_2
    //   192: iload_2
    //   193: ifge +19 -> 212
    //   196: aload 4
    //   198: astore_3
    //   199: bipush -2
    //   201: invokestatic 77	mrk:a	(I)Lmrk;
    //   204: astore_1
    //   205: aload 4
    //   207: invokestatic 82	myb:a	(Lorg/apache/http/HttpResponse;)V
    //   210: aload_1
    //   211: areturn
    //   212: aload 5
    //   214: astore_1
    //   215: aload 4
    //   217: astore_3
    //   218: aload_0
    //   219: getfield 23	mpe:c	Z
    //   222: ifne +33 -> 255
    //   225: aload 5
    //   227: astore_1
    //   228: aload 4
    //   230: astore_3
    //   231: aload 6
    //   233: getfield 145	mpd:d	Ljava/lang/String;
    //   236: ifnull +19 -> 255
    //   239: aload 4
    //   241: astore_3
    //   242: new 147	msm
    //   245: dup
    //   246: aload 6
    //   248: getfield 145	mpd:d	Ljava/lang/String;
    //   251: invokespecial 148	msm:<init>	(Ljava/lang/String;)V
    //   254: astore_1
    //   255: aload 4
    //   257: astore_3
    //   258: invokestatic 151	mrk:a	()Lmrm;
    //   261: iload_2
    //   262: invokevirtual 156	mrm:a	(I)Lmrm;
    //   265: aload 6
    //   267: getfield 159	mpd:a	Landroid/net/Uri;
    //   270: invokevirtual 162	mrm:a	(Landroid/net/Uri;)Lmrm;
    //   273: aload 6
    //   275: getfield 164	mpd:c	Ljava/lang/String;
    //   278: invokevirtual 167	mrm:a	(Ljava/lang/String;)Lmrm;
    //   281: aload_1
    //   282: invokevirtual 170	mrm:a	(Lmsm;)Lmrm;
    //   285: aload 6
    //   287: getfield 173	mpd:f	Z
    //   290: invokevirtual 176	mrm:a	(Z)Lmrm;
    //   293: aload 6
    //   295: getfield 178	mpd:b	Z
    //   298: invokevirtual 180	mrm:b	(Z)Lmrm;
    //   301: aload 6
    //   303: getfield 183	mpd:g	Z
    //   306: invokevirtual 185	mrm:c	(Z)Lmrm;
    //   309: invokevirtual 188	mrm:a	()Lmrk;
    //   312: astore_1
    //   313: aload 4
    //   315: invokestatic 82	myb:a	(Lorg/apache/http/HttpResponse;)V
    //   318: aload_1
    //   319: areturn
    //   320: astore_1
    //   321: aconst_null
    //   322: astore 4
    //   324: aload 4
    //   326: astore_3
    //   327: ldc -66
    //   329: aload_1
    //   330: invokestatic 193	jst:a	(Ljava/lang/String;Ljava/lang/Throwable;)V
    //   333: aload 4
    //   335: invokestatic 82	myb:a	(Lorg/apache/http/HttpResponse;)V
    //   338: bipush -2
    //   340: invokestatic 77	mrk:a	(I)Lmrk;
    //   343: areturn
    //   344: astore_1
    //   345: aconst_null
    //   346: astore 4
    //   348: aload 4
    //   350: astore_3
    //   351: ldc -61
    //   353: aload_1
    //   354: invokestatic 193	jst:a	(Ljava/lang/String;Ljava/lang/Throwable;)V
    //   357: aload 4
    //   359: invokestatic 82	myb:a	(Lorg/apache/http/HttpResponse;)V
    //   362: goto -24 -> 338
    //   365: astore_1
    //   366: aconst_null
    //   367: astore 4
    //   369: aload 4
    //   371: astore_3
    //   372: ldc -59
    //   374: aload_1
    //   375: invokestatic 193	jst:a	(Ljava/lang/String;Ljava/lang/Throwable;)V
    //   378: aload 4
    //   380: invokestatic 82	myb:a	(Lorg/apache/http/HttpResponse;)V
    //   383: goto -45 -> 338
    //   386: astore_1
    //   387: aconst_null
    //   388: astore 4
    //   390: aload 4
    //   392: astore_3
    //   393: ldc -57
    //   395: aload_1
    //   396: invokestatic 193	jst:a	(Ljava/lang/String;Ljava/lang/Throwable;)V
    //   399: aload 4
    //   401: invokestatic 82	myb:a	(Lorg/apache/http/HttpResponse;)V
    //   404: goto -66 -> 338
    //   407: astore_1
    //   408: aconst_null
    //   409: astore_3
    //   410: aload_3
    //   411: invokestatic 82	myb:a	(Lorg/apache/http/HttpResponse;)V
    //   414: aload_1
    //   415: athrow
    //   416: astore_1
    //   417: goto -7 -> 410
    //   420: astore_1
    //   421: goto -31 -> 390
    //   424: astore_1
    //   425: goto -56 -> 369
    //   428: astore_1
    //   429: goto -81 -> 348
    //   432: astore_1
    //   433: goto -109 -> 324
    // Local variable table:
    //   start	length	slot	name	signature
    //   0	436	0	this	mpe
    //   0	436	1	paramUri	android.net.Uri
    //   50	212	2	i	int
    //   14	397	3	localObject1	Object
    //   33	367	4	localHttpResponse	org.apache.http.HttpResponse
    //   1	225	5	localObject2	Object
    //   158	144	6	localmpd	mpd
    // Exception table:
    //   from	to	target	type
    //   23	35	320	java/io/IOException
    //   23	35	344	java/lang/IllegalStateException
    //   23	35	365	org/xml/sax/SAXException
    //   23	35	386	java/lang/AssertionError
    //   23	35	407	finally
    //   38	51	416	finally
    //   61	66	416	finally
    //   83	88	416	finally
    //   91	132	416	finally
    //   135	141	416	finally
    //   151	160	416	finally
    //   163	183	416	finally
    //   186	192	416	finally
    //   199	205	416	finally
    //   218	225	416	finally
    //   231	239	416	finally
    //   242	255	416	finally
    //   258	313	416	finally
    //   327	333	416	finally
    //   351	357	416	finally
    //   372	378	416	finally
    //   393	399	416	finally
    //   38	51	420	java/lang/AssertionError
    //   61	66	420	java/lang/AssertionError
    //   83	88	420	java/lang/AssertionError
    //   91	132	420	java/lang/AssertionError
    //   135	141	420	java/lang/AssertionError
    //   151	160	420	java/lang/AssertionError
    //   163	183	420	java/lang/AssertionError
    //   186	192	420	java/lang/AssertionError
    //   199	205	420	java/lang/AssertionError
    //   218	225	420	java/lang/AssertionError
    //   231	239	420	java/lang/AssertionError
    //   242	255	420	java/lang/AssertionError
    //   258	313	420	java/lang/AssertionError
    //   38	51	424	org/xml/sax/SAXException
    //   61	66	424	org/xml/sax/SAXException
    //   83	88	424	org/xml/sax/SAXException
    //   91	132	424	org/xml/sax/SAXException
    //   135	141	424	org/xml/sax/SAXException
    //   151	160	424	org/xml/sax/SAXException
    //   163	183	424	org/xml/sax/SAXException
    //   186	192	424	org/xml/sax/SAXException
    //   199	205	424	org/xml/sax/SAXException
    //   218	225	424	org/xml/sax/SAXException
    //   231	239	424	org/xml/sax/SAXException
    //   242	255	424	org/xml/sax/SAXException
    //   258	313	424	org/xml/sax/SAXException
    //   38	51	428	java/lang/IllegalStateException
    //   61	66	428	java/lang/IllegalStateException
    //   83	88	428	java/lang/IllegalStateException
    //   91	132	428	java/lang/IllegalStateException
    //   135	141	428	java/lang/IllegalStateException
    //   151	160	428	java/lang/IllegalStateException
    //   163	183	428	java/lang/IllegalStateException
    //   186	192	428	java/lang/IllegalStateException
    //   199	205	428	java/lang/IllegalStateException
    //   218	225	428	java/lang/IllegalStateException
    //   231	239	428	java/lang/IllegalStateException
    //   242	255	428	java/lang/IllegalStateException
    //   258	313	428	java/lang/IllegalStateException
    //   38	51	432	java/io/IOException
    //   61	66	432	java/io/IOException
    //   83	88	432	java/io/IOException
    //   91	132	432	java/io/IOException
    //   135	141	432	java/io/IOException
    //   151	160	432	java/io/IOException
    //   163	183	432	java/io/IOException
    //   186	192	432	java/io/IOException
    //   199	205	432	java/io/IOException
    //   218	225	432	java/io/IOException
    //   231	239	432	java/io/IOException
    //   242	255	432	java/io/IOException
    //   258	313	432	java/io/IOException
  }
}

/* Location:
 * Qualified Name:     mpe
 * Java Class Version: 6 (50.0)
 * JD-Core Version:    0.7.1
 */