final class mty
{
  private final String a;
  
  public mty(String paramString)
  {
    a = paramString;
  }
  
  /* Error */
  public final java.util.Map a()
  {
    // Byte code:
    //   0: new 19	org/json/JSONObject
    //   3: dup
    //   4: aload_0
    //   5: getfield 13	mty:a	Ljava/lang/String;
    //   8: invokespecial 21	org/json/JSONObject:<init>	(Ljava/lang/String;)V
    //   11: astore_3
    //   12: aload_3
    //   13: ldc 23
    //   15: invokevirtual 27	org/json/JSONObject:has	(Ljava/lang/String;)Z
    //   18: ifne +7 -> 25
    //   21: invokestatic 32	java/util/Collections:emptyMap	()Ljava/util/Map;
    //   24: areturn
    //   25: aload_3
    //   26: ldc 23
    //   28: invokevirtual 36	org/json/JSONObject:getJSONArray	(Ljava/lang/String;)Lorg/json/JSONArray;
    //   31: astore 6
    //   33: aload 6
    //   35: ifnonnull +7 -> 42
    //   38: invokestatic 32	java/util/Collections:emptyMap	()Ljava/util/Map;
    //   41: areturn
    //   42: new 38	java/util/HashMap
    //   45: dup
    //   46: invokespecial 39	java/util/HashMap:<init>	()V
    //   49: astore 4
    //   51: iconst_0
    //   52: istore_1
    //   53: aload 6
    //   55: invokevirtual 45	org/json/JSONArray:length	()I
    //   58: istore_2
    //   59: aload 4
    //   61: astore_3
    //   62: iload_1
    //   63: iload_2
    //   64: if_icmpge +139 -> 203
    //   67: aload 6
    //   69: iload_1
    //   70: invokevirtual 49	org/json/JSONArray:getJSONObject	(I)Lorg/json/JSONObject;
    //   73: astore 7
    //   75: aload 7
    //   77: ldc 51
    //   79: invokevirtual 55	org/json/JSONObject:optString	(Ljava/lang/String;)Ljava/lang/String;
    //   82: astore 8
    //   84: iconst_0
    //   85: invokestatic 61	java/lang/Boolean:valueOf	(Z)Ljava/lang/Boolean;
    //   88: astore 5
    //   90: aload 5
    //   92: astore_3
    //   93: aload 8
    //   95: ifnull +21 -> 116
    //   98: aload 5
    //   100: astore_3
    //   101: ldc 63
    //   103: aload 8
    //   105: invokevirtual 69	java/lang/String:equals	(Ljava/lang/Object;)Z
    //   108: ifeq +8 -> 116
    //   111: iconst_1
    //   112: invokestatic 61	java/lang/Boolean:valueOf	(Z)Ljava/lang/Boolean;
    //   115: astore_3
    //   116: aload 7
    //   118: ldc 71
    //   120: invokevirtual 27	org/json/JSONObject:has	(Ljava/lang/String;)Z
    //   123: ifeq +26 -> 149
    //   126: aload 4
    //   128: new 73	msa
    //   131: dup
    //   132: aload 7
    //   134: ldc 71
    //   136: invokevirtual 76	org/json/JSONObject:getString	(Ljava/lang/String;)Ljava/lang/String;
    //   139: invokespecial 77	msa:<init>	(Ljava/lang/String;)V
    //   142: aload_3
    //   143: invokeinterface 83 3 0
    //   148: pop
    //   149: iload_1
    //   150: iconst_1
    //   151: iadd
    //   152: istore_1
    //   153: goto -100 -> 53
    //   156: astore_3
    //   157: getstatic 86	mtx:a	Ljava/lang/String;
    //   160: new 88	java/lang/StringBuilder
    //   163: dup
    //   164: bipush 32
    //   166: invokespecial 91	java/lang/StringBuilder:<init>	(I)V
    //   169: ldc 93
    //   171: invokevirtual 97	java/lang/StringBuilder:append	(Ljava/lang/String;)Ljava/lang/StringBuilder;
    //   174: iload_1
    //   175: invokevirtual 100	java/lang/StringBuilder:append	(I)Ljava/lang/StringBuilder;
    //   178: invokevirtual 104	java/lang/StringBuilder:toString	()Ljava/lang/String;
    //   181: invokestatic 110	android/util/Log:w	(Ljava/lang/String;Ljava/lang/String;)I
    //   184: pop
    //   185: goto -36 -> 149
    //   188: astore_3
    //   189: getstatic 86	mtx:a	Ljava/lang/String;
    //   192: ldc 112
    //   194: aload_3
    //   195: invokestatic 116	android/util/Log:e	(Ljava/lang/String;Ljava/lang/String;Ljava/lang/Throwable;)I
    //   198: pop
    //   199: invokestatic 32	java/util/Collections:emptyMap	()Ljava/util/Map;
    //   202: astore_3
    //   203: aload_3
    //   204: areturn
    // Local variable table:
    //   start	length	slot	name	signature
    //   0	205	0	this	mty
    //   52	123	1	i	int
    //   58	7	2	j	int
    //   11	132	3	localObject	Object
    //   156	1	3	localJSONException1	org.json.JSONException
    //   188	7	3	localJSONException2	org.json.JSONException
    //   202	2	3	localMap	java.util.Map
    //   49	78	4	localHashMap	java.util.HashMap
    //   88	11	5	localBoolean	Boolean
    //   31	37	6	localJSONArray	org.json.JSONArray
    //   73	60	7	localJSONObject	org.json.JSONObject
    //   82	22	8	str	String
    // Exception table:
    //   from	to	target	type
    //   67	90	156	org/json/JSONException
    //   101	116	156	org/json/JSONException
    //   116	149	156	org/json/JSONException
    //   0	25	188	org/json/JSONException
    //   25	33	188	org/json/JSONException
    //   38	42	188	org/json/JSONException
    //   42	51	188	org/json/JSONException
    //   53	59	188	org/json/JSONException
    //   157	185	188	org/json/JSONException
  }
}

/* Location:
 * Qualified Name:     mty
 * Java Class Version: 6 (50.0)
 * JD-Core Version:    0.7.1
 */