public class mua
  implements mtr
{
  private static final String a = mua.class.getCanonicalName();
  private final jml b;
  private final mtv c;
  
  public mua(jml paramjml, mtv parammtv)
  {
    b = paramjml;
    c = parammtv;
  }
  
  /* Error */
  private mru a(msh parammsh)
  {
    // Byte code:
    //   0: aload_1
    //   1: ifnonnull +5 -> 6
    //   4: aconst_null
    //   5: areturn
    //   6: aload_0
    //   7: getfield 31	mua:c	Lmtv;
    //   10: aload_1
    //   11: invokevirtual 41	mtv:a	(Lmsh;)Lorg/apache/http/client/methods/HttpPost;
    //   14: astore 5
    //   16: aload_0
    //   17: getfield 29	mua:b	Ljml;
    //   20: aload 5
    //   22: invokeinterface 46 2 0
    //   27: astore_3
    //   28: aload_3
    //   29: astore_1
    //   30: aload_3
    //   31: invokeinterface 52 1 0
    //   36: invokeinterface 58 1 0
    //   41: istore_2
    //   42: iload_2
    //   43: sipush 200
    //   46: if_icmpeq +100 -> 146
    //   49: aload_3
    //   50: astore_1
    //   51: aload_3
    //   52: invokeinterface 62 1 0
    //   57: ifnull +16 -> 73
    //   60: aload_3
    //   61: astore_1
    //   62: aload_3
    //   63: invokeinterface 62 1 0
    //   68: invokeinterface 67 1 0
    //   73: aload_3
    //   74: astore_1
    //   75: getstatic 22	mua:a	Ljava/lang/String;
    //   78: astore 4
    //   80: aload_3
    //   81: astore_1
    //   82: aload 5
    //   84: invokevirtual 73	org/apache/http/client/methods/HttpPost:getURI	()Ljava/net/URI;
    //   87: invokestatic 79	java/lang/String:valueOf	(Ljava/lang/Object;)Ljava/lang/String;
    //   90: astore 6
    //   92: aload_3
    //   93: astore_1
    //   94: aload 4
    //   96: new 81	java/lang/StringBuilder
    //   99: dup
    //   100: aload 6
    //   102: invokestatic 79	java/lang/String:valueOf	(Ljava/lang/Object;)Ljava/lang/String;
    //   105: invokevirtual 84	java/lang/String:length	()I
    //   108: bipush 42
    //   110: iadd
    //   111: invokespecial 87	java/lang/StringBuilder:<init>	(I)V
    //   114: ldc 89
    //   116: invokevirtual 93	java/lang/StringBuilder:append	(Ljava/lang/String;)Ljava/lang/StringBuilder;
    //   119: aload 6
    //   121: invokevirtual 93	java/lang/StringBuilder:append	(Ljava/lang/String;)Ljava/lang/StringBuilder;
    //   124: ldc 95
    //   126: invokevirtual 93	java/lang/StringBuilder:append	(Ljava/lang/String;)Ljava/lang/StringBuilder;
    //   129: iload_2
    //   130: invokevirtual 98	java/lang/StringBuilder:append	(I)Ljava/lang/StringBuilder;
    //   133: invokevirtual 101	java/lang/StringBuilder:toString	()Ljava/lang/String;
    //   136: invokestatic 107	android/util/Log:w	(Ljava/lang/String;Ljava/lang/String;)I
    //   139: pop
    //   140: aload_3
    //   141: invokestatic 112	myb:a	(Lorg/apache/http/HttpResponse;)V
    //   144: aconst_null
    //   145: areturn
    //   146: aload_3
    //   147: astore_1
    //   148: new 114	mud
    //   151: dup
    //   152: new 116	org/json/JSONObject
    //   155: dup
    //   156: new 118	org/apache/http/impl/client/BasicResponseHandler
    //   159: dup
    //   160: invokespecial 119	org/apache/http/impl/client/BasicResponseHandler:<init>	()V
    //   163: aload_3
    //   164: invokevirtual 123	org/apache/http/impl/client/BasicResponseHandler:handleResponse	(Lorg/apache/http/HttpResponse;)Ljava/lang/String;
    //   167: invokespecial 126	org/json/JSONObject:<init>	(Ljava/lang/String;)V
    //   170: ldc -128
    //   172: invokevirtual 132	org/json/JSONObject:getJSONObject	(Ljava/lang/String;)Lorg/json/JSONObject;
    //   175: invokespecial 135	mud:<init>	(Lorg/json/JSONObject;)V
    //   178: invokevirtual 138	mud:a	()Lmru;
    //   181: astore 4
    //   183: aload_3
    //   184: invokestatic 112	myb:a	(Lorg/apache/http/HttpResponse;)V
    //   187: aload 4
    //   189: areturn
    //   190: astore 4
    //   192: aconst_null
    //   193: astore_3
    //   194: aload_3
    //   195: astore_1
    //   196: getstatic 22	mua:a	Ljava/lang/String;
    //   199: astore 6
    //   201: aload_3
    //   202: astore_1
    //   203: aload 5
    //   205: invokevirtual 73	org/apache/http/client/methods/HttpPost:getURI	()Ljava/net/URI;
    //   208: invokestatic 79	java/lang/String:valueOf	(Ljava/lang/Object;)Ljava/lang/String;
    //   211: astore 5
    //   213: aload_3
    //   214: astore_1
    //   215: aload 6
    //   217: new 81	java/lang/StringBuilder
    //   220: dup
    //   221: aload 5
    //   223: invokestatic 79	java/lang/String:valueOf	(Ljava/lang/Object;)Ljava/lang/String;
    //   226: invokevirtual 84	java/lang/String:length	()I
    //   229: bipush 19
    //   231: iadd
    //   232: invokespecial 87	java/lang/StringBuilder:<init>	(I)V
    //   235: ldc -116
    //   237: invokevirtual 93	java/lang/StringBuilder:append	(Ljava/lang/String;)Ljava/lang/StringBuilder;
    //   240: aload 5
    //   242: invokevirtual 93	java/lang/StringBuilder:append	(Ljava/lang/String;)Ljava/lang/StringBuilder;
    //   245: invokevirtual 101	java/lang/StringBuilder:toString	()Ljava/lang/String;
    //   248: aload 4
    //   250: invokestatic 144	android/util/Log:e	(Ljava/lang/String;Ljava/lang/String;Ljava/lang/Throwable;)I
    //   253: pop
    //   254: aload_3
    //   255: invokestatic 112	myb:a	(Lorg/apache/http/HttpResponse;)V
    //   258: aconst_null
    //   259: areturn
    //   260: astore 4
    //   262: aconst_null
    //   263: astore_3
    //   264: aload_3
    //   265: astore_1
    //   266: getstatic 22	mua:a	Ljava/lang/String;
    //   269: ldc -110
    //   271: aload 4
    //   273: invokestatic 144	android/util/Log:e	(Ljava/lang/String;Ljava/lang/String;Ljava/lang/Throwable;)I
    //   276: pop
    //   277: aload_3
    //   278: invokestatic 112	myb:a	(Lorg/apache/http/HttpResponse;)V
    //   281: aconst_null
    //   282: areturn
    //   283: astore_1
    //   284: aconst_null
    //   285: astore 4
    //   287: aload_1
    //   288: astore_3
    //   289: aload 4
    //   291: invokestatic 112	myb:a	(Lorg/apache/http/HttpResponse;)V
    //   294: aload_3
    //   295: athrow
    //   296: astore_3
    //   297: aload_1
    //   298: astore 4
    //   300: goto -11 -> 289
    //   303: astore 4
    //   305: goto -41 -> 264
    //   308: astore 4
    //   310: goto -116 -> 194
    // Local variable table:
    //   start	length	slot	name	signature
    //   0	313	0	this	mua
    //   0	313	1	parammsh	msh
    //   41	89	2	i	int
    //   27	268	3	localObject1	Object
    //   296	1	3	localObject2	Object
    //   78	110	4	localObject3	Object
    //   190	59	4	localIOException1	java.io.IOException
    //   260	12	4	localException1	Exception
    //   285	14	4	localObject4	Object
    //   303	1	4	localException2	Exception
    //   308	1	4	localIOException2	java.io.IOException
    //   14	227	5	localObject5	Object
    //   90	126	6	str	String
    // Exception table:
    //   from	to	target	type
    //   16	28	190	java/io/IOException
    //   16	28	260	java/lang/Exception
    //   16	28	283	finally
    //   30	42	296	finally
    //   51	60	296	finally
    //   62	73	296	finally
    //   75	80	296	finally
    //   82	92	296	finally
    //   94	140	296	finally
    //   148	183	296	finally
    //   196	201	296	finally
    //   203	213	296	finally
    //   215	254	296	finally
    //   266	277	296	finally
    //   30	42	303	java/lang/Exception
    //   51	60	303	java/lang/Exception
    //   62	73	303	java/lang/Exception
    //   75	80	303	java/lang/Exception
    //   82	92	303	java/lang/Exception
    //   94	140	303	java/lang/Exception
    //   148	183	303	java/lang/Exception
    //   30	42	308	java/io/IOException
    //   51	60	308	java/io/IOException
    //   62	73	308	java/io/IOException
    //   75	80	308	java/io/IOException
    //   82	92	308	java/io/IOException
    //   94	140	308	java/io/IOException
    //   148	183	308	java/io/IOException
  }
}

/* Location:
 * Qualified Name:     mua
 * Java Class Version: 6 (50.0)
 * JD-Core Version:    0.7.1
 */