import android.net.Uri;
import java.util.concurrent.ExecutorService;

public final class ncu
  implements eud
{
  static final Uri a = Uri.parse("http://dummy.googlevideo.com/videoplayback");
  final String b;
  private final ExecutorService c;
  private est d;
  private boolean e;
  private int f;
  private long g;
  private ncv h;
  private boolean i = true;
  private boolean j;
  private boolean k;
  private int l;
  private eud m;
  
  public ncu(String paramString, ExecutorService paramExecutorService)
  {
    b = jju.a(paramString);
    c = ((ExecutorService)jju.a(paramExecutorService));
    d = null;
  }
  
  /* Error */
  public final est a(int paramInt)
  {
    // Byte code:
    //   0: aload_0
    //   1: monitorenter
    //   2: aload_0
    //   3: getfield 66	ncu:k	Z
    //   6: ifeq +12 -> 18
    //   9: aload_0
    //   10: getfield 63	ncu:d	Lest;
    //   13: astore_2
    //   14: aload_0
    //   15: monitorexit
    //   16: aload_2
    //   17: areturn
    //   18: aload_0
    //   19: getfield 68	ncu:m	Leud;
    //   22: ifnull +17 -> 39
    //   25: aload_0
    //   26: getfield 68	ncu:m	Leud;
    //   29: iload_1
    //   30: invokeinterface 70 2 0
    //   35: astore_2
    //   36: goto -22 -> 14
    //   39: getstatic 75	nra:b	Lnra;
    //   42: getstatic 80	nrb:c	Lnrb;
    //   45: ldc 82
    //   47: invokestatic 87	nqz:a	(Lnra;Lnrb;Ljava/lang/String;)V
    //   50: aconst_null
    //   51: astore_2
    //   52: goto -38 -> 14
    //   55: astore_2
    //   56: aload_0
    //   57: monitorexit
    //   58: aload_2
    //   59: athrow
    // Local variable table:
    //   start	length	slot	name	signature
    //   0	60	0	this	ncu
    //   0	60	1	paramInt	int
    //   13	39	2	localest	est
    //   55	4	2	localObject	Object
    // Exception table:
    //   from	to	target	type
    //   2	14	55	finally
    //   18	36	55	finally
    //   39	50	55	finally
  }
  
  public final void a()
  {
    try
    {
      if (m != null) {
        m.a();
      }
      return;
    }
    finally
    {
      localObject = finally;
      throw ((Throwable)localObject);
    }
  }
  
  /* Error */
  public final void a(int paramInt, long paramLong, byte[] paramArrayOfByte)
  {
    // Byte code:
    //   0: aload_0
    //   1: monitorenter
    //   2: aload_0
    //   3: getfield 47	ncu:i	Z
    //   6: istore 5
    //   8: iload 5
    //   10: ifne +6 -> 16
    //   13: aload_0
    //   14: monitorexit
    //   15: return
    //   16: aload_0
    //   17: iconst_0
    //   18: putfield 47	ncu:i	Z
    //   21: new 92	ncw
    //   24: dup
    //   25: aload_0
    //   26: iload_1
    //   27: aload 4
    //   29: invokespecial 95	ncw:<init>	(Lncu;I[B)V
    //   32: astore 4
    //   34: aload_0
    //   35: getfield 61	ncu:c	Ljava/util/concurrent/ExecutorService;
    //   38: aload 4
    //   40: invokeinterface 99 2 0
    //   45: pop
    //   46: aload_0
    //   47: iload_1
    //   48: putfield 101	ncu:f	I
    //   51: aload_0
    //   52: lload_2
    //   53: putfield 103	ncu:g	J
    //   56: goto -43 -> 13
    //   59: astore 4
    //   61: aload_0
    //   62: monitorexit
    //   63: aload 4
    //   65: athrow
    // Local variable table:
    //   start	length	slot	name	signature
    //   0	66	0	this	ncu
    //   0	66	1	paramInt	int
    //   0	66	2	paramLong	long
    //   0	66	4	paramArrayOfByte	byte[]
    //   6	3	5	bool	boolean
    // Exception table:
    //   from	to	target	type
    //   2	8	59	finally
    //   16	56	59	finally
  }
  
  public final void a(long paramLong)
  {
    try
    {
      if (m != null) {
        m.a(paramLong);
      }
      return;
    }
    finally
    {
      localObject = finally;
      throw ((Throwable)localObject);
    }
  }
  
  public final void a(etr parametr)
  {
    try
    {
      if ((m != null) && (!(parametr instanceof ncv))) {
        m.a(parametr);
      }
      return;
    }
    finally
    {
      parametr = finally;
      throw parametr;
    }
  }
  
  public final void a(etr parametr, Exception paramException)
  {
    try
    {
      if (m != null) {
        m.a(parametr, paramException);
      }
      return;
    }
    finally
    {
      parametr = finally;
      throw parametr;
    }
  }
  
  /* Error */
  public final void a(eud parameud)
  {
    // Byte code:
    //   0: aload_0
    //   1: monitorenter
    //   2: aload_0
    //   3: aload_1
    //   4: putfield 68	ncu:m	Leud;
    //   7: aload_0
    //   8: getfield 66	ncu:k	Z
    //   11: ifeq +29 -> 40
    //   14: aload_0
    //   15: getfield 68	ncu:m	Leud;
    //   18: invokeinterface 118 1 0
    //   23: ifne +17 -> 40
    //   26: getstatic 75	nra:b	Lnra;
    //   29: getstatic 80	nrb:c	Lnrb;
    //   32: ldc 120
    //   34: invokestatic 87	nqz:a	(Lnra;Lnrb;Ljava/lang/String;)V
    //   37: aload_0
    //   38: monitorexit
    //   39: return
    //   40: aload_0
    //   41: getfield 122	ncu:j	Z
    //   44: ifeq -7 -> 37
    //   47: aload_0
    //   48: getfield 68	ncu:m	Leud;
    //   51: aload_0
    //   52: getfield 124	ncu:l	I
    //   55: invokeinterface 127 2 0
    //   60: goto -23 -> 37
    //   63: astore_1
    //   64: aload_0
    //   65: monitorexit
    //   66: aload_1
    //   67: athrow
    // Local variable table:
    //   start	length	slot	name	signature
    //   0	68	0	this	ncu
    //   0	68	1	parameud	eud
    // Exception table:
    //   from	to	target	type
    //   2	37	63	finally
    //   40	60	63	finally
  }
  
  /* Error */
  public final void a(java.util.List paramList)
  {
    // Byte code:
    //   0: aload_0
    //   1: monitorenter
    //   2: aload_0
    //   3: getfield 68	ncu:m	Leud;
    //   6: ifnull +16 -> 22
    //   9: aload_0
    //   10: getfield 68	ncu:m	Leud;
    //   13: aload_1
    //   14: invokeinterface 130 2 0
    //   19: aload_0
    //   20: monitorexit
    //   21: return
    //   22: aload_0
    //   23: iconst_0
    //   24: putfield 122	ncu:j	Z
    //   27: goto -8 -> 19
    //   30: astore_1
    //   31: aload_0
    //   32: monitorexit
    //   33: aload_1
    //   34: athrow
    // Local variable table:
    //   start	length	slot	name	signature
    //   0	35	0	this	ncu
    //   0	35	1	paramList	java.util.List
    // Exception table:
    //   from	to	target	type
    //   2	19	30	finally
    //   22	27	30	finally
  }
  
  /* Error */
  public final void a(java.util.List paramList, long paramLong, etu parametu)
  {
    // Byte code:
    //   0: aload_0
    //   1: monitorenter
    //   2: aload_0
    //   3: getfield 68	ncu:m	Leud;
    //   6: ifnull +19 -> 25
    //   9: aload_0
    //   10: getfield 68	ncu:m	Leud;
    //   13: aload_1
    //   14: lload_2
    //   15: aload 4
    //   17: invokeinterface 133 5 0
    //   22: aload_0
    //   23: monitorexit
    //   24: return
    //   25: aload 4
    //   27: getfield 138	etu:b	Letr;
    //   30: ifnonnull -8 -> 22
    //   33: aload_0
    //   34: getfield 140	ncu:h	Lncv;
    //   37: ifnull -15 -> 22
    //   40: aload_0
    //   41: getfield 142	ncu:e	Z
    //   44: ifne -22 -> 22
    //   47: aload 4
    //   49: aload_0
    //   50: getfield 140	ncu:h	Lncv;
    //   53: putfield 138	etu:b	Letr;
    //   56: aload_0
    //   57: iconst_1
    //   58: putfield 142	ncu:e	Z
    //   61: goto -39 -> 22
    //   64: astore_1
    //   65: aload_0
    //   66: monitorexit
    //   67: aload_1
    //   68: athrow
    // Local variable table:
    //   start	length	slot	name	signature
    //   0	69	0	this	ncu
    //   0	69	1	paramList	java.util.List
    //   0	69	2	paramLong	long
    //   0	69	4	parametu	etu
    // Exception table:
    //   from	to	target	type
    //   2	22	64	finally
    //   25	61	64	finally
  }
  
  final void a(ncv paramncv)
  {
    try
    {
      h = paramncv;
      d = est.a(b, m.e);
      return;
    }
    finally
    {
      paramncv = finally;
      throw paramncv;
    }
  }
  
  /* Error */
  public final boolean a(lys paramlys)
  {
    // Byte code:
    //   0: aload_0
    //   1: monitorenter
    //   2: aload_0
    //   3: getfield 101	ncu:f	I
    //   6: ifne +22 -> 28
    //   9: aload_0
    //   10: getfield 103	ncu:g	J
    //   13: lstore_2
    //   14: lload_2
    //   15: lconst_0
    //   16: lcmp
    //   17: ifne +11 -> 28
    //   20: iconst_1
    //   21: istore 6
    //   23: aload_0
    //   24: monitorexit
    //   25: iload 6
    //   27: ireturn
    //   28: aload_1
    //   29: getfield 160	lys:a	Ljava/util/List;
    //   32: invokeinterface 166 1 0
    //   37: astore_1
    //   38: aload_1
    //   39: invokeinterface 171 1 0
    //   44: ifeq +97 -> 141
    //   47: aload_1
    //   48: invokeinterface 175 1 0
    //   53: checkcast 177	lxg
    //   56: astore 7
    //   58: aload 7
    //   60: getfield 180	lxg:a	Lqub;
    //   63: getfield 184	qub:a	I
    //   66: aload_0
    //   67: getfield 101	ncu:f	I
    //   70: if_icmpne -32 -> 38
    //   73: aload 7
    //   75: getfield 180	lxg:a	Lqub;
    //   78: getfield 186	qub:m	Ljava/lang/String;
    //   81: invokestatic 192	android/text/TextUtils:isEmpty	(Ljava/lang/CharSequence;)Z
    //   84: ifne +9 -> 93
    //   87: iconst_0
    //   88: istore 6
    //   90: goto -67 -> 23
    //   93: aload 7
    //   95: invokevirtual 195	lxg:b	()Landroid/net/Uri;
    //   98: ldc -59
    //   100: invokevirtual 200	android/net/Uri:getQueryParameter	(Ljava/lang/String;)Ljava/lang/String;
    //   103: astore_1
    //   104: aload_1
    //   105: invokestatic 206	java/lang/Long:parseLong	(Ljava/lang/String;)J
    //   108: lstore_2
    //   109: aload_0
    //   110: getfield 103	ncu:g	J
    //   113: lstore 4
    //   115: lload_2
    //   116: lload 4
    //   118: lcmp
    //   119: ifne +9 -> 128
    //   122: iconst_1
    //   123: istore 6
    //   125: goto -102 -> 23
    //   128: iconst_0
    //   129: istore 6
    //   131: goto -108 -> 23
    //   134: astore_1
    //   135: iconst_0
    //   136: istore 6
    //   138: goto -115 -> 23
    //   141: iconst_0
    //   142: istore 6
    //   144: goto -121 -> 23
    //   147: astore_1
    //   148: aload_0
    //   149: monitorexit
    //   150: aload_1
    //   151: athrow
    // Local variable table:
    //   start	length	slot	name	signature
    //   0	152	0	this	ncu
    //   0	152	1	paramlys	lys
    //   13	103	2	l1	long
    //   113	4	4	l2	long
    //   21	122	6	bool	boolean
    //   56	38	7	locallxg	lxg
    // Exception table:
    //   from	to	target	type
    //   104	115	134	java/lang/NumberFormatException
    //   2	14	147	finally
    //   28	38	147	finally
    //   38	87	147	finally
    //   93	104	147	finally
    //   104	115	147	finally
  }
  
  /* Error */
  public final void b(int paramInt)
  {
    // Byte code:
    //   0: aload_0
    //   1: monitorenter
    //   2: aload_0
    //   3: getfield 68	ncu:m	Leud;
    //   6: ifnull +16 -> 22
    //   9: aload_0
    //   10: getfield 68	ncu:m	Leud;
    //   13: iload_1
    //   14: invokeinterface 127 2 0
    //   19: aload_0
    //   20: monitorexit
    //   21: return
    //   22: aload_0
    //   23: iconst_1
    //   24: putfield 122	ncu:j	Z
    //   27: aload_0
    //   28: iload_1
    //   29: putfield 124	ncu:l	I
    //   32: goto -13 -> 19
    //   35: astore_2
    //   36: aload_0
    //   37: monitorexit
    //   38: aload_2
    //   39: athrow
    // Local variable table:
    //   start	length	slot	name	signature
    //   0	40	0	this	ncu
    //   0	40	1	paramInt	int
    //   35	4	2	localObject	Object
    // Exception table:
    //   from	to	target	type
    //   2	19	35	finally
    //   22	32	35	finally
  }
  
  /* Error */
  public final boolean b()
  {
    // Byte code:
    //   0: iconst_1
    //   1: istore_1
    //   2: aload_0
    //   3: monitorenter
    //   4: aload_0
    //   5: getfield 68	ncu:m	Leud;
    //   8: ifnull +17 -> 25
    //   11: aload_0
    //   12: getfield 68	ncu:m	Leud;
    //   15: invokeinterface 118 1 0
    //   20: istore_1
    //   21: aload_0
    //   22: monitorexit
    //   23: iload_1
    //   24: ireturn
    //   25: aload_0
    //   26: getfield 63	ncu:d	Lest;
    //   29: ifnonnull +8 -> 37
    //   32: iconst_0
    //   33: istore_1
    //   34: goto -13 -> 21
    //   37: aload_0
    //   38: iconst_1
    //   39: putfield 66	ncu:k	Z
    //   42: goto -21 -> 21
    //   45: astore_2
    //   46: aload_0
    //   47: monitorexit
    //   48: aload_2
    //   49: athrow
    // Local variable table:
    //   start	length	slot	name	signature
    //   0	50	0	this	ncu
    //   1	33	1	bool	boolean
    //   45	4	2	localObject	Object
    // Exception table:
    //   from	to	target	type
    //   4	21	45	finally
    //   25	32	45	finally
    //   37	42	45	finally
  }
  
  public final int c()
  {
    return 1;
  }
  
  public final void d()
  {
    try
    {
      i = false;
      return;
    }
    finally
    {
      localObject = finally;
      throw ((Throwable)localObject);
    }
  }
}

/* Location:
 * Qualified Name:     ncu
 * Java Class Version: 6 (50.0)
 * JD-Core Version:    0.7.1
 */