import android.os.Handler;
import android.os.Looper;

final class ntq
  extends Handler
{
  ntq(ntp paramntp, Looper paramLooper)
  {
    super(paramLooper);
  }
  
  /* Error */
  public final void handleMessage(android.os.Message arg1)
  {
    // Byte code:
    //   0: aload_0
    //   1: getfield 10	ntq:a	Lntp;
    //   4: astore 6
    //   6: aload 6
    //   8: getfield 22	ntp:i	Z
    //   11: ifne +169 -> 180
    //   14: aload 6
    //   16: getfield 26	ntp:p	Landroid/os/PowerManager$WakeLock;
    //   19: invokevirtual 32	android/os/PowerManager$WakeLock:acquire	()V
    //   22: aload_1
    //   23: getfield 38	android/os/Message:what	I
    //   26: tableswitch	default:+2275->2301, 1:+155->181, 2:+602->628, 3:+842->868, 4:+562->588, 5:+530->556, 6:+74->100, 7:+594->620, 8:+1047->1073, 9:+1118->1144, 10:+1237->1263, 11:+1473->1499, 12:+1665->1691, 13:+1900->1926, 14:+1928->1954, 15:+2160->2186
    //   100: aload 6
    //   102: getfield 42	ntp:e	Ljava/lang/Object;
    //   105: astore_1
    //   106: aload_1
    //   107: monitorenter
    //   108: aload 6
    //   110: getfield 45	ntp:f	I
    //   113: iconst_1
    //   114: iadd
    //   115: istore_2
    //   116: aload 6
    //   118: iload_2
    //   119: putfield 45	ntp:f	I
    //   122: iload_2
    //   123: aload 6
    //   125: getfield 48	ntp:g	I
    //   128: if_icmpne +2161 -> 2289
    //   131: aload 6
    //   133: getfield 51	ntp:u	Z
    //   136: ifne +2153 -> 2289
    //   139: iconst_1
    //   140: istore_3
    //   141: aload 6
    //   143: iload_3
    //   144: putfield 54	ntp:h	Z
    //   147: aload 6
    //   149: getfield 54	ntp:h	Z
    //   152: ifeq +18 -> 170
    //   155: aload 6
    //   157: getfield 58	ntp:c	Lnuj;
    //   160: aload 6
    //   162: getfield 45	ntp:f	I
    //   165: invokeinterface 63 2 0
    //   170: aload_1
    //   171: monitorexit
    //   172: aload 6
    //   174: getfield 26	ntp:p	Landroid/os/PowerManager$WakeLock;
    //   177: invokevirtual 66	android/os/PowerManager$WakeLock:release	()V
    //   180: return
    //   181: aload 6
    //   183: getfield 70	ntp:j	Lnug;
    //   186: invokevirtual 74	nug:a	()V
    //   189: aload_1
    //   190: getfield 77	android/os/Message:obj	Ljava/lang/Object;
    //   193: checkcast 79	java/lang/String
    //   196: astore 7
    //   198: aload 7
    //   200: invokestatic 85	android/text/TextUtils:isEmpty	(Ljava/lang/CharSequence;)Z
    //   203: ifeq +230 -> 433
    //   206: aload 6
    //   208: getfield 70	ntp:j	Lnug;
    //   211: aconst_null
    //   212: invokevirtual 88	nug:a	(Ljava/lang/String;)Ljava/util/List;
    //   215: astore_1
    //   216: aload_1
    //   217: invokeinterface 94 1 0
    //   222: astore_1
    //   223: aload_1
    //   224: invokeinterface 100 1 0
    //   229: ifeq +218 -> 447
    //   232: aload_1
    //   233: invokeinterface 104 1 0
    //   238: checkcast 106	nuk
    //   241: astore 8
    //   243: aload 8
    //   245: getfield 109	nuk:a	Ljava/lang/String;
    //   248: astore 9
    //   250: aload 8
    //   252: getfield 111	nuk:i	Ljava/lang/String;
    //   255: astore 10
    //   257: aload 8
    //   259: getfield 114	nuk:c	Lnqr;
    //   262: invokevirtual 120	nqr:name	()Ljava/lang/String;
    //   265: invokestatic 124	java/lang/String:valueOf	(Ljava/lang/Object;)Ljava/lang/String;
    //   268: astore 11
    //   270: new 126	java/lang/StringBuilder
    //   273: dup
    //   274: aload 9
    //   276: invokestatic 124	java/lang/String:valueOf	(Ljava/lang/Object;)Ljava/lang/String;
    //   279: invokevirtual 130	java/lang/String:length	()I
    //   282: bipush 48
    //   284: iadd
    //   285: aload 10
    //   287: invokestatic 124	java/lang/String:valueOf	(Ljava/lang/Object;)Ljava/lang/String;
    //   290: invokevirtual 130	java/lang/String:length	()I
    //   293: iadd
    //   294: aload 11
    //   296: invokestatic 124	java/lang/String:valueOf	(Ljava/lang/Object;)Ljava/lang/String;
    //   299: invokevirtual 130	java/lang/String:length	()I
    //   302: iadd
    //   303: invokespecial 132	java/lang/StringBuilder:<init>	(I)V
    //   306: ldc -122
    //   308: invokevirtual 138	java/lang/StringBuilder:append	(Ljava/lang/String;)Ljava/lang/StringBuilder;
    //   311: aload 9
    //   313: invokevirtual 138	java/lang/StringBuilder:append	(Ljava/lang/String;)Ljava/lang/StringBuilder;
    //   316: ldc -116
    //   318: invokevirtual 138	java/lang/StringBuilder:append	(Ljava/lang/String;)Ljava/lang/StringBuilder;
    //   321: aload 10
    //   323: invokevirtual 138	java/lang/StringBuilder:append	(Ljava/lang/String;)Ljava/lang/StringBuilder;
    //   326: ldc -114
    //   328: invokevirtual 138	java/lang/StringBuilder:append	(Ljava/lang/String;)Ljava/lang/StringBuilder;
    //   331: aload 11
    //   333: invokevirtual 138	java/lang/StringBuilder:append	(Ljava/lang/String;)Ljava/lang/StringBuilder;
    //   336: pop
    //   337: aload 6
    //   339: getfield 146	ntp:k	Ljava/util/Map;
    //   342: aload 8
    //   344: getfield 109	nuk:a	Ljava/lang/String;
    //   347: aload 8
    //   349: invokeinterface 152 3 0
    //   354: pop
    //   355: aload 6
    //   357: getfield 156	ntp:q	Ljiq;
    //   360: aload 8
    //   362: getfield 158	nuk:j	I
    //   365: invokestatic 163	java/lang/Integer:valueOf	(I)Ljava/lang/Integer;
    //   368: aload 8
    //   370: invokeinterface 168 3 0
    //   375: pop
    //   376: aload 8
    //   378: invokevirtual 171	nuk:b	()Z
    //   381: ifeq -158 -> 223
    //   384: aload 8
    //   386: getfield 114	nuk:c	Lnqr;
    //   389: getstatic 173	nqr:a	Lnqr;
    //   392: if_acmpeq -169 -> 223
    //   395: aload 8
    //   397: getstatic 173	nqr:a	Lnqr;
    //   400: putfield 114	nuk:c	Lnqr;
    //   403: aload 8
    //   405: iconst_1
    //   406: putfield 176	nuk:d	I
    //   409: aload 6
    //   411: getfield 70	ntp:j	Lnug;
    //   414: aload 8
    //   416: invokevirtual 179	nug:b	(Lnuk;)V
    //   419: goto -196 -> 223
    //   422: astore_1
    //   423: aload 6
    //   425: getfield 26	ntp:p	Landroid/os/PowerManager$WakeLock;
    //   428: invokevirtual 66	android/os/PowerManager$WakeLock:release	()V
    //   431: aload_1
    //   432: athrow
    //   433: aload 6
    //   435: getfield 70	ntp:j	Lnug;
    //   438: aload 7
    //   440: invokevirtual 88	nug:a	(Ljava/lang/String;)Ljava/util/List;
    //   443: astore_1
    //   444: goto -228 -> 216
    //   447: new 181	java/util/HashMap
    //   450: dup
    //   451: aload 6
    //   453: getfield 146	ntp:k	Ljava/util/Map;
    //   456: invokeinterface 184 1 0
    //   461: invokespecial 185	java/util/HashMap:<init>	(I)V
    //   464: astore_1
    //   465: aload 6
    //   467: getfield 146	ntp:k	Ljava/util/Map;
    //   470: invokeinterface 189 1 0
    //   475: invokeinterface 192 1 0
    //   480: astore 8
    //   482: aload 8
    //   484: invokeinterface 100 1 0
    //   489: ifeq +35 -> 524
    //   492: aload 8
    //   494: invokeinterface 104 1 0
    //   499: checkcast 106	nuk
    //   502: astore 9
    //   504: aload_1
    //   505: aload 9
    //   507: getfield 109	nuk:a	Ljava/lang/String;
    //   510: aload 9
    //   512: invokevirtual 195	nuk:a	()Lnqq;
    //   515: invokeinterface 152 3 0
    //   520: pop
    //   521: goto -39 -> 482
    //   524: aload 6
    //   526: aload 7
    //   528: putfield 198	ntp:v	Ljava/lang/String;
    //   531: aload 6
    //   533: getfield 58	ntp:c	Lnuj;
    //   536: aload_1
    //   537: invokeinterface 201 2 0
    //   542: aload 6
    //   544: iconst_1
    //   545: putfield 204	ntp:t	Z
    //   548: aload 6
    //   550: invokevirtual 206	ntp:e	()V
    //   553: goto -453 -> 100
    //   556: aload_1
    //   557: getfield 209	android/os/Message:arg1	I
    //   560: ifeq +1744 -> 2304
    //   563: iconst_1
    //   564: istore_3
    //   565: aload 6
    //   567: getfield 212	ntp:s	Z
    //   570: iload_3
    //   571: if_icmpeq -471 -> 100
    //   574: aload 6
    //   576: iload_3
    //   577: putfield 212	ntp:s	Z
    //   580: aload 6
    //   582: invokevirtual 206	ntp:e	()V
    //   585: goto -485 -> 100
    //   588: aload_1
    //   589: getfield 209	android/os/Message:arg1	I
    //   592: ifeq +1717 -> 2309
    //   595: iconst_1
    //   596: istore_3
    //   597: aload 6
    //   599: getfield 215	ntp:r	Z
    //   602: iload_3
    //   603: if_icmpeq -503 -> 100
    //   606: aload 6
    //   608: iload_3
    //   609: putfield 215	ntp:r	Z
    //   612: aload 6
    //   614: invokevirtual 206	ntp:e	()V
    //   617: goto -517 -> 100
    //   620: aload 6
    //   622: invokevirtual 206	ntp:e	()V
    //   625: goto -525 -> 100
    //   628: aload 6
    //   630: getfield 204	ntp:t	Z
    //   633: invokestatic 220	jju:b	(Z)V
    //   636: aload_1
    //   637: getfield 77	android/os/Message:obj	Ljava/lang/Object;
    //   640: checkcast 106	nuk
    //   643: astore_1
    //   644: aload 6
    //   646: getfield 146	ntp:k	Ljava/util/Map;
    //   649: aload_1
    //   650: getfield 109	nuk:a	Ljava/lang/String;
    //   653: invokeinterface 224 2 0
    //   658: ifeq +129 -> 787
    //   661: aload 6
    //   663: getfield 146	ntp:k	Ljava/util/Map;
    //   666: aload_1
    //   667: getfield 109	nuk:a	Ljava/lang/String;
    //   670: invokeinterface 228 2 0
    //   675: checkcast 106	nuk
    //   678: astore 7
    //   680: aload 7
    //   682: invokevirtual 171	nuk:b	()Z
    //   685: ifne +79 -> 764
    //   688: aload 6
    //   690: getfield 70	ntp:j	Lnug;
    //   693: aload 7
    //   695: invokevirtual 230	nug:c	(Lnuk;)V
    //   698: aload 6
    //   700: getfield 70	ntp:j	Lnug;
    //   703: aload_1
    //   704: invokevirtual 232	nug:a	(Lnuk;)V
    //   707: aload 6
    //   709: getfield 146	ntp:k	Ljava/util/Map;
    //   712: aload_1
    //   713: getfield 109	nuk:a	Ljava/lang/String;
    //   716: aload_1
    //   717: invokeinterface 152 3 0
    //   722: pop
    //   723: aload 6
    //   725: getfield 156	ntp:q	Ljiq;
    //   728: aload_1
    //   729: getfield 158	nuk:j	I
    //   732: invokestatic 163	java/lang/Integer:valueOf	(I)Ljava/lang/Integer;
    //   735: aload_1
    //   736: invokeinterface 168 3 0
    //   741: pop
    //   742: aload 6
    //   744: getfield 58	ntp:c	Lnuj;
    //   747: aload_1
    //   748: invokevirtual 195	nuk:a	()Lnqq;
    //   751: invokeinterface 235 2 0
    //   756: aload 6
    //   758: invokevirtual 206	ntp:e	()V
    //   761: goto -661 -> 100
    //   764: aload 6
    //   766: getfield 239	ntp:o	Ljava/util/HashSet;
    //   769: aload_1
    //   770: getfield 109	nuk:a	Ljava/lang/String;
    //   773: invokevirtual 244	java/util/HashSet:remove	(Ljava/lang/Object;)Z
    //   776: ifeq -676 -> 100
    //   779: aload 6
    //   781: invokevirtual 206	ntp:e	()V
    //   784: goto -684 -> 100
    //   787: aload 6
    //   789: getfield 70	ntp:j	Lnug;
    //   792: aload_1
    //   793: invokevirtual 232	nug:a	(Lnuk;)V
    //   796: aload 6
    //   798: getfield 198	ntp:v	Ljava/lang/String;
    //   801: aload_1
    //   802: getfield 111	nuk:i	Ljava/lang/String;
    //   805: invokestatic 248	android/text/TextUtils:equals	(Ljava/lang/CharSequence;Ljava/lang/CharSequence;)Z
    //   808: ifeq -708 -> 100
    //   811: aload 6
    //   813: getfield 146	ntp:k	Ljava/util/Map;
    //   816: aload_1
    //   817: getfield 109	nuk:a	Ljava/lang/String;
    //   820: aload_1
    //   821: invokeinterface 152 3 0
    //   826: pop
    //   827: aload 6
    //   829: getfield 156	ntp:q	Ljiq;
    //   832: aload_1
    //   833: getfield 158	nuk:j	I
    //   836: invokestatic 163	java/lang/Integer:valueOf	(I)Ljava/lang/Integer;
    //   839: aload_1
    //   840: invokeinterface 168 3 0
    //   845: pop
    //   846: aload 6
    //   848: getfield 58	ntp:c	Lnuj;
    //   851: aload_1
    //   852: invokevirtual 195	nuk:a	()Lnqq;
    //   855: invokeinterface 235 2 0
    //   860: aload 6
    //   862: invokevirtual 206	ntp:e	()V
    //   865: goto -765 -> 100
    //   868: aload 6
    //   870: getfield 204	ntp:t	Z
    //   873: invokestatic 220	jju:b	(Z)V
    //   876: aload_1
    //   877: getfield 77	android/os/Message:obj	Ljava/lang/Object;
    //   880: checkcast 79	java/lang/String
    //   883: astore 7
    //   885: aload_1
    //   886: getfield 209	android/os/Message:arg1	I
    //   889: istore_2
    //   890: aload 6
    //   892: getfield 146	ntp:k	Ljava/util/Map;
    //   895: aload 7
    //   897: invokeinterface 224 2 0
    //   902: ifne +16 -> 918
    //   905: aload 6
    //   907: getfield 70	ntp:j	Lnug;
    //   910: aload 7
    //   912: invokevirtual 251	nug:b	(Ljava/lang/String;)V
    //   915: goto -815 -> 100
    //   918: aload 6
    //   920: getfield 254	ntp:l	Ljava/util/Map;
    //   923: aload 7
    //   925: invokeinterface 256 2 0
    //   930: checkcast 258	nue
    //   933: astore_1
    //   934: aload_1
    //   935: ifnull +26 -> 961
    //   938: aload_1
    //   939: iload_2
    //   940: invokeinterface 259 2 0
    //   945: aload 6
    //   947: getfield 262	ntp:m	Ljava/util/Map;
    //   950: aload_1
    //   951: invokeinterface 264 1 0
    //   956: aload_1
    //   957: invokestatic 269	jrq:b	(Ljava/util/Map;Ljava/lang/Object;Ljava/lang/Object;)Z
    //   960: pop
    //   961: aload 6
    //   963: getfield 272	ntp:n	Ljava/util/Map;
    //   966: astore_1
    //   967: aload_1
    //   968: monitorenter
    //   969: aload 6
    //   971: getfield 272	ntp:n	Ljava/util/Map;
    //   974: aload 7
    //   976: invokeinterface 256 2 0
    //   981: pop
    //   982: aload_1
    //   983: monitorexit
    //   984: aload 6
    //   986: getfield 239	ntp:o	Ljava/util/HashSet;
    //   989: aload 7
    //   991: invokevirtual 244	java/util/HashSet:remove	(Ljava/lang/Object;)Z
    //   994: pop
    //   995: aload 6
    //   997: getfield 146	ntp:k	Ljava/util/Map;
    //   1000: aload 7
    //   1002: invokeinterface 256 2 0
    //   1007: checkcast 106	nuk
    //   1010: astore_1
    //   1011: aload 6
    //   1013: getfield 156	ntp:q	Ljiq;
    //   1016: aload_1
    //   1017: invokeinterface 274 2 0
    //   1022: pop
    //   1023: aload_1
    //   1024: aload_1
    //   1025: getfield 176	nuk:d	I
    //   1028: iload_2
    //   1029: ior
    //   1030: putfield 176	nuk:d	I
    //   1033: aload 6
    //   1035: getfield 70	ntp:j	Lnug;
    //   1038: aload_1
    //   1039: invokevirtual 230	nug:c	(Lnuk;)V
    //   1042: aload_1
    //   1043: invokevirtual 195	nuk:a	()Lnqq;
    //   1046: astore_1
    //   1047: aload 6
    //   1049: getfield 58	ntp:c	Lnuj;
    //   1052: aload_1
    //   1053: invokeinterface 276 2 0
    //   1058: aload 6
    //   1060: invokevirtual 206	ntp:e	()V
    //   1063: goto -963 -> 100
    //   1066: astore 7
    //   1068: aload_1
    //   1069: monitorexit
    //   1070: aload 7
    //   1072: athrow
    //   1073: aload 6
    //   1075: getfield 146	ntp:k	Ljava/util/Map;
    //   1078: aload_1
    //   1079: getfield 77	android/os/Message:obj	Ljava/lang/Object;
    //   1082: invokeinterface 228 2 0
    //   1087: checkcast 106	nuk
    //   1090: astore 7
    //   1092: aload 7
    //   1094: ifnull -994 -> 100
    //   1097: aload 7
    //   1099: aload_1
    //   1100: getfield 209	android/os/Message:arg1	I
    //   1103: i2l
    //   1104: bipush 31
    //   1106: lshl
    //   1107: aload_1
    //   1108: getfield 279	android/os/Message:arg2	I
    //   1111: i2l
    //   1112: ladd
    //   1113: putfield 282	nuk:f	J
    //   1116: aload 6
    //   1118: getfield 70	ntp:j	Lnug;
    //   1121: aload 7
    //   1123: invokevirtual 179	nug:b	(Lnuk;)V
    //   1126: aload 6
    //   1128: getfield 58	ntp:c	Lnuj;
    //   1131: aload 7
    //   1133: invokevirtual 195	nuk:a	()Lnqq;
    //   1136: invokeinterface 284 2 0
    //   1141: goto -1041 -> 100
    //   1144: aload 6
    //   1146: getfield 146	ntp:k	Ljava/util/Map;
    //   1149: aload_1
    //   1150: getfield 77	android/os/Message:obj	Ljava/lang/Object;
    //   1153: invokeinterface 228 2 0
    //   1158: checkcast 106	nuk
    //   1161: astore 7
    //   1163: aload 7
    //   1165: ifnull -1065 -> 100
    //   1168: aload_1
    //   1169: getfield 209	android/os/Message:arg1	I
    //   1172: i2l
    //   1173: bipush 31
    //   1175: lshl
    //   1176: aload_1
    //   1177: getfield 279	android/os/Message:arg2	I
    //   1180: i2l
    //   1181: ladd
    //   1182: lstore 4
    //   1184: aload 7
    //   1186: getfield 286	nuk:e	J
    //   1189: lload 4
    //   1191: lcmp
    //   1192: ifeq +29 -> 1221
    //   1195: aload 6
    //   1197: getfield 272	ntp:n	Ljava/util/Map;
    //   1200: astore_1
    //   1201: aload_1
    //   1202: monitorenter
    //   1203: aload 6
    //   1205: getfield 272	ntp:n	Ljava/util/Map;
    //   1208: aload 7
    //   1210: getfield 109	nuk:a	Ljava/lang/String;
    //   1213: invokeinterface 256 2 0
    //   1218: pop
    //   1219: aload_1
    //   1220: monitorexit
    //   1221: aload 7
    //   1223: lload 4
    //   1225: putfield 286	nuk:e	J
    //   1228: aload 6
    //   1230: getfield 70	ntp:j	Lnug;
    //   1233: aload 7
    //   1235: invokevirtual 179	nug:b	(Lnuk;)V
    //   1238: aload 6
    //   1240: getfield 58	ntp:c	Lnuj;
    //   1243: aload 7
    //   1245: invokevirtual 195	nuk:a	()Lnqq;
    //   1248: invokeinterface 288 2 0
    //   1253: goto -1153 -> 100
    //   1256: astore 7
    //   1258: aload_1
    //   1259: monitorexit
    //   1260: aload 7
    //   1262: athrow
    //   1263: aload_1
    //   1264: getfield 77	android/os/Message:obj	Ljava/lang/Object;
    //   1267: checkcast 290	android/util/Pair
    //   1270: astore_1
    //   1271: aload_1
    //   1272: getfield 293	android/util/Pair:first	Ljava/lang/Object;
    //   1275: checkcast 79	java/lang/String
    //   1278: astore 7
    //   1280: aload 6
    //   1282: getfield 146	ntp:k	Ljava/util/Map;
    //   1285: aload 7
    //   1287: invokeinterface 228 2 0
    //   1292: checkcast 106	nuk
    //   1295: astore 8
    //   1297: aload 8
    //   1299: ifnull -1199 -> 100
    //   1302: aload_1
    //   1303: getfield 296	android/util/Pair:second	Ljava/lang/Object;
    //   1306: ifnull +136 -> 1442
    //   1309: aload_1
    //   1310: getfield 296	android/util/Pair:second	Ljava/lang/Object;
    //   1313: checkcast 298	nql
    //   1316: astore_1
    //   1317: aload 8
    //   1319: aload_1
    //   1320: putfield 301	nuk:h	Lnql;
    //   1323: aload 8
    //   1325: getstatic 302	nqr:c	Lnqr;
    //   1328: putfield 114	nuk:c	Lnqr;
    //   1331: aload 6
    //   1333: getfield 254	ntp:l	Ljava/util/Map;
    //   1336: aload 7
    //   1338: invokeinterface 256 2 0
    //   1343: checkcast 258	nue
    //   1346: astore_1
    //   1347: aload_1
    //   1348: ifnull +19 -> 1367
    //   1351: aload 6
    //   1353: getfield 262	ntp:m	Ljava/util/Map;
    //   1356: aload_1
    //   1357: invokeinterface 264 1 0
    //   1362: aload_1
    //   1363: invokestatic 269	jrq:b	(Ljava/util/Map;Ljava/lang/Object;Ljava/lang/Object;)Z
    //   1366: pop
    //   1367: aload 6
    //   1369: getfield 272	ntp:n	Ljava/util/Map;
    //   1372: astore_1
    //   1373: aload_1
    //   1374: monitorenter
    //   1375: aload 6
    //   1377: getfield 272	ntp:n	Ljava/util/Map;
    //   1380: aload 7
    //   1382: invokeinterface 256 2 0
    //   1387: pop
    //   1388: aload_1
    //   1389: monitorexit
    //   1390: aload 6
    //   1392: getfield 239	ntp:o	Ljava/util/HashSet;
    //   1395: aload 7
    //   1397: invokevirtual 244	java/util/HashSet:remove	(Ljava/lang/Object;)Z
    //   1400: pop
    //   1401: aload 6
    //   1403: getfield 305	ntp:w	Z
    //   1406: ifeq +54 -> 1460
    //   1409: aload 6
    //   1411: getfield 70	ntp:j	Lnug;
    //   1414: aload 8
    //   1416: invokevirtual 179	nug:b	(Lnuk;)V
    //   1419: aload 6
    //   1421: getfield 58	ntp:c	Lnuj;
    //   1424: aload 8
    //   1426: invokevirtual 195	nuk:a	()Lnqq;
    //   1429: invokeinterface 307 2 0
    //   1434: aload 6
    //   1436: invokevirtual 206	ntp:e	()V
    //   1439: goto -1339 -> 100
    //   1442: new 298	nql
    //   1445: dup
    //   1446: invokespecial 309	nql:<init>	()V
    //   1449: astore_1
    //   1450: goto -133 -> 1317
    //   1453: astore 7
    //   1455: aload_1
    //   1456: monitorexit
    //   1457: aload 7
    //   1459: athrow
    //   1460: aload 6
    //   1462: getfield 146	ntp:k	Ljava/util/Map;
    //   1465: aload 7
    //   1467: invokeinterface 256 2 0
    //   1472: pop
    //   1473: aload 6
    //   1475: getfield 156	ntp:q	Ljiq;
    //   1478: aload 8
    //   1480: invokeinterface 274 2 0
    //   1485: pop
    //   1486: aload 6
    //   1488: getfield 70	ntp:j	Lnug;
    //   1491: aload 8
    //   1493: invokevirtual 230	nug:c	(Lnuk;)V
    //   1496: goto -77 -> 1419
    //   1499: aload_1
    //   1500: getfield 77	android/os/Message:obj	Ljava/lang/Object;
    //   1503: checkcast 79	java/lang/String
    //   1506: astore 7
    //   1508: aload 6
    //   1510: getfield 146	ntp:k	Ljava/util/Map;
    //   1513: aload 7
    //   1515: invokeinterface 228 2 0
    //   1520: checkcast 106	nuk
    //   1523: ifnull -1423 -> 100
    //   1526: aload 7
    //   1528: invokestatic 124	java/lang/String:valueOf	(Ljava/lang/Object;)Ljava/lang/String;
    //   1531: astore_1
    //   1532: aload_1
    //   1533: invokevirtual 130	java/lang/String:length	()I
    //   1536: ifeq +125 -> 1661
    //   1539: ldc_w 311
    //   1542: aload_1
    //   1543: invokevirtual 315	java/lang/String:concat	(Ljava/lang/String;)Ljava/lang/String;
    //   1546: astore_1
    //   1547: aload_1
    //   1548: invokestatic 318	jst:b	(Ljava/lang/String;)V
    //   1551: aload 6
    //   1553: getfield 254	ntp:l	Ljava/util/Map;
    //   1556: aload 7
    //   1558: invokeinterface 256 2 0
    //   1563: checkcast 258	nue
    //   1566: astore_1
    //   1567: aload_1
    //   1568: ifnull +19 -> 1587
    //   1571: aload 6
    //   1573: getfield 262	ntp:m	Ljava/util/Map;
    //   1576: aload_1
    //   1577: invokeinterface 264 1 0
    //   1582: aload_1
    //   1583: invokestatic 269	jrq:b	(Ljava/util/Map;Ljava/lang/Object;Ljava/lang/Object;)Z
    //   1586: pop
    //   1587: aload 6
    //   1589: getfield 272	ntp:n	Ljava/util/Map;
    //   1592: astore_1
    //   1593: aload_1
    //   1594: monitorenter
    //   1595: aload 6
    //   1597: getfield 272	ntp:n	Ljava/util/Map;
    //   1600: aload 7
    //   1602: invokeinterface 228 2 0
    //   1607: checkcast 160	java/lang/Integer
    //   1610: astore 8
    //   1612: aload 8
    //   1614: ifnonnull +61 -> 1675
    //   1617: iconst_0
    //   1618: istore_2
    //   1619: iconst_1
    //   1620: iload_2
    //   1621: iconst_5
    //   1622: imul
    //   1623: ishl
    //   1624: getstatic 320	ntp:a	I
    //   1627: invokestatic 326	java/lang/Math:min	(II)I
    //   1630: istore_2
    //   1631: aload_1
    //   1632: monitorexit
    //   1633: aload 6
    //   1635: getfield 239	ntp:o	Ljava/util/HashSet;
    //   1638: aload 7
    //   1640: invokevirtual 329	java/util/HashSet:add	(Ljava/lang/Object;)Z
    //   1643: pop
    //   1644: aload 6
    //   1646: aload 7
    //   1648: iload_2
    //   1649: invokevirtual 332	ntp:b	(Ljava/lang/String;I)I
    //   1652: pop
    //   1653: aload 6
    //   1655: invokevirtual 206	ntp:e	()V
    //   1658: goto -1558 -> 100
    //   1661: new 79	java/lang/String
    //   1664: dup
    //   1665: ldc_w 311
    //   1668: invokespecial 334	java/lang/String:<init>	(Ljava/lang/String;)V
    //   1671: astore_1
    //   1672: goto -125 -> 1547
    //   1675: aload 8
    //   1677: invokevirtual 337	java/lang/Integer:intValue	()I
    //   1680: istore_2
    //   1681: goto -62 -> 1619
    //   1684: astore 7
    //   1686: aload_1
    //   1687: monitorexit
    //   1688: aload 7
    //   1690: athrow
    //   1691: aload_1
    //   1692: getfield 77	android/os/Message:obj	Ljava/lang/Object;
    //   1695: checkcast 79	java/lang/String
    //   1698: astore 7
    //   1700: aload 6
    //   1702: getfield 146	ntp:k	Ljava/util/Map;
    //   1705: aload 7
    //   1707: invokeinterface 228 2 0
    //   1712: checkcast 106	nuk
    //   1715: astore 8
    //   1717: aload 8
    //   1719: ifnull -1619 -> 100
    //   1722: aload 7
    //   1724: invokestatic 124	java/lang/String:valueOf	(Ljava/lang/Object;)Ljava/lang/String;
    //   1727: astore_1
    //   1728: aload_1
    //   1729: invokevirtual 130	java/lang/String:length	()I
    //   1732: ifeq +134 -> 1866
    //   1735: ldc_w 339
    //   1738: aload_1
    //   1739: invokevirtual 315	java/lang/String:concat	(Ljava/lang/String;)Ljava/lang/String;
    //   1742: astore_1
    //   1743: aload_1
    //   1744: invokestatic 341	jst:a	(Ljava/lang/String;)V
    //   1747: aload 8
    //   1749: getstatic 343	nqr:d	Lnqr;
    //   1752: putfield 114	nuk:c	Lnqr;
    //   1755: aload 6
    //   1757: getfield 305	ntp:w	Z
    //   1760: ifeq +120 -> 1880
    //   1763: aload 6
    //   1765: getfield 70	ntp:j	Lnug;
    //   1768: aload 8
    //   1770: invokevirtual 179	nug:b	(Lnuk;)V
    //   1773: aload 6
    //   1775: getfield 254	ntp:l	Ljava/util/Map;
    //   1778: aload 7
    //   1780: invokeinterface 256 2 0
    //   1785: checkcast 258	nue
    //   1788: astore_1
    //   1789: aload_1
    //   1790: ifnull +19 -> 1809
    //   1793: aload 6
    //   1795: getfield 262	ntp:m	Ljava/util/Map;
    //   1798: aload_1
    //   1799: invokeinterface 264 1 0
    //   1804: aload_1
    //   1805: invokestatic 269	jrq:b	(Ljava/util/Map;Ljava/lang/Object;Ljava/lang/Object;)Z
    //   1808: pop
    //   1809: aload 6
    //   1811: getfield 272	ntp:n	Ljava/util/Map;
    //   1814: astore_1
    //   1815: aload_1
    //   1816: monitorenter
    //   1817: aload 6
    //   1819: getfield 272	ntp:n	Ljava/util/Map;
    //   1822: aload 7
    //   1824: invokeinterface 256 2 0
    //   1829: pop
    //   1830: aload_1
    //   1831: monitorexit
    //   1832: aload 6
    //   1834: getfield 239	ntp:o	Ljava/util/HashSet;
    //   1837: aload 7
    //   1839: invokevirtual 244	java/util/HashSet:remove	(Ljava/lang/Object;)Z
    //   1842: pop
    //   1843: aload 6
    //   1845: getfield 58	ntp:c	Lnuj;
    //   1848: aload 8
    //   1850: invokevirtual 195	nuk:a	()Lnqq;
    //   1853: invokeinterface 307 2 0
    //   1858: aload 6
    //   1860: invokevirtual 206	ntp:e	()V
    //   1863: goto -1763 -> 100
    //   1866: new 79	java/lang/String
    //   1869: dup
    //   1870: ldc_w 339
    //   1873: invokespecial 334	java/lang/String:<init>	(Ljava/lang/String;)V
    //   1876: astore_1
    //   1877: goto -134 -> 1743
    //   1880: aload 6
    //   1882: getfield 146	ntp:k	Ljava/util/Map;
    //   1885: aload 7
    //   1887: invokeinterface 256 2 0
    //   1892: pop
    //   1893: aload 6
    //   1895: getfield 156	ntp:q	Ljiq;
    //   1898: aload 8
    //   1900: invokeinterface 274 2 0
    //   1905: pop
    //   1906: aload 6
    //   1908: getfield 70	ntp:j	Lnug;
    //   1911: aload 8
    //   1913: invokevirtual 230	nug:c	(Lnuk;)V
    //   1916: goto -143 -> 1773
    //   1919: astore 7
    //   1921: aload_1
    //   1922: monitorexit
    //   1923: aload 7
    //   1925: athrow
    //   1926: aload_1
    //   1927: getfield 77	android/os/Message:obj	Ljava/lang/Object;
    //   1930: checkcast 79	java/lang/String
    //   1933: astore_1
    //   1934: aload 6
    //   1936: getfield 239	ntp:o	Ljava/util/HashSet;
    //   1939: aload_1
    //   1940: invokevirtual 244	java/util/HashSet:remove	(Ljava/lang/Object;)Z
    //   1943: ifeq -1843 -> 100
    //   1946: aload 6
    //   1948: invokevirtual 206	ntp:e	()V
    //   1951: goto -1851 -> 100
    //   1954: aload 6
    //   1956: getfield 146	ntp:k	Ljava/util/Map;
    //   1959: invokeinterface 189 1 0
    //   1964: invokeinterface 192 1 0
    //   1969: astore_1
    //   1970: aload_1
    //   1971: invokeinterface 100 1 0
    //   1976: ifeq +146 -> 2122
    //   1979: aload_1
    //   1980: invokeinterface 104 1 0
    //   1985: checkcast 106	nuk
    //   1988: astore 7
    //   1990: aload 7
    //   1992: getfield 109	nuk:a	Ljava/lang/String;
    //   1995: astore 8
    //   1997: aload 7
    //   1999: getfield 111	nuk:i	Ljava/lang/String;
    //   2002: astore 9
    //   2004: aload 7
    //   2006: getfield 114	nuk:c	Lnqr;
    //   2009: invokevirtual 120	nqr:name	()Ljava/lang/String;
    //   2012: invokestatic 124	java/lang/String:valueOf	(Ljava/lang/Object;)Ljava/lang/String;
    //   2015: astore 10
    //   2017: new 126	java/lang/StringBuilder
    //   2020: dup
    //   2021: aload 8
    //   2023: invokestatic 124	java/lang/String:valueOf	(Ljava/lang/Object;)Ljava/lang/String;
    //   2026: invokevirtual 130	java/lang/String:length	()I
    //   2029: bipush 46
    //   2031: iadd
    //   2032: aload 9
    //   2034: invokestatic 124	java/lang/String:valueOf	(Ljava/lang/Object;)Ljava/lang/String;
    //   2037: invokevirtual 130	java/lang/String:length	()I
    //   2040: iadd
    //   2041: aload 10
    //   2043: invokestatic 124	java/lang/String:valueOf	(Ljava/lang/Object;)Ljava/lang/String;
    //   2046: invokevirtual 130	java/lang/String:length	()I
    //   2049: iadd
    //   2050: invokespecial 132	java/lang/StringBuilder:<init>	(I)V
    //   2053: ldc_w 345
    //   2056: invokevirtual 138	java/lang/StringBuilder:append	(Ljava/lang/String;)Ljava/lang/StringBuilder;
    //   2059: aload 8
    //   2061: invokevirtual 138	java/lang/StringBuilder:append	(Ljava/lang/String;)Ljava/lang/StringBuilder;
    //   2064: ldc -116
    //   2066: invokevirtual 138	java/lang/StringBuilder:append	(Ljava/lang/String;)Ljava/lang/StringBuilder;
    //   2069: aload 9
    //   2071: invokevirtual 138	java/lang/StringBuilder:append	(Ljava/lang/String;)Ljava/lang/StringBuilder;
    //   2074: ldc -114
    //   2076: invokevirtual 138	java/lang/StringBuilder:append	(Ljava/lang/String;)Ljava/lang/StringBuilder;
    //   2079: aload 10
    //   2081: invokevirtual 138	java/lang/StringBuilder:append	(Ljava/lang/String;)Ljava/lang/StringBuilder;
    //   2084: pop
    //   2085: aload 7
    //   2087: getfield 114	nuk:c	Lnqr;
    //   2090: getstatic 347	nqr:b	Lnqr;
    //   2093: invokevirtual 349	nqr:equals	(Ljava/lang/Object;)Z
    //   2096: ifeq +13 -> 2109
    //   2099: aload 6
    //   2101: aload 7
    //   2103: sipush 128
    //   2106: invokevirtual 352	ntp:a	(Lnuk;I)V
    //   2109: aload 6
    //   2111: getfield 70	ntp:j	Lnug;
    //   2114: aload 7
    //   2116: invokevirtual 179	nug:b	(Lnuk;)V
    //   2119: goto -149 -> 1970
    //   2122: aload 6
    //   2124: aconst_null
    //   2125: putfield 198	ntp:v	Ljava/lang/String;
    //   2128: aload 6
    //   2130: getfield 146	ntp:k	Ljava/util/Map;
    //   2133: invokeinterface 355 1 0
    //   2138: aload 6
    //   2140: getfield 156	ntp:q	Ljiq;
    //   2143: invokeinterface 356 1 0
    //   2148: aload 6
    //   2150: getfield 272	ntp:n	Ljava/util/Map;
    //   2153: astore_1
    //   2154: aload_1
    //   2155: monitorenter
    //   2156: aload 6
    //   2158: getfield 272	ntp:n	Ljava/util/Map;
    //   2161: invokeinterface 355 1 0
    //   2166: aload_1
    //   2167: monitorexit
    //   2168: aload 6
    //   2170: getfield 239	ntp:o	Ljava/util/HashSet;
    //   2173: invokevirtual 357	java/util/HashSet:clear	()V
    //   2176: goto -2076 -> 100
    //   2179: astore 7
    //   2181: aload_1
    //   2182: monitorexit
    //   2183: aload 7
    //   2185: athrow
    //   2186: aload 6
    //   2188: getfield 70	ntp:j	Lnug;
    //   2191: invokevirtual 74	nug:a	()V
    //   2194: aload 6
    //   2196: getfield 70	ntp:j	Lnug;
    //   2199: getfield 360	nug:a	Landroid/database/sqlite/SQLiteDatabase;
    //   2202: ldc_w 362
    //   2205: aconst_null
    //   2206: aconst_null
    //   2207: invokevirtual 368	android/database/sqlite/SQLiteDatabase:delete	(Ljava/lang/String;Ljava/lang/String;[Ljava/lang/String;)I
    //   2210: pop
    //   2211: aload 6
    //   2213: getfield 254	ntp:l	Ljava/util/Map;
    //   2216: invokeinterface 355 1 0
    //   2221: aload 6
    //   2223: getfield 262	ntp:m	Ljava/util/Map;
    //   2226: invokeinterface 355 1 0
    //   2231: aload 6
    //   2233: getfield 146	ntp:k	Ljava/util/Map;
    //   2236: invokeinterface 355 1 0
    //   2241: aload 6
    //   2243: getfield 156	ntp:q	Ljiq;
    //   2246: invokeinterface 356 1 0
    //   2251: aload 6
    //   2253: getfield 272	ntp:n	Ljava/util/Map;
    //   2256: astore_1
    //   2257: aload_1
    //   2258: monitorenter
    //   2259: aload 6
    //   2261: getfield 272	ntp:n	Ljava/util/Map;
    //   2264: invokeinterface 355 1 0
    //   2269: aload_1
    //   2270: monitorexit
    //   2271: aload 6
    //   2273: getfield 239	ntp:o	Ljava/util/HashSet;
    //   2276: invokevirtual 357	java/util/HashSet:clear	()V
    //   2279: goto -2179 -> 100
    //   2282: astore 7
    //   2284: aload_1
    //   2285: monitorexit
    //   2286: aload 7
    //   2288: athrow
    //   2289: iconst_0
    //   2290: istore_3
    //   2291: goto -2150 -> 141
    //   2294: astore 7
    //   2296: aload_1
    //   2297: monitorexit
    //   2298: aload 7
    //   2300: athrow
    //   2301: goto -2201 -> 100
    //   2304: iconst_0
    //   2305: istore_3
    //   2306: goto -1741 -> 565
    //   2309: iconst_0
    //   2310: istore_3
    //   2311: goto -1714 -> 597
    // Local variable table:
    //   start	length	slot	name	signature
    //   0	2314	0	this	ntq
    //   115	1566	2	i	int
    //   140	2171	3	bool	boolean
    //   1182	42	4	l	long
    //   4	2268	6	localntp	ntp
    //   196	805	7	localObject1	Object
    //   1066	5	7	localObject2	Object
    //   1090	154	7	localnuk1	nuk
    //   1256	5	7	localObject3	Object
    //   1278	118	7	str1	String
    //   1453	13	7	localObject4	Object
    //   1506	141	7	str2	String
    //   1684	5	7	localObject5	Object
    //   1698	188	7	str3	String
    //   1919	5	7	localObject6	Object
    //   1988	127	7	localnuk2	nuk
    //   2179	5	7	localObject7	Object
    //   2282	5	7	localObject8	Object
    //   2294	5	7	localObject9	Object
    //   241	1819	8	localObject10	Object
    //   248	1822	9	localObject11	Object
    //   255	1825	10	str4	String
    //   268	64	11	str5	String
    // Exception table:
    //   from	to	target	type
    //   22	100	422	finally
    //   100	108	422	finally
    //   181	216	422	finally
    //   216	223	422	finally
    //   223	419	422	finally
    //   433	444	422	finally
    //   447	482	422	finally
    //   482	521	422	finally
    //   524	553	422	finally
    //   556	563	422	finally
    //   565	585	422	finally
    //   588	595	422	finally
    //   597	617	422	finally
    //   620	625	422	finally
    //   628	761	422	finally
    //   764	784	422	finally
    //   787	865	422	finally
    //   868	915	422	finally
    //   918	934	422	finally
    //   938	961	422	finally
    //   961	969	422	finally
    //   984	1063	422	finally
    //   1070	1073	422	finally
    //   1073	1092	422	finally
    //   1097	1141	422	finally
    //   1144	1163	422	finally
    //   1168	1203	422	finally
    //   1221	1253	422	finally
    //   1260	1263	422	finally
    //   1263	1297	422	finally
    //   1302	1317	422	finally
    //   1317	1347	422	finally
    //   1351	1367	422	finally
    //   1367	1375	422	finally
    //   1390	1419	422	finally
    //   1419	1439	422	finally
    //   1442	1450	422	finally
    //   1457	1460	422	finally
    //   1460	1496	422	finally
    //   1499	1547	422	finally
    //   1547	1567	422	finally
    //   1571	1587	422	finally
    //   1587	1595	422	finally
    //   1633	1658	422	finally
    //   1661	1672	422	finally
    //   1688	1691	422	finally
    //   1691	1717	422	finally
    //   1722	1743	422	finally
    //   1743	1773	422	finally
    //   1773	1789	422	finally
    //   1793	1809	422	finally
    //   1809	1817	422	finally
    //   1832	1863	422	finally
    //   1866	1877	422	finally
    //   1880	1916	422	finally
    //   1923	1926	422	finally
    //   1926	1951	422	finally
    //   1954	1970	422	finally
    //   1970	2109	422	finally
    //   2109	2119	422	finally
    //   2122	2156	422	finally
    //   2168	2176	422	finally
    //   2183	2186	422	finally
    //   2186	2259	422	finally
    //   2271	2279	422	finally
    //   2286	2289	422	finally
    //   2298	2301	422	finally
    //   969	984	1066	finally
    //   1068	1070	1066	finally
    //   1203	1221	1256	finally
    //   1258	1260	1256	finally
    //   1375	1390	1453	finally
    //   1455	1457	1453	finally
    //   1595	1612	1684	finally
    //   1619	1633	1684	finally
    //   1675	1681	1684	finally
    //   1686	1688	1684	finally
    //   1817	1832	1919	finally
    //   1921	1923	1919	finally
    //   2156	2168	2179	finally
    //   2181	2183	2179	finally
    //   2259	2271	2282	finally
    //   2284	2286	2282	finally
    //   108	139	2294	finally
    //   141	170	2294	finally
    //   170	172	2294	finally
    //   2296	2298	2294	finally
  }
}

/* Location:
 * Qualified Name:     ntq
 * Java Class Version: 6 (50.0)
 * JD-Core Version:    0.7.1
 */