final class nwp
  implements Runnable
{
  nwp(nwo paramnwo) {}
  
  /* Error */
  public final void run()
  {
    // Byte code:
    //   0: aload_0
    //   1: getfield 12	nwp:a	Lnwo;
    //   4: astore_1
    //   5: aload_1
    //   6: getfield 29	nwo:e	Ljsg;
    //   9: invokevirtual 34	jsg:a	()Ljsf;
    //   12: astore_2
    //   13: aload_1
    //   14: getfield 37	nwo:a	Lhpo;
    //   17: aload_1
    //   18: getfield 41	nwo:b	Ljava/lang/String;
    //   21: invokeinterface 46 2 0
    //   26: astore_3
    //   27: aload_3
    //   28: invokestatic 52	android/text/TextUtils:isEmpty	(Ljava/lang/CharSequence;)Z
    //   31: ifne +34 -> 65
    //   34: aload_3
    //   35: aload_1
    //   36: invokevirtual 55	nwo:b	()Ljava/lang/String;
    //   39: invokevirtual 61	java/lang/String:equals	(Ljava/lang/Object;)Z
    //   42: pop
    //   43: aload_1
    //   44: getfield 65	nwo:c	Landroid/content/SharedPreferences;
    //   47: invokeinterface 71 1 0
    //   52: ldc 73
    //   54: aload_3
    //   55: invokeinterface 79 3 0
    //   60: invokeinterface 82 1 0
    //   65: aload_1
    //   66: invokevirtual 55	nwo:b	()Ljava/lang/String;
    //   69: astore 4
    //   71: aload 4
    //   73: invokestatic 52	android/text/TextUtils:isEmpty	(Ljava/lang/CharSequence;)Z
    //   76: ifne +111 -> 187
    //   79: aload_1
    //   80: getfield 29	nwo:e	Ljsg;
    //   83: invokevirtual 34	jsg:a	()Ljsf;
    //   86: astore_2
    //   87: aload_1
    //   88: getfield 86	nwo:d	Lkzg;
    //   91: astore_3
    //   92: new 88	kzh
    //   95: dup
    //   96: aload_3
    //   97: getfield 94	kzg:g	Lmdl;
    //   100: aload_3
    //   101: getfield 98	kzg:h	Lnpx;
    //   104: invokeinterface 103 1 0
    //   109: invokespecial 106	kzh:<init>	(Lmdl;Lnpv;)V
    //   112: astore_3
    //   113: aload_3
    //   114: getfield 109	kzh:a	Lrll;
    //   117: aload 4
    //   119: invokevirtual 113	java/lang/String:getBytes	()[B
    //   122: putfield 118	rll:a	[B
    //   125: aload_1
    //   126: getfield 122	nwo:f	Llzg;
    //   129: invokeinterface 127 1 0
    //   134: ifne +11 -> 145
    //   137: aload_3
    //   138: getfield 109	kzh:a	Lrll;
    //   141: iconst_1
    //   142: putfield 130	rll:b	Z
    //   145: aload_1
    //   146: getfield 133	nwo:g	Landroid/content/Context;
    //   149: invokestatic 138	nwt:a	(Landroid/content/Context;)Ljava/lang/Boolean;
    //   152: astore 4
    //   154: aload 4
    //   156: ifnull +19 -> 175
    //   159: aload 4
    //   161: invokevirtual 143	java/lang/Boolean:booleanValue	()Z
    //   164: ifne +11 -> 175
    //   167: aload_3
    //   168: getfield 109	kzh:a	Lrll;
    //   171: iconst_1
    //   172: putfield 145	rll:c	Z
    //   175: aload_1
    //   176: getfield 86	nwo:d	Lkzg;
    //   179: getfield 148	kzg:a	Lmfe;
    //   182: aload_3
    //   183: invokevirtual 153	mfe:b	(Lmcf;)Ltps;
    //   186: pop
    //   187: return
    //   188: astore_3
    //   189: ldc -101
    //   191: aload_3
    //   192: invokestatic 160	jst:b	(Ljava/lang/String;Ljava/lang/Throwable;)V
    //   195: aload_2
    //   196: invokevirtual 163	jsf:a	()Z
    //   199: ifne -186 -> 13
    //   202: goto -137 -> 65
    //   205: astore 4
    //   207: ldc -91
    //   209: aload 4
    //   211: invokestatic 160	jst:b	(Ljava/lang/String;Ljava/lang/Throwable;)V
    //   214: aload_2
    //   215: invokevirtual 163	jsf:a	()Z
    //   218: ifeq -31 -> 187
    //   221: goto -46 -> 175
    //   224: astore 4
    //   226: ldc -91
    //   228: aload 4
    //   230: invokestatic 160	jst:b	(Ljava/lang/String;Ljava/lang/Throwable;)V
    //   233: aload_2
    //   234: invokevirtual 163	jsf:a	()Z
    //   237: ifne -62 -> 175
    //   240: return
    // Local variable table:
    //   start	length	slot	name	signature
    //   0	241	0	this	nwp
    //   4	172	1	localnwo	nwo
    //   12	222	2	localjsf	jsf
    //   26	157	3	localObject1	Object
    //   188	4	3	localIOException	java.io.IOException
    //   69	91	4	localObject2	Object
    //   205	5	4	localmfq	mfq
    //   224	5	4	localIllegalStateException	IllegalStateException
    // Exception table:
    //   from	to	target	type
    //   13	65	188	java/io/IOException
    //   175	187	205	mfq
    //   175	187	224	java/lang/IllegalStateException
  }
}

/* Location:
 * Qualified Name:     nwp
 * Java Class Version: 6 (50.0)
 * JD-Core Version:    0.7.1
 */