public final class oep
{
  private static String[] b = { "video_id", "key_set_id", "pssh_data", "mimetype", "license_server_url", "last_updated_timestamp", "last_update_gls_authorized_formats", "last_update_sdk_version", "last_update_attempt_timestamp", "last_update_attempt_http_code", "last_update_attempt_gls_code" };
  final jih a;
  
  public oep(jih paramjih)
  {
    a = ((jih)jju.a(paramjih));
  }
  
  /* Error */
  public final oat a(String paramString)
  {
    // Byte code:
    //   0: aconst_null
    //   1: astore 5
    //   3: aload_0
    //   4: getfield 50	oep:a	Ljih;
    //   7: invokeinterface 55 1 0
    //   12: ldc 57
    //   14: getstatic 36	oep:b	[Ljava/lang/String;
    //   17: ldc 59
    //   19: iconst_1
    //   20: anewarray 12	java/lang/String
    //   23: dup
    //   24: iconst_0
    //   25: aload_1
    //   26: aastore
    //   27: aconst_null
    //   28: aconst_null
    //   29: aconst_null
    //   30: aconst_null
    //   31: invokevirtual 65	android/database/sqlite/SQLiteDatabase:query	(Ljava/lang/String;[Ljava/lang/String;Ljava/lang/String;[Ljava/lang/String;Ljava/lang/String;Ljava/lang/String;Ljava/lang/String;Ljava/lang/String;)Landroid/database/Cursor;
    //   34: astore 6
    //   36: aload 6
    //   38: invokeinterface 71 1 0
    //   43: pop
    //   44: aload 6
    //   46: invokeinterface 74 1 0
    //   51: istore_2
    //   52: iload_2
    //   53: ifeq +15 -> 68
    //   56: aload 5
    //   58: astore_1
    //   59: aload 6
    //   61: invokeinterface 77 1 0
    //   66: aload_1
    //   67: areturn
    //   68: aload 6
    //   70: aload 6
    //   72: ldc 14
    //   74: invokeinterface 81 2 0
    //   79: invokeinterface 85 2 0
    //   84: astore_1
    //   85: aload 6
    //   87: aload 6
    //   89: ldc 16
    //   91: invokeinterface 81 2 0
    //   96: invokeinterface 89 2 0
    //   101: astore 5
    //   103: aload 6
    //   105: aload 6
    //   107: ldc 20
    //   109: invokeinterface 81 2 0
    //   114: invokeinterface 85 2 0
    //   119: astore 7
    //   121: aload 6
    //   123: aload 6
    //   125: ldc 18
    //   127: invokeinterface 81 2 0
    //   132: invokeinterface 89 2 0
    //   137: astore 8
    //   139: aload 6
    //   141: aload 6
    //   143: ldc 22
    //   145: invokeinterface 81 2 0
    //   150: invokeinterface 85 2 0
    //   155: astore 9
    //   157: aload 6
    //   159: aload 6
    //   161: ldc 24
    //   163: invokeinterface 81 2 0
    //   168: invokeinterface 93 2 0
    //   173: lstore_3
    //   174: aload 6
    //   176: aload 6
    //   178: ldc 26
    //   180: invokeinterface 81 2 0
    //   185: invokeinterface 85 2 0
    //   190: astore 10
    //   192: aload 6
    //   194: aload 6
    //   196: ldc 28
    //   198: invokeinterface 81 2 0
    //   203: invokeinterface 97 2 0
    //   208: pop
    //   209: aload 6
    //   211: aload 6
    //   213: ldc 30
    //   215: invokeinterface 81 2 0
    //   220: invokeinterface 93 2 0
    //   225: pop2
    //   226: aload 6
    //   228: aload 6
    //   230: ldc 32
    //   232: invokeinterface 81 2 0
    //   237: invokeinterface 97 2 0
    //   242: pop
    //   243: aload 6
    //   245: aload 6
    //   247: ldc 34
    //   249: invokeinterface 81 2 0
    //   254: invokeinterface 97 2 0
    //   259: pop
    //   260: new 99	oat
    //   263: dup
    //   264: aload_1
    //   265: aload 5
    //   267: aload 7
    //   269: aload 8
    //   271: aload 9
    //   273: lload_3
    //   274: aload 10
    //   276: iconst_0
    //   277: invokespecial 102	oat:<init>	(Ljava/lang/String;[BLjava/lang/String;[BLjava/lang/String;JLjava/lang/String;B)V
    //   280: astore_1
    //   281: goto -222 -> 59
    //   284: astore_1
    //   285: aload 6
    //   287: invokeinterface 77 1 0
    //   292: aload_1
    //   293: athrow
    // Local variable table:
    //   start	length	slot	name	signature
    //   0	294	0	this	oep
    //   0	294	1	paramString	String
    //   51	2	2	bool	boolean
    //   173	101	3	l	long
    //   1	265	5	arrayOfByte1	byte[]
    //   34	252	6	localCursor	android.database.Cursor
    //   119	149	7	str1	String
    //   137	133	8	arrayOfByte2	byte[]
    //   155	117	9	str2	String
    //   190	85	10	str3	String
    // Exception table:
    //   from	to	target	type
    //   36	52	284	finally
    //   68	281	284	finally
  }
}

/* Location:
 * Qualified Name:     oep
 * Java Class Version: 6 (50.0)
 * JD-Core Version:    0.7.1
 */