import java.util.concurrent.ExecutorService;
import java.util.concurrent.Executors;

final class piu
  implements Runnable
{
  private final ExecutorService a = Executors.newFixedThreadPool(2);
  
  public piu(pit parampit) {}
  
  /* Error */
  public final void run()
  {
    // Byte code:
    //   0: invokestatic 37	java/lang/Thread:interrupted	()Z
    //   3: ifne +68 -> 71
    //   6: aload_0
    //   7: getfield 14	piu:b	Lpit;
    //   10: getfield 43	pit:e	Ljava/net/ServerSocket;
    //   13: invokevirtual 49	java/net/ServerSocket:accept	()Ljava/net/Socket;
    //   16: astore_1
    //   17: aload_0
    //   18: getfield 25	piu:a	Ljava/util/concurrent/ExecutorService;
    //   21: new 51	piv
    //   24: dup
    //   25: aload_0
    //   26: getfield 14	piu:b	Lpit;
    //   29: aload_1
    //   30: invokespecial 54	piv:<init>	(Lpit;Ljava/net/Socket;)V
    //   33: invokeinterface 60 2 0
    //   38: goto -38 -> 0
    //   41: astore_1
    //   42: aload_1
    //   43: invokevirtual 64	java/net/SocketException:getMessage	()Ljava/lang/String;
    //   46: ldc 66
    //   48: invokevirtual 72	java/lang/String:equals	(Ljava/lang/Object;)Z
    //   51: ifne +9 -> 60
    //   54: ldc 74
    //   56: aload_1
    //   57: invokestatic 79	jst:a	(Ljava/lang/String;Ljava/lang/Throwable;)V
    //   60: aload_0
    //   61: getfield 25	piu:a	Ljava/util/concurrent/ExecutorService;
    //   64: invokeinterface 83 1 0
    //   69: pop
    //   70: return
    //   71: aload_0
    //   72: getfield 25	piu:a	Ljava/util/concurrent/ExecutorService;
    //   75: invokeinterface 83 1 0
    //   80: pop
    //   81: return
    //   82: astore_1
    //   83: ldc 85
    //   85: aload_1
    //   86: invokestatic 79	jst:a	(Ljava/lang/String;Ljava/lang/Throwable;)V
    //   89: aload_0
    //   90: getfield 25	piu:a	Ljava/util/concurrent/ExecutorService;
    //   93: invokeinterface 83 1 0
    //   98: pop
    //   99: return
    //   100: astore_1
    //   101: aload_0
    //   102: getfield 25	piu:a	Ljava/util/concurrent/ExecutorService;
    //   105: invokeinterface 83 1 0
    //   110: pop
    //   111: aload_1
    //   112: athrow
    // Local variable table:
    //   start	length	slot	name	signature
    //   0	113	0	this	piu
    //   16	14	1	localSocket	java.net.Socket
    //   41	16	1	localSocketException	java.net.SocketException
    //   82	4	1	localIOException	java.io.IOException
    //   100	12	1	localObject	Object
    // Exception table:
    //   from	to	target	type
    //   0	38	41	java/net/SocketException
    //   0	38	82	java/io/IOException
    //   0	38	100	finally
    //   42	60	100	finally
    //   83	89	100	finally
  }
}

/* Location:
 * Qualified Name:     piu
 * Java Class Version: 6 (50.0)
 * JD-Core Version:    0.7.1
 */