import java.net.Socket;

final class piv
  implements Runnable
{
  private final Socket a;
  
  public piv(pit parampit, Socket paramSocket)
  {
    a = paramSocket;
  }
  
  /* Error */
  public final void run()
  {
    // Byte code:
    //   0: new 29	org/apache/http/impl/DefaultHttpServerConnection
    //   3: dup
    //   4: invokespecial 30	org/apache/http/impl/DefaultHttpServerConnection:<init>	()V
    //   7: astore_2
    //   8: aload_2
    //   9: aload_0
    //   10: getfield 19	piv:a	Ljava/net/Socket;
    //   13: aload_0
    //   14: getfield 14	piv:b	Lpit;
    //   17: getfield 35	pit:a	Lorg/apache/http/params/HttpParams;
    //   20: invokevirtual 39	org/apache/http/impl/DefaultHttpServerConnection:bind	(Ljava/net/Socket;Lorg/apache/http/params/HttpParams;)V
    //   23: new 41	org/apache/http/protocol/BasicHttpContext
    //   26: dup
    //   27: invokespecial 42	org/apache/http/protocol/BasicHttpContext:<init>	()V
    //   30: astore_3
    //   31: invokestatic 48	java/lang/Thread:interrupted	()Z
    //   34: ifne +31 -> 65
    //   37: aload_2
    //   38: invokevirtual 51	org/apache/http/impl/DefaultHttpServerConnection:isOpen	()Z
    //   41: ifeq +24 -> 65
    //   44: aload_0
    //   45: getfield 14	piv:b	Lpit;
    //   48: getfield 54	pit:b	Lorg/apache/http/protocol/HttpService;
    //   51: aload_2
    //   52: aload_3
    //   53: invokevirtual 60	org/apache/http/protocol/HttpService:handleRequest	(Lorg/apache/http/HttpServerConnection;Lorg/apache/http/protocol/HttpContext;)V
    //   56: goto -25 -> 31
    //   59: astore_3
    //   60: aload_2
    //   61: invokevirtual 63	org/apache/http/impl/DefaultHttpServerConnection:shutdown	()V
    //   64: return
    //   65: aload_2
    //   66: invokevirtual 63	org/apache/http/impl/DefaultHttpServerConnection:shutdown	()V
    //   69: return
    //   70: astore_2
    //   71: return
    //   72: astore_3
    //   73: aload_3
    //   74: instanceof 65
    //   77: ifeq +36 -> 113
    //   80: aload_3
    //   81: invokevirtual 69	java/io/IOException:getMessage	()Ljava/lang/String;
    //   84: ldc 71
    //   86: invokevirtual 77	java/lang/String:contains	(Ljava/lang/CharSequence;)Z
    //   89: ifne +17 -> 106
    //   92: aload_3
    //   93: invokevirtual 69	java/io/IOException:getMessage	()Ljava/lang/String;
    //   96: ldc 79
    //   98: invokevirtual 77	java/lang/String:contains	(Ljava/lang/CharSequence;)Z
    //   101: istore_1
    //   102: iload_1
    //   103: ifeq +10 -> 113
    //   106: aload_2
    //   107: invokevirtual 63	org/apache/http/impl/DefaultHttpServerConnection:shutdown	()V
    //   110: return
    //   111: astore_2
    //   112: return
    //   113: ldc 81
    //   115: aload_3
    //   116: invokestatic 86	jst:a	(Ljava/lang/String;Ljava/lang/Throwable;)V
    //   119: goto -13 -> 106
    //   122: astore_3
    //   123: aload_2
    //   124: invokevirtual 63	org/apache/http/impl/DefaultHttpServerConnection:shutdown	()V
    //   127: aload_3
    //   128: athrow
    //   129: astore_3
    //   130: ldc 88
    //   132: aload_3
    //   133: invokestatic 86	jst:a	(Ljava/lang/String;Ljava/lang/Throwable;)V
    //   136: aload_2
    //   137: invokevirtual 63	org/apache/http/impl/DefaultHttpServerConnection:shutdown	()V
    //   140: return
    //   141: astore_2
    //   142: return
    //   143: astore_2
    //   144: return
    //   145: astore_2
    //   146: goto -19 -> 127
    // Local variable table:
    //   start	length	slot	name	signature
    //   0	149	0	this	piv
    //   101	2	1	bool	boolean
    //   7	59	2	localDefaultHttpServerConnection	org.apache.http.impl.DefaultHttpServerConnection
    //   70	37	2	localIOException1	java.io.IOException
    //   111	26	2	localIOException2	java.io.IOException
    //   141	1	2	localIOException3	java.io.IOException
    //   143	1	2	localIOException4	java.io.IOException
    //   145	1	2	localIOException5	java.io.IOException
    //   30	23	3	localBasicHttpContext	org.apache.http.protocol.BasicHttpContext
    //   59	1	3	localConnectionClosedException	org.apache.http.ConnectionClosedException
    //   72	44	3	localIOException6	java.io.IOException
    //   122	6	3	localObject	Object
    //   129	4	3	localHttpException	org.apache.http.HttpException
    // Exception table:
    //   from	to	target	type
    //   8	31	59	org/apache/http/ConnectionClosedException
    //   31	56	59	org/apache/http/ConnectionClosedException
    //   65	69	70	java/io/IOException
    //   8	31	72	java/io/IOException
    //   31	56	72	java/io/IOException
    //   106	110	111	java/io/IOException
    //   8	31	122	finally
    //   31	56	122	finally
    //   73	102	122	finally
    //   113	119	122	finally
    //   130	136	122	finally
    //   8	31	129	org/apache/http/HttpException
    //   31	56	129	org/apache/http/HttpException
    //   136	140	141	java/io/IOException
    //   60	64	143	java/io/IOException
    //   123	127	145	java/io/IOException
  }
}

/* Location:
 * Qualified Name:     piv
 * Java Class Version: 6 (50.0)
 * JD-Core Version:    0.7.1
 */