final class ply
  implements Runnable
{
  ply(plx paramplx) {}
  
  /* Error */
  public final void run()
  {
    // Byte code:
    //   0: invokestatic 28	jju:b	()V
    //   3: aload_0
    //   4: getfield 12	ply:a	Lplx;
    //   7: astore 17
    //   9: sipush 4096
    //   12: newarray <illegal type>
    //   14: astore 18
    //   16: ldc2_w 29
    //   19: lstore_3
    //   20: getstatic 35	fca:a	Lfca;
    //   23: bipush 10
    //   25: invokevirtual 38	fca:b	(I)V
    //   28: iconst_0
    //   29: istore_1
    //   30: aload 17
    //   32: getfield 44	plx:d	Z
    //   35: ifne +310 -> 345
    //   38: iload_1
    //   39: ifne +306 -> 345
    //   42: lload_3
    //   43: lstore 7
    //   45: getstatic 35	fca:a	Lfca;
    //   48: invokevirtual 46	fca:a	()V
    //   51: lload_3
    //   52: lstore 7
    //   54: aload 17
    //   56: getfield 50	plx:c	Lfbi;
    //   59: getfield 55	fbi:d	J
    //   62: lstore 13
    //   64: lload 13
    //   66: lstore 15
    //   68: lload_3
    //   69: lstore 9
    //   71: lload_3
    //   72: lstore 11
    //   74: lload_3
    //   75: lstore 5
    //   77: aload 17
    //   79: getfield 58	plx:b	Lfbg;
    //   82: aload 17
    //   84: getfield 50	plx:c	Lfbi;
    //   87: invokeinterface 63 2 0
    //   92: lstore_3
    //   93: lload 13
    //   95: lstore 7
    //   97: lload 7
    //   99: lstore 15
    //   101: lload_3
    //   102: lstore 9
    //   104: lload_3
    //   105: lstore 11
    //   107: lload_3
    //   108: lstore 5
    //   110: aload 17
    //   112: getfield 44	plx:d	Z
    //   115: ifne +47 -> 162
    //   118: lload 7
    //   120: lstore 15
    //   122: lload_3
    //   123: lstore 9
    //   125: lload_3
    //   126: lstore 11
    //   128: lload_3
    //   129: lstore 5
    //   131: aload 17
    //   133: getfield 58	plx:b	Lfbg;
    //   136: aload 18
    //   138: iconst_0
    //   139: sipush 4096
    //   142: invokeinterface 66 4 0
    //   147: istore_2
    //   148: iload_2
    //   149: iflt +13 -> 162
    //   152: lload 7
    //   154: iload_2
    //   155: i2l
    //   156: ladd
    //   157: lstore 7
    //   159: goto -62 -> 97
    //   162: aload 17
    //   164: getfield 58	plx:b	Lfbg;
    //   167: invokeinterface 67 1 0
    //   172: iconst_1
    //   173: istore_1
    //   174: goto -144 -> 30
    //   177: astore 19
    //   179: iconst_1
    //   180: istore_1
    //   181: goto -151 -> 30
    //   184: astore 19
    //   186: lload 9
    //   188: lstore 5
    //   190: lload 15
    //   192: aload 17
    //   194: getfield 50	plx:c	Lfbi;
    //   197: getfield 55	fbi:d	J
    //   200: lcmp
    //   201: ifle +39 -> 240
    //   204: lload 9
    //   206: lstore 5
    //   208: aload 17
    //   210: new 52	fbi
    //   213: dup
    //   214: aload 17
    //   216: getfield 50	plx:c	Lfbi;
    //   219: getfield 70	fbi:a	Landroid/net/Uri;
    //   222: lload 15
    //   224: lload 9
    //   226: aload 17
    //   228: getfield 50	plx:c	Lfbi;
    //   231: getfield 74	fbi:f	Ljava/lang/String;
    //   234: invokespecial 77	fbi:<init>	(Landroid/net/Uri;JJLjava/lang/String;)V
    //   237: putfield 50	plx:c	Lfbi;
    //   240: lload 9
    //   242: lstore 7
    //   244: aload 17
    //   246: getfield 58	plx:b	Lfbg;
    //   249: invokeinterface 67 1 0
    //   254: lload 9
    //   256: lstore_3
    //   257: goto -227 -> 30
    //   260: astore 19
    //   262: lload 9
    //   264: lstore_3
    //   265: goto -235 -> 30
    //   268: astore 19
    //   270: lload 11
    //   272: lstore 5
    //   274: aload 17
    //   276: iconst_1
    //   277: putfield 44	plx:d	Z
    //   280: lload 11
    //   282: lstore 7
    //   284: aload 17
    //   286: getfield 58	plx:b	Lfbg;
    //   289: invokeinterface 67 1 0
    //   294: lload 11
    //   296: lstore_3
    //   297: goto -267 -> 30
    //   300: astore 19
    //   302: lload 11
    //   304: lstore_3
    //   305: goto -275 -> 30
    //   308: astore 19
    //   310: lload 5
    //   312: lstore 7
    //   314: aload 17
    //   316: getfield 58	plx:b	Lfbg;
    //   319: invokeinterface 67 1 0
    //   324: lload 5
    //   326: lstore 7
    //   328: aload 19
    //   330: athrow
    //   331: astore 19
    //   333: lload 7
    //   335: lstore_3
    //   336: aload 17
    //   338: iconst_1
    //   339: putfield 44	plx:d	Z
    //   342: goto -312 -> 30
    //   345: getstatic 35	fca:a	Lfca;
    //   348: bipush 10
    //   350: invokevirtual 79	fca:c	(I)V
    //   353: return
    //   354: astore 19
    //   356: iconst_1
    //   357: istore_1
    //   358: goto -22 -> 336
    //   361: astore 20
    //   363: goto -39 -> 324
    // Local variable table:
    //   start	length	slot	name	signature
    //   0	366	0	this	ply
    //   29	329	1	i	int
    //   147	8	2	j	int
    //   19	317	3	l1	long
    //   75	250	5	l2	long
    //   43	291	7	l3	long
    //   69	194	9	l4	long
    //   72	231	11	l5	long
    //   62	32	13	l6	long
    //   66	157	15	l7	long
    //   7	330	17	localplx	plx
    //   14	123	18	arrayOfByte	byte[]
    //   177	1	19	localIOException1	java.io.IOException
    //   184	1	19	localfcb	fcb
    //   260	1	19	localIOException2	java.io.IOException
    //   268	1	19	localIOException3	java.io.IOException
    //   300	1	19	localIOException4	java.io.IOException
    //   308	21	19	localObject	Object
    //   331	1	19	localInterruptedException1	InterruptedException
    //   354	1	19	localInterruptedException2	InterruptedException
    //   361	1	20	localIOException5	java.io.IOException
    // Exception table:
    //   from	to	target	type
    //   162	172	177	java/io/IOException
    //   77	93	184	fcb
    //   110	118	184	fcb
    //   131	148	184	fcb
    //   244	254	260	java/io/IOException
    //   77	93	268	java/io/IOException
    //   110	118	268	java/io/IOException
    //   131	148	268	java/io/IOException
    //   284	294	300	java/io/IOException
    //   77	93	308	finally
    //   110	118	308	finally
    //   131	148	308	finally
    //   190	204	308	finally
    //   208	240	308	finally
    //   274	280	308	finally
    //   45	51	331	java/lang/InterruptedException
    //   54	64	331	java/lang/InterruptedException
    //   244	254	331	java/lang/InterruptedException
    //   284	294	331	java/lang/InterruptedException
    //   314	324	331	java/lang/InterruptedException
    //   328	331	331	java/lang/InterruptedException
    //   162	172	354	java/lang/InterruptedException
    //   314	324	361	java/io/IOException
  }
}

/* Location:
 * Qualified Name:     ply
 * Java Class Version: 6 (50.0)
 * JD-Core Version:    0.7.1
 */